Workbook

Sheet Summary
A2: Rebaseline
A3: Scope | B3: Category | C3: Emission Source | D3: Included (Y/N) | E3: H1 FY25 tCO2e Market | F3: H1 FY25 tCO2e Location | G3: FY24 tCO2e Market | H3: FY 24 tCO2e Location | I3: FY 23 tCO2e Market | J3: FY 23 tCO2e Location | K3: FY22 tCO2e Market | L3: FY22 tCO2e Location
A4: 1 | B4: - | C4: Stationary combustion | D4: Y | E4: 1336.419 | F4: 1336.419 | G4: 1736.4822 | H4: 1736.4822 | I4: 1355.3302 | J4: 1355.3302 | K4: 1408.5867 | L4: 1408.5867
A5: 1 | B5: - | C5: Company vehicles | D5: Y | E5: 936.81688 | F5: 936.81688 | G5: 2120.6171 | H5: 2120.6171 | I5: 1917.79 | J5: 1917.79 | K5: 825.72832 | L5: 825.72832
A6: 1 | B6: - | C6: Fugitive emissions | D6: N | E6: 0 | F6: 0 | G6: 0 | H6: 0 | I6: 0 | J6: 0 | K6: 0 | L6: 0
A7: 1 | B7: - | C7: Refrigerants | D7: Y | E7: 6.410566 | F7: 6.410566 | G7: 18.080351 | H7: 18.080351 | I7: 1.5385 | J7: 1.5385 | K7: 1.6471 | L7: 1.6471
A8: 1 | C8: Scope 1 Extrapolation | D8: N | E8: 0 | F8: 0 | G8: 0 | H8: 0 | I8: 328.95312 | J8: 328.95312 | K8: 1333.8499 | L8: 1333.8499
A9: 2 | B9: - | C9: Electricity usage | D9: Y | E9: 3365.3929 | F9: 2757.2595 | G9: 3667.1893 | H9: 5692.5506 | I9: 5272.9372 | J9: 4764.3818 | K9: 4520.5869 | L9: 4279.6023
A10: 2 | B10: - | C10: Heating | D10: Y | E10: 53.952952 | F10: 53.952952 | G10: 139.6637 | H10: 139.6637 | I10: 53.555697 | J10: 53.555697 | K10: 0 | L10: 0
A11: 2 | B11: - | C11: Cooling | D11: N | E11: 0 | F11: 0 | G11: 0 | H11: 0 | I11: 0 | J11: 0 | K11: 0 | L11: 0
A12: 2 | C12: Scope 2 Extrapolation | D12: N | E12: 0 | F12: 0 | G12: 0 | H12: 0 | I12: 1023.98 | J12: 1250.3916 | K12: 1329.2162 | L12: 1338.9516
A13: 3 | B13: 1 | C13: Purchased goods and services | D13: Y | E13: 79412.202 | F13: 79412.202 | G13: 176935.41 | H13: 176935.41 | I13: 191705.14 | J13: 191705.14 | K13: 154151.64 | L13: 154151.64
A14: 3 | B14: 2 | C14: Capital goods | D14: Y | E14: 1553.4786 | F14: 1553.4786 | G14: 6973.2078 | H14: 6973.2078 | I14: 8445.8016 | J14: 8445.8016 | K14: 5971.4072 | L14: 5971.4072
A15: 3 | B15: 3 | C15: Fuel and energy related activities | D15: Y | E15: 1173.4546 | F15: 1173.4546 | G15: 2303.622 | H15: 2303.622 | I15: 2299.2305 | J15: 2299.2305 | K15: 2160.8372 | L15: 2160.8372
A16: 3 | B16: 4 | C16: Upstream transportation and distribution | D16: Y | E16: 22660.451 | F16: 22660.451 | G16: 38920.499 | H16: 38920.499 | I16: 41103.353 | J16: 41103.353 | K16: 42362.16 | L16: 42362.16
A17: 3 | B17: 5 | C17: Waste generated in operations | D17: Y | E17: 398.82427 | F17: 398.82427 | G17: 625.92365 | H17: 625.92365 | I17: 721.55269 | J17: 721.55269 | K17: 464.9853 | L17: 464.9853
A18: 3 | B18: 6 | C18: Business travel | D18: Y | E18: 3171.7995 | F18: 3171.7995 | G18: 6734.7391 | H18: 6734.7391 | I18: 6514.0033 | J18: 6514.0033 | K18: 5708.7733 | L18: 5708.7733
A19: 3 | B19: 7 | C19: Employee commuting | D19: Y | E19: 3379.0944 | F19: 3379.0944 | G19: 6955.0292 | H19: 6955.0292 | I19: 6123.1243 | J19: 6123.1243 | K19: 5166.7426 | L19: 5166.7426
A20: 3 | B20: 8 | C20: Upstream leased assets | D20: Y | E20: 1436.436 | F20: 1436.436 | G20: 2922.6612 | H20: 2922.6612 | I20: 2800.9244 | J20: 2800.9244 | K20: 2691.9199 | L20: 2691.9199
A21: 3 | B21: 9 | C21: Downstream transportation and distribution | D21: N | E21: 0 | F21: 0 | G21: 0 | H21: 0 | I21: 0 | J21: 0 | K21: 0 | L21: 0
A22: 3 | B22: 10 | C22: Processing of sold products | D22: N | E22: 0 | F22: 0 | G22: 0 | H22: 0 | I22: 0 | J22: 0 | K22: 0 | L22: 0
A23: 3 | B23: 11 | C23: Use of sold products | D23: Y | E23: 861.11502 | F23: 861.11502 | G23: 1722.23 | H23: 1722.23 | I23: 1722.23 | J23: 1722.23 | K23: 1722.23 | L23: 1722.23
A24: 3 | B24: 12 | C24: End of life treatment of sold products | D24: Y | E24: 20.476429 | F24: 20.476429 | G24: 41.126644 | H24: 41.126644 | I24: 93.945599 | J24: 93.945599 | K24: 95.631573 | L24: 95.631573
... A27: 3 | B27: 15 | C27: Investments | D27: N | E27: 0 | F27: 0 | G27: 0 | H27: 0 | I27: 0 | J27: 0 | K27: 0 | L27: 0
A28: Total | E28: 119766.32 | F28: 119158.19 | G28: 251816.48 | H28: 253841.84 | I28: 271483.39 | J28: 271201.24 | K28: 229915.94 | L28: 229684.69
A31: Original
A32: Scope | B32: Category | C32: Emission Source | E32: H1 FY25 tCO2e Market | F32: H1 FY25 tCO2e Location | G32: FY24 tCO2e Market | H32: FY 24 tCO2e Location | I32: FY23 Original Market | J32: FY23 Original Location | K32: FY22 Original | L32: FY22 Original
A33: 1 | B33: - | C33: Total Scope 1 | E33: N/A | F33: N/A | G33: N/A | H33: N/A | I33: 3351 | J33: 3351 | K33: 2443 | L33: 2443
A34: 2 | B34: - | C34: Total Scope 2 | E34: N/A | F34: N/A | G34: N/A | H34: N/A | I34: 5585.1041 | J34: 4953.291 | K34: 4806 | L34: 4557.67
A35: 3 | B35: 1 | C35: Purchased goods and services | E35: N/A | F35: N/A | G35: N/A | H35: N/A | I35: 81338 | J35: 81338 | K35: 101436 | L35: 101436
A36: 3 | B36: 2 | C36: Capital goods | E36: N/A | F36: N/A | G36: N/A | H36: N/A | I36: 14113 | J36: 14113 | K36: 12431 | L36: 12431
A37: 3 | B37: 3 | C37: Fuel and energy related activities | E37: N/A | F37: N/A | G37: N/A | H37: N/A | I37: 1915 | J37: 1915 | K37: 1705 | L37: 1705
A38: 3 | B38: 4 | C38: Upstream transportation and distribution | E38: N/A | F38: N/A | G38: N/A | H38: N/A | I38: 38779 | J38: 38779 | K38: 67200 | L38: 67200
A39: 3 | B39: 5 | C39: Waste generated in operations | E39: N/A | F39: N/A | G39: N/A | H39: N/A | I39: 1816 | J39: 1816 | K39: 1499 | L39: 1499
A40: 3 | B40: 6 | C40: Business travel | E40: N/A | F40: N/A | G40: N/A | H40: N/A | I40: 7253 | J40: 7253 | K40: 8889 | L40: 8889
A41: 3 | B41: 7 | C41: Employee commuting | E41: N/A | F41: N/A | G41: N/A | H41: N/A | I41: 3258 | J41: 3258 | K41: 2972 | L41: 2972
A42: 3 | B42: 8 | C42: Upstream leased assets | E42: N/A | F42: N/A | G42: N/A | H42: N/A | I42: 0 | J42: 0 | K42: 0 | L42: 0
A43: 3 | B43: 9 | C43: Downstream transportation and distribution | E43: N/A | F43: N/A | G43: N/A | H43: N/A | I43: 0 | J43: 0 | K43: 0 | L43: 0
A44: 3 | B44: 10 | C44: Processing of sold products | E44: N/A | F44: N/A | G44: N/A | H44: N/A | I44: 0 | J44: 0 | K44: 0 | L44: 0
A45: 3 | B45: 11 | C45: Use of sold products | E45: N/A | F45: N/A | G45: N/A | H45: N/A | I45: 2173 | J45: 2173 | K45: 1567 | L45: 1567
A46: 3 | B46: 12 | C46: End of life treatment of sold products | E46: N/A | F46: N/A | G46: N/A | H46: N/A | I46: 1466 | J46: 1466 | K46: 1184 | L46: 1184
... A49: 3 | B49: 15 | C49: Investments | E49: N/A | F49: N/A | G49: N/A | H49: N/A | I49: 0 | J49: 0 | K49: 0 | L49: 0
A50: Total | E50: N/A | F50: N/A | G50: N/A | H50: N/A | I50: 161047.1 | J50: 160415.29 | K50: 206132 | L50: 205883.67
A53: Notes
A54: Scope 3 Emissions Category 1 (Purchased Goods and Services): The increase in FY23 compared to FY24 is primarily due to the assumptions made regarding the extrapolation of emissions from newly acquired sites. There are some big spenders acquired mid-way through the FY23 year (and thus have partial coverage in the original raw FY23 dataset). To make up for this partial coverage, these are extrapolated backwards based on the FY24 (full coverage) dataset. Similarly, some sites are acquired mid-way through FY24. Because these sites do not have a full FY24 dataset from which to extrapolate backwards, we conduct a 'full year extrapolation' on the available FY24 data to make up for the FY24 data gaps. We then take this 'full year extrapolation' and backtrack it to the prior years. FY24 calculations represent actual (in some cases partial) emissions throughout the year, without these 'full year' extrapolations for the entities acquired midway through the year. This, by comparison, slightly inflates the FY23 and FY22 footprints.
A56: Overall Trends: The emissions calculations for both Scope 1 and 2 are influenced by the timing of acquisitions and the availability of complete data. While Scope 2 data seems to be available in proportion to the months of the year for which a site operates under diploma ownership (example: 6 months of ownership entails a proportionate 6 months of Scope 2 data), there seems to be a trend whereby Scope 1 data is disproportionately lacking for the year in which an entity is acquired (6 months of diploma ownership will not necessarily entail 6 months of Scope 1 data). This ensures that a given site reports disproportionately larger Scope 1 emissions the year after it is acquired (when Scope 1 data availability is actually representative of the year). This may explain why FY25 H1 Scope 1 emissions are slighly larger than may be expected (sites acquired midway through FY24 will now, in FY25, be reporting full Scope 1 data)

Sheet FY25 H1
B2: FY25 H1 Footprint by Entity Code
B4: Scope | C4: Category | D4: Upstream/Downstream | E4: Emission Source | F4: Diploma Total | G4: G3010 | H4: L2050 | I4: L3015 | J4: S7030 | K4: S7040 | L4: S7060 | M4: S7090 | N4: S6040 | O4: G5020 | P4: L2010 | Q4: L2020 | R4: L2030 | S4: L2040 | T4: S2050 | U4: S2060 | V4: C5520 | W4: S4030 | X4: G5040 | Y4: L2500 | Z4: L7010 | AA4: S4010 | AB4: C2540 | AC4: C4050 | AD4: C2090 | AE4: C2091 | AF4: c4030 | AG4: C7010 | AH4: G3045 | AI4: L2090 | AJ4: L5010 | AK4: S1030 | AL4: G5025 | AM4: HoIntSealsE | AN4: S1040 | AO4: S2210 | AP4: S7020 | AQ4: L2060 | AR4: L3025 | AS4: L7030 | AT4: S1010 | AU4: L2510 | AV4: L2700 | AW4: L7020 | AX4: S4020 | AY4: S6020 | AZ4: S6070 | BA4: C2530 | BB4: c1010 | BC4: C1040 | BD4: C2040 | BE4: C2041 | BF4: C2042 | BG4: C2043 | BH4: C2080 | BI4: C2551 | BJ4: C2552 | BK4: C2553 | BL4: C2554 | BM4: C2555 | BN4: C3510 | BO4: C5010 | BP4: C6020 | BQ4: C8010 | BR4: C9010 | BS4: C9050 | BT4: G2010 | BU4: G3015 | BV4: G3020 | BW4: G3041 | BX4: G4010 | BY4: G5005 | BZ4: G5010 | CA4: HoControls | CB4: HoGrp | CC4: HoIntSeals | CD4: HoLS | CE4: L5020 | CF4: R1100 | CG4: R1120 | CH4: R1140 | CI4: R1170 | CJ4: R1180 | CK4: R1190 | CL4: R1210 | CM4: R1220 | CN4: R1230 | CO4: R1240 | CP4: R2100 | CQ4: R2110 | CR4: R2120 | CS4: R2130 | CT4: R2150 | CU4: R2160 | CV4: R2170 | CW4: R2180 | CX4: R2190 | CY4: R2210 | CZ4: R2220 | DA4: R3100 | DB4: R4100 | DC4: R4110 | DD4: R4120 | DE4: R4130 | DF4: R4140 | DG4: R4150 | DH4: R4160 | DI4: R5100 | DJ4: R5110 | DK4: R5120 | DL4: R9100 | DM4: S3010 | DN4: S3030 | DO4: S4040 | DP4: S4050 | DQ4: S9010 | DR4: C1510 | DS4: C1520 | DT4: C1530 | DU4: C2045 | DV4: C2046 | DW4: C2571 | DX4: C2572 | DY4: C2573 | DZ4: C2574 | EA4: C2575 | EB4: C2576 | EC4: C2577 | ED4: C2578 | EE4: C3040 | EF4: C4510 | EG4: C5510 | EH4: C8500 | EI4: G3025 | EJ4: G5015 | EK4: HoControlsU | EL4: HoDHI | EM4: HoLSU | EN4: HoNaSeals | EO4: LCAoem | EP4: S1020 | EQ4: S2010 | ER4: S2025 | ES4: S2026 | ET4: S2310 | EU4: S8010 | EV4: S8020 | EW4: S8030 | EX4: C1050 | EY4: HoLSC | EZ4: HoLSDCHI
B5: 1 | C5: - | D5: Internal | E5: All Scope 1 | F5: 2279.6464 | G5: 0 | H5: 0 | I5: 0 | J5: 25.806701 | K5: 0 | L5: 175.90592 | M5: 0 | N5: 0 | O5: 0 | P5: 0 | Q5: 46.336699 | R5: 0 | S5: 76.030307 | T5: 1.4696002 | U5: 0.23063682 | V5: 0 | W5: 0 | X5: 0 | Y5: 42.559856 | Z5: 0 | AA5: 7.3909522 | AB5: 0 | AC5: 0 | AD5: 7.9714473 | AE5: 0 | AF5: 50.750081 | AG5: 11.380546 | AH5: 0 | AI5: 64.843237 | AJ5: 201.5569 | AK5: 14.553844 | AL5: 0 | AM5: 0 | AN5: 0 | AO5: 11.157766 | AP5: 1.5031316 | AQ5: 0 | AR5: 4.1364233 | AS5: 0 | AT5: 41.353875 | AU5: 0 | AV5: 28.08464 | AW5: 0 | AX5: 3.7431061 | AY5: 0 | AZ5: 0 | BA5: 0 | BB5: 7.619832 | BC5: 0 | BD5: 26.69327 | BE5: 0 | BF5: 0 | BG5: 0 | BH5: 22.008105 | BI5: 0 | BJ5: 0 | BK5: 0 | BL5: 0 | BM5: 0 | BN5: 0 | BO5: 0 | BP5: 0 | BQ5: 4.9854103 | BR5: 0 | BS5: 0.91236779 | BT5: 0 | BU5: 0 | BV5: 0 | BW5: 0 | BX5: 0 | BY5: 0 | BZ5: 0 | CA5: 0 | CB5: 0 | CC5: 0 | CD5: 0 | CE5: 9.7825271 | CF5: 0 | CG5: 0 | CH5: 0 | CI5: 55.849459 | CJ5: 34.147693 | CK5: 103.71384 | CL5: 5.7413865 | CM5: 31.453037 | CN5: 15.159629 | CO5: 0 | CP5: 0 | CQ5: 2.0459856 | CR5: 11.430266 | CS5: 38.537621 | CT5: 23.835095 | CU5: 1.3946236 | CV5: 12.399258 | CW5: 3.9694787 | CX5: 6.956272 | CY5: 15.502602 | CZ5: 0 | DA5: 0 | DB5: 3.8866804 | DC5: 0.080546 | DD5: 6.051055 | DE5: 5.7849274 | DF5: 0 | DG5: 4.0654471 | DH5: 40.613292 | DI5: 12.163572 | DJ5: 0 | DK5: 0 | DL5: 0 | DM5: 16.774316 | DN5: 0.0065844 | DO5: 9.7101472 | DP5: 7.1483213 | DQ5: 9.5661576 | DR5: 18.311 | DS5: 63.81345 | DT5: 28.77252 | DU5: 5.9943694 | DV5: 0 | DW5: 0 | DX5: 0 | DY5: 0 | DZ5: 0 | EA5: 0 | EB5: 0 | EC5: 0 | ED5: 0 | EE5: 0.1558623 | EF5: 0.14248282 | EG5: 42.710661 | EH5: 530.59684 | EI5: 0 | EJ5: 0 | EK5: 0 | EL5: 0 | EM5: 0 | EN5: 0 | EO5: 59.473027 | EP5: 0 | EQ5: 0 | ER5: 55.401292 | ES5: 0 | ET5: 23.28176 | EU5: 35.683393 | EV5: 16.779744 | EW5: 28.806907 | EX5: 2.9686576 | EY5: 0 | EZ5: 0
B6: 2 | C6: - | D6: Internal | E6: All Scope 2 MB | F6: 3419.3459 | G6: 0 | H6: 0 | I6: 82.74892 | J6: 21.247164 | K6: 0 | L6: 39.518139 | M6: 3.594078 | N6: 0 | O6: 0 | P6: 0 | Q6: 10.463418 | R6: 0 | S6: 18.042299 | T6: 5.4453685 | U6: 7.3970685 | V6: 0 | W6: 0 | X6: 0 | Y6: 37.550504 | Z6: 0 | AA6: 89.982221 | AB6: 0 | AC6: 0 | AD6: 15.549907 | AE6: 0 | AF6: 31.360778 | AG6: 13.723513 | AH6: 0 | AI6: 49.014704 | AJ6: 35.981301 | AK6: 4.6702774 | AL6: 0 | AM6: 0 | AN6: 0 | AO6: 2.6228953 | AP6: 0.58796805 | AQ6: 0 | AR6: 1.57833 | AS6: 0 | AT6: 258.20286 | AU6: 0.43670195 | AV6: 3.1972041 | AW6: 0 | AX6: 0.31476658 | AY6: 0 | AZ6: 0 | BA6: 1.6992072 | BB6: 23.187357 | BC6: 0 | BD6: 30.464343 | BE6: 0 | BF6: 0 | BG6: 0 | BH6: 68.546084 | BI6: 0 | BJ6: 0 | BK6: 0 | BL6: 0 | BM6: 0 | BN6: 0 | BO6: 0 | BP6: 0 | BQ6: 127.43111 | BR6: 0 | BS6: 3.8361542 | BT6: 17.159709 | BU6: 0 | BV6: 0 | BW6: 0 | BX6: 0 | BY6: 0 | BZ6: 0 | CA6: 0 | CB6: 0 | CC6: 0 | CD6: 0 | CE6: 0 | CF6: 0 | CG6: 0 | CH6: 0 | CI6: 13.142131 | CJ6: 11.172027 | CK6: 18.527964 | CL6: 3.6740536 | CM6: 15.742265 | CN6: 3.7117483 | CO6: 0 | CP6: 0 | CQ6: 14.261551 | CR6: 8.5153792 | CS6: 4.0319489 | CT6: 41.489791 | CU6: 22.20582 | CV6: 18.066944 | CW6: 3.7495789 | CX6: 3.4566676 | CY6: 3.6611004 | CZ6: 8.2893278 | DA6: 0 | DB6: 6.0801038 | DC6: 5.917536 | DD6: 2.5911626 | DE6: 4.1758139 | DF6: 3.4230473 | DG6: 2.5911626 | DH6: 38.451264 | DI6: 0.87223988 | DJ6: 0 | DK6: 0 | DL6: 0 | DM6: 40.410725 | DN6: 5.8058697 | DO6: 4.1864174 | DP6: 13.943293 | DQ6: 27.181631 | DR6: 10.584665 | DS6: 68.652687 | DT6: 25.413465 | DU6: 14.814487 | DV6: 0 | DW6: 0 | DX6: 0 | DY6: 0 | DZ6: 0 | EA6: 0 | EB6: 0 | EC6: 0 | ED6: 0 | EE6: 2.9510964 | EF6: 7.6743586 | EG6: 16.694828 | EH6: 1396.8837 | EI6: 0 | EJ6: 0 | EK6: 0 | EL6: 0 | EM6: 0 | EN6: 0 | EO6: 87.208839 | EP6: 0 | EQ6: 0 | ER6: 181.30726 | ES6: 0 | ET6: 24.920081 | EU6: 166.89445 | EV6: 33.490128 | EW6: 24.766915 | EX6: 2.2059897 | EY6: 0 | EZ6: 0
B7: 2 | D7: Internal | E7: All Scope 2 LB | F7: 2811.2125 | G7: 0 | H7: 0 | I7: 82.74892 | J7: 21.247164 | K7: 0 | L7: 39.518139 | M7: 3.594078 | N7: 0 | O7: 0 | P7: 0 | Q7: 10.463418 | R7: 0 | S7: 18.042299 | T7: 5.4453685 | U7: 7.3970685 | V7: 0 | W7: 0 | X7: 0 | Y7: 19.209577 | Z7: 0 | AA7: 48.075632 | AB7: 0 | AC7: 0 | AD7: 7.92288 | AE7: 0 | AF7: 15.978725 | AG7: 6.9923084 | AH7: 0 | AI7: 31.917672 | AJ7: 23.430507 | AK7: 2.918424 | AL7: 0 | AM7: 0 | AN7: 0 | AO7: 1.3982087 | AP7: 0.9250271 | AQ7: 0 | AR7: 1.57833 | AS7: 0 | AT7: 156.50452 | AU7: 0.07232 | AV7: 0.5294728 | AW7: 0 | AX7: 0.0521269 | AY7: 0 | AZ7: 0 | BA7: 1.6992072 | BB7: 12.360678 | BC7: 0 | BD7: 16.405335 | BE7: 0 | BF7: 0 | BG7: 0 | BH7: 36.540432 | BI7: 0 | BJ7: 0 | BK7: 0 | BL7: 0 | BM7: 0 | BN7: 0 | BO7: 0 | BP7: 0 | BQ7: 67.930765 | BR7: 0 | BS7: 2.0449707 | BT7: 9.147469 | BU7: 0 | BV7: 0 | BW7: 0 | BX7: 0 | BY7: 0 | BZ7: 0 | CA7: 0 | CB7: 0 | CC7: 0 | CD7: 0 | CE7: 0 | CF7: 0 | CG7: 0 | CH7: 0 | CI7: 7.0057852 | CJ7: 5.9555655 | CK7: 9.8768565 | CL7: 1.9585584 | CM7: 8.3918607 | CN7: 1.9786526 | CO7: 0 | CP7: 0 | CQ7: 7.602524 | CR7: 4.5393642 | CS7: 2.1493446 | CT7: 22.117309 | CU7: 11.837442 | CV7: 9.6310964 | CW7: 1.9988193 | CX7: 1.8426746 | CY7: 1.9516533 | CZ7: 4.4188611 | DA7: 0 | DB7: 4.5661552 | DC7: 3.1545103 | DD7: 1.3812927 | DE7: 2.226036 | DF7: 1.8247524 | DG7: 1.3812927 | DH7: 20.497536 | DI7: 0.46497219 | DJ7: 0 | DK7: 0 | DL7: 0 | DM7: 21.542082 | DN7: 3.0949834 | DO7: 2.2316884 | DP7: 7.4328672 | DQ7: 14.489939 | DR7: 10.157874 | DS7: 69.155729 | DT7: 24.388751 | DU7: 13.31924 | DV7: 0 | DW7: 0 | DX7: 0 | DY7: 0 | DZ7: 0 | EA7: 0 | EB7: 0 | EC7: 0 | ED7: 0 | EE7: 2.8954448 | EF7: 7.5296358 | EG7: 16.379998 | EH7: 1338.3144 | EI7: 0 | EJ7: 0 | EK7: 0 | EL7: 0 | EM7: 0 | EN7: 0 | EO7: 82.766135 | EP7: 0 | EQ7: 0 | ER7: 180.48855 | ES7: 0 | ET7: 23.085985 | EU7: 146.11416 | EV7: 31.505278 | EW7: 24.299862 | EX7: 1.1759653 | EY7: 0 | EZ7: 0
B8: 3 | C8: 1 | D8: Upstream | E8: Purchased goods and services | F8: 79412.202 | G8: 0.8714176 | H8: 856.14424 | I8: 3821.8502 | J8: 579.21649 | K8: -10.316326 | L8: 1300.3478 | M8: 1.0266621 | N8: 65.285235 | O8: 0 | P8: 0 | Q8: 3997.1941 | R8: 0 | S8: 6118.23 | T8: 488.13135 | U8: 624.93159 | V8: 0.08261794 | W8: 5.6895635 | X8: -57.844455 | Y8: 1896.4305 | Z8: 0 | AA8: 428.88079 | AB8: 0.94715867 | AC8: 44.064847 | AD8: 223.29358 | AE8: 137.40119 | AF8: 1081.619 | AG8: 1013.8449 | AH8: 2.0094466 | AI8: 2512.0444 | AJ8: 3261.5603 | AK8: 533.77045 | AL8: 116.19232 | AM8: 0 | AN8: 1.4749546 | AO8: 55.359166 | AP8: 37.597377 | AQ8: 187.01237 | AR8: 527.69624 | AS8: 96.077573 | AT8: 2183.6991 | AU8: 160.05744 | AV8: 1439.2633 | AW8: 0 | AX8: 260.95036 | AY8: 126.97579 | AZ8: 0 | BA8: 1.8249574 | BB8: 815.84054 | BC8: 0.51109164 | BD8: 1115.5842 | BE8: -20.528104 | BF8: 14.795069 | BG8: 67.25831 | BH8: 1507.5798 | BI8: 2.7195855 | BJ8: 2.9037274 | BK8: 0.23713409 | BL8: 1.7489347 | BM8: 1.3062513 | BN8: 390.03145 | BO8: 0 | BP8: 0 | BQ8: 456.32756 | BR8: 1080.5179 | BS8: 420.11868 | BT8: 824.76992 | BU8: 0 | BV8: 0.058196984 | BW8: 0.014047579 | BX8: 0.63661389 | BY8: 0 | BZ8: 2464.2223 | CA8: 434.5339 | CB8: -6.7118907 | CC8: 0.14039964 | CD8: -177.68309 | CE8: 349.52311 | CF8: 0 | CG8: 0 | CH8: 0 | CI8: 159.91902 | CJ8: 198.78936 | CK8: 513.94834 | CL8: 123.57497 | CM8: 180.38769 | CN8: 95.057645 | CO8: 0 | CP8: 0 | CQ8: 404.63974 | CR8: 380.44395 | CS8: 202.46653 | CT8: 566.3848 | CU8: -10.88296 | CV8: 108.61213 | CW8: 191.86251 | CX8: 84.370373 | CY8: 372.99607 | CZ8: 31.188651 | DA8: 185.95134 | DB8: 67.194707 | DC8: 19.025834 | DD8: 34.661021 | DE8: 82.387647 | DF8: 60.955967 | DG8: 45.583356 | DH8: 708.63212 | DI8: 75.305366 | DJ8: 0.32175688 | DK8: 0 | DL8: 0 | DM8: 271.80162 | DN8: 33.421592 | DO8: 31.286948 | DP8: 213.5727 | DQ8: 88.396998 | DR8: 362.72184 | DS8: 658.8293 | DT8: 225.22525 | DU8: 1002.4266 | DV8: 648.47658 | DW8: 18.125283 | DX8: 2.5763415 | DY8: 15.550886 | DZ8: 2.6657774 | EA8: 6.7363405 | EB8: 30.884277 | EC8: 7.4851807 | ED8: 1.3582148 | EE8: 227.25597 | EF8: 639.65908 | EG8: 2765.466 | EH8: 392.91741 | EI8: 83.099458 | EJ8: 220.26643 | EK8: -160.92179 | EL8: -53.591333 | EM8: 0 | EN8: 0 | EO8: 8811.9978 | EP8: 92.813925 | EQ8: 94.853924 | ER8: 6029.4358 | ES8: 2.9591872 | ET8: 511.62 | EU8: 6671.2089 | EV8: 106.37958 | EW8: 539.12357 | EX8: 0 | EY8: 21.677391 | EZ8: 43.31756
B9: 3 | C9: 2 | D9: Upstream | E9: Capital goods | F9: 1553.4786 | G9: 0 | H9: 0 | I9: 111.91095 | J9: 14.8567 | K9: 0 | L9: 51.229986 | M9: 0 | N9: 0 | O9: 0 | P9: 0 | Q9: 45.66365 | R9: 0 | S9: 507.487 | T9: -0.33072708 | U9: 4.4703406 | V9: 0 | W9: 0 | X9: 0 | Y9: 31.186604 | Z9: 0 | AA9: 6.5154163 | AB9: 0 | AC9: 1.6114739 | AD9: 3.2767352 | AE9: 0 | AF9: 5.1408419 | AG9: 4.1112729 | AH9: 0 | AI9: 12.383367 | AJ9: 78.79598 | AK9: 0.30146601 | AL9: 0 | AM9: 0 | AN9: 0 | AO9: 0 | AP9: 0 | AQ9: 0 | AR9: 41.698919 | AS9: 0 | AT9: 83.331494 | AU9: 0 | AV9: 29.445283 | AW9: 0 | AX9: 0 | AY9: 0.83262591 | AZ9: 0 | BA9: 0 | BB9: 16.777976 | BC9: 0 | BD9: 1.2276385 | BE9: 0 | BF9: 0 | BG9: 0 | BH9: 17.723702 | BI9: 0 | BJ9: 0 | BK9: 0 | BL9: 0 | BM9: 0 | BN9: 0 | BO9: 0 | BP9: 0 | BQ9: 0 | BR9: 56.484665 | BS9: 0 | BT9: 11.93266 | BU9: 0 | BV9: 0 | BW9: 0 | BX9: 0 | BY9: 0 | BZ9: 0 | CA9: 0 | CB9: 0 | CC9: 0 | CD9: 0 | CE9: 0 | CF9: 0 | CG9: 0 | CH9: 0 | CI9: 0 | CJ9: 0.53402641 | CK9: 33.439403 | CL9: 0.85017718 | CM9: 1.9097377 | CN9: 2.0979692 | CO9: 0 | CP9: 0 | CQ9: 1.2547131 | CR9: 23.138014 | CS9: 1.7315285 | CT9: 7.1332569 | CU9: 1.6876071 | CV9: 0 | CW9: 2.0015319 | CX9: 0 | CY9: 6.9626371 | CZ9: 4.6955047 | DA9: 5.2945124 | DB9: 0 | DC9: 0 | DD9: 0 | DE9: 0 | DF9: 0 | DG9: 0 | DH9: 7.628311 | DI9: 5.6732941 | DJ9: 0 | DK9: 0 | DL9: 0 | DM9: 0 | DN9: 0 | DO9: 0 | DP9: 0 | DQ9: 0 | DR9: 0 | DS9: 17.698712 | DT9: 4.4958019 | DU9: 5.1291505 | DV9: 0 | DW9: 0 | DX9: 0 | DY9: 0 | DZ9: 0 | EA9: 0 | EB9: 0 | EC9: 0 | ED9: 0 | EE9: 0 | EF9: 7.2281303 | EG9: 4.8059626 | EH9: 81.548226 | EI9: 0 | EJ9: 0 | EK9: 0 | EL9: 0 | EM9: 0 | EN9: 0 | EO9: 0 | EP9: 0 | EQ9: 0 | ER9: 129.58086 | ES9: 0 | ET9: 0 | EU9: 58.76436 | EV9: 0 | EW9: 0 | EX9: 0 | EY9: 0 | EZ9: 0.12917942
B10: 3 | C10: 3 | D10: Upstream | E10: Fuel and energy related activities | F10: 1173.4546 | G10: 0 | H10: 0 | I10: 20.147809 | J10: 11.497602 | K10: 0 | L10: 52.708475 | M10: 0.87509056 | N10: 0 | O10: 0 | P10: 0 | Q10: 10.825322 | R10: 0 | S10: 17.980938 | T10: 1.8925014 | U10: 2.2802348 | V10: 0 | W10: 0 | X10: 0 | Y10: 16.679025 | Z10: 0 | AA10: 16.959535 | AB10: 0 | AC10: 0 | AD10: 3.330769 | AE10: 0 | AF10: 15.242216 | AG10: 4.5457921 | AH10: 0 | AI10: 25.139249 | AJ10: 48.308008 | AK10: 3.5377815 | AL10: 0 | AM10: 0 | AN10: 0 | AO10: 2.3081366 | AP10: 0.69107493 | AQ10: 0 | AR10: 1.4876213 | AS10: 0 | AT10: 61.757478 | AU10: 0.083958212 | AV10: 7.7663923 | AW10: 0 | AX10: 1.0329917 | AY10: 0 | AZ10: 0 | BA10: 0.46761522 | BB10: 5.8414445 | BC10: 0 | BD10: 10.342264 | BE10: 0 | BF10: 0 | BG10: 0 | BH10: 16.169308 | BI10: 0 | BJ10: 0 | BK10: 0 | BL10: 0 | BM10: 0 | BN10: 0 | BO10: 0 | BP10: 0 | BQ10: 23.764003 | BR10: 0 | BS10: 0.93129404 | BT10: 3.0878478 | BU10: 0 | BV10: 0 | BW10: 0 | BX10: 0 | BY10: 0 | BZ10: 0 | CA10: 0 | CB10: 0 | CC10: 0 | CD10: 0 | CE10: 2.3936557 | CF10: 0 | CG10: 0 | CH10: 0 | CI10: 15.307488 | CJ10: 9.8394469 | CK10: 26.105047 | CL10: 1.6606382 | CM10: 9.0133631 | CN10: 3.7993671 | CO10: 0 | CP10: 0 | CQ10: 2.9663271 | CR10: 4.4533189 | CS10: 7.9335692 | CT10: 12.756694 | CU10: 4.335 | CV10: 5.371745 | CW10: 1.3303752 | CX10: 1.9821625 | CY10: 4.2983498 | CZ10: 1.4916444 | DA10: 0 | DB10: 2.0314468 | DC10: 1.0845722 | DD10: 1.8326564 | DE10: 2.1457949 | DF10: 0.61596902 | DG10: 1.3781553 | DH10: 14.285473 | DI10: 3.2078688 | DJ10: 0 | DK10: 0 | DL10: 0 | DM10: 10.357517 | DN10: 1.0458397 | DO10: 2.5092683 | DP10: 4.3822657 | DQ10: 6.9538971 | DR10: 5.4852244 | DS10: 26.680909 | DT10: 10.196731 | DU10: 6.1211812 | DV10: 0 | DW10: 0 | DX10: 0 | DY10: 0 | DZ10: 0 | EA10: 0 | EB10: 0 | EC10: 0 | ED10: 0 | EE10: 0.9654654 | EF10: 2.4674499 | EG10: 11.659608 | EH10: 389.04475 | EI10: 0 | EJ10: 0 | EK10: 0 | EL10: 0 | EM10: 0 | EN10: 0 | EO10: 26.7783 | EP10: 0 | EQ10: 0 | ER10: 52.082279 | ES10: 0 | ET10: 12.013993 | EU10: 51.133807 | EV10: 7.3014389 | EW10: 15.916524 | EX10: 1.0562394 | EY10: 0 | EZ10: 0
B11: 3 | C11: 4 | D11: Upstream | E11: Upstream transportation and distribution | F11: 22660.451 | G11: 0 | H11: -90.478019 | I11: 31.37629 | J11: 14.850305 | K11: 0 | L11: 0 | M11: 0.13041779 | N11: -5.1065664 | O11: 0 | P11: 0 | Q11: 299.02956 | R11: 0 | S11: 1143.0719 | T11: 207.10148 | U11: 171.10877 | V11: 0 | W11: 0.46917101 | X11: 0 | Y11: 118.74758 | Z11: 0 | AA11: 292.56538 | AB11: 0 | AC11: 44.479765 | AD11: -21.48079 | AE11: 39.706809 | AF11: 581.23264 | AG11: 88.114966 | AH11: 0 | AI11: 359.08432 | AJ11: 220.7786 | AK11: 16.648945 | AL11: 0 | AM11: 0 | AN11: 0 | AO11: 14.416684 | AP11: 1.5921671 | AQ11: -7.3441107 | AR11: -30.847022 | AS11: 1.982299 | AT11: 2524.2116 | AU11: 20.791649 | AV11: 146.60511 | AW11: 0 | AX11: 26.769158 | AY11: 5.4879901 | AZ11: 0 | BA11: 0 | BB11: 194.7204 | BC11: 0 | BD11: 234.24064 | BE11: 0.34049566 | BF11: 0 | BG11: 0 | BH11: 200.90703 | BI11: 0 | BJ11: 0 | BK11: 0 | BL11: 0 | BM11: 0 | BN11: 39.830195 | BO11: 0 | BP11: 0 | BQ11: 378.78298 | BR11: 477.22284 | BS11: 233.29029 | BT11: 0 | BU11: 0 | BV11: 0 | BW11: 0 | BX11: 0 | BY11: 0 | BZ11: 0 | CA11: 0 | CB11: 0 | CC11: 0 | CD11: 0 | CE11: 1.0874765 | CF11: 0 | CG11: 0 | CH11: 0 | CI11: 17.330687 | CJ11: 80.887472 | CK11: 101.70323 | CL11: 89.622329 | CM11: 27.768451 | CN11: 12.748569 | CO11: 0 | CP11: 0 | CQ11: 329.03549 | CR11: 41.301888 | CS11: 23.783143 | CT11: 267.78547 | CU11: 5.062333 | CV11: 76.740483 | CW11: 66.710585 | CX11: 27.015904 | CY11: 70.877676 | CZ11: 16.790555 | DA11: 18.607326 | DB11: 36.325379 | DC11: 10.488776 | DD11: 7.1807061 | DE11: 13.611451 | DF11: 27.48751 | DG11: 6.9036706 | DH11: 116.61338 | DI11: 0 | DJ11: 0 | DK11: 0 | DL11: 0 | DM11: 319.99392 | DN11: 29.149394 | DO11: 6.0720216 | DP11: 79.237718 | DQ11: 64.201641 | DR11: 24.661065 | DS11: 214.90341 | DT11: 64.262438 | DU11: 0.028066671 | DV11: 96.292976 | DW11: 0 | DX11: 0 | DY11: 0 | DZ11: 0 | EA11: 0 | EB11: 0 | EC11: 0 | ED11: 0 | EE11: 164.91225 | EF11: 120.52513 | EG11: 906.36118 | EH11: 4368.2325 | EI11: 0 | EJ11: 0 | EK11: 0 | EL11: 0 | EM11: 0 | EN11: 0 | EO11: 1874.4859 | EP11: 92.103432 | EQ11: 0 | ER11: 3792.6289 | ES11: 0 | ET11: 193.07284 | EU11: 528.18314 | EV11: 0.30259086 | EW11: 252.93885 | EX11: 0 | EY11: 0 | EZ11: 0
B12: 3 | C12: 5 | D12: Upstream | E12: Waste generated in operations | F12: 398.82427 | G12: 0 | H12: 0 | I12: 22.750954 | J12: 13.959694 | K12: 0 | L12: 42.42619 | M12: 0 | N12: 2.4058523 | O12: 0 | P12: 0 | Q12: 2.3539313 | R12: 0 | S12: 37.282678 | T12: 0 | U12: 0 | V12: 0 | W12: 0 | X12: 0 | Y12: 9.1585668 | Z12: 0 | AA12: 11.364582 | AB12: 0 | AC12: 0 | AD12: 0.77750247 | AE12: 0 | AF12: 0 | AG12: 0 | AH12: 0 | AI12: 0 | AJ12: 21.940782 | AK12: 5.6099703 | AL12: 0 | AM12: 0 | AN12: 0 | AO12: 3.3124936 | AP12: 0 | AQ12: 0 | AR12: 2.784268 | AS12: 0 | AT12: 14.319297 | AU12: 0 | AV12: 0 | AW12: 0 | AX12: 0 | AY12: 2.1777249 | AZ12: 0 | BA12: 0 | BB12: 9.7821939 | BC12: 0 | BD12: 0 | BE12: 0 | BF12: 0 | BG12: 0 | BH12: 0 | BI12: 0 | BJ12: 0 | BK12: 0 | BL12: 0 | BM12: 0 | BN12: 0 | BO12: 0 | BP12: 0 | BQ12: 0 | BR12: 30.196007 | BS12: 0 | BT12: 0 | BU12: 0 | BV12: 0 | BW12: 0 | BX12: 0 | BY12: 0 | BZ12: 0 | CA12: 0 | CB12: 0 | CC12: 0 | CD12: 0 | CE12: 4.9080435 | CF12: 0 | CG12: 0 | CH12: 0 | CI12: 0 | CJ12: 12.233609 | CK12: 21.866854 | CL12: 4.8746888 | CM12: 10.269365 | CN12: 0 | CO12: 0 | CP12: 0 | CQ12: 0 | CR12: 0 | CS12: 0 | CT12: 0 | CU12: 0 | CV12: 0 | CW12: 0 | CX12: 0 | CY12: 0 | CZ12: 0 | DA12: 0 | DB12: 0 | DC12: 6.0202825 | DD12: 0 | DE12: 0 | DF12: 0 | DG12: 3.8247951 | DH12: 37.413942 | DI12: 3.3304257 | DJ12: 0 | DK12: 0 | DL12: 0 | DM12: 6.5717261 | DN12: 5.3735074 | DO12: 0.67108977 | DP12: 3.0279947 | DQ12: 0 | DR12: 0 | DS12: 0 | DT12: 0 | DU12: 0 | DV12: 0 | DW12: 0 | DX12: 0 | DY12: 0 | DZ12: 0 | EA12: 0 | EB12: 0 | EC12: 0 | ED12: 0 | EE12: 0 | EF12: 6.0580801 | EG12: 0 | EH12: 0 | EI12: 0 | EJ12: 0 | EK12: 0 | EL12: 0 | EM12: 0 | EN12: 0 | EO12: 39.77718 | EP12: 0 | EQ12: 0 | ER12: 0 | ES12: 0 | ET12: 0 | EU12: 0 | EV12: 0 | EW12: 0 | EX12: 0 | EY12: 0 | EZ12: 0
B13: 3 | C13: 6 | D13: Upstream | E13: Business travel | F13: 3171.7995 | G13: 0 | H13: 0 | I13: 182.03817 | J13: 18.593791 | K13: 6.3719193 | L13: 116.12869 | M13: 0 | N13: 0.94715128 | O13: 0 | P13: 0 | Q13: 205.69346 | R13: 0 | S13: 161.67129 | T13: 18.542308 | U13: 8.0298688 | V13: 0.26728949 | W13: 0.250462 | X13: 0 | Y13: 75.649873 | Z13: 0 | AA13: 27.395583 | AB13: 1.3436009 | AC13: 1.4194121 | AD13: 2.7908651 | AE13: 5.2680273 | AF13: 25.328374 | AG13: 6.5894705 | AH13: 0 | AI13: 50.988623 | AJ13: 67.551748 | AK13: 2.5595342 | AL13: 0 | AM13: 0 | AN13: 0.32541442 | AO13: 0 | AP13: 0.36370363 | AQ13: 0 | AR13: 39.193546 | AS13: 0 | AT13: 46.621271 | AU13: 4.9167948 | AV13: 38.034751 | AW13: 0 | AX13: 6.7320902 | AY13: 8.2163388 | AZ13: 0 | BA13: 3.364679 | BB13: 21.519197 | BC13: 2.3360251 | BD13: 0 | BE13: 0.49096305 | BF13: 3.3291327 | BG13: 22.253992 | BH13: 84.893073 | BI13: 17.859093 | BJ13: 0.1684982 | BK13: 0.77914491 | BL13: 2.972419 | BM13: 7.1880289 | BN13: 13.443626 | BO13: 0 | BP13: 0 | BQ13: 0 | BR13: 50.660953 | BS13: 0 | BT13: 483.11255 | BU13: 0 | BV13: 0 | BW13: 0 | BX13: 0 | BY13: 0 | BZ13: 0 | CA13: 66.24175 | CB13: -170.78273 | CC13: 45.661697 | CD13: 58.879282 | CE13: 3.5280289 | CF13: 0 | CG13: 0 | CH13: 0 | CI13: 26.375867 | CJ13: 8.9527333 | CK13: 30.405729 | CL13: 0.89100921 | CM13: 9.9880168 | CN13: 5.8018404 | CO13: 0 | CP13: 0 | CQ13: 4.1797785 | CR13: 0.53004081 | CS13: 9.9054023 | CT13: 22.296664 | CU13: 1.9180865 | CV13: 0.7877973 | CW13: 2.8302796 | CX13: 3.4994074 | CY13: 7.9980574 | CZ13: 14.128309 | DA13: 9.7214206 | DB13: 2.6092898 | DC13: 0.0064363776 | DD13: 2.1757817 | DE13: 0.35875143 | DF13: 0.15903472 | DG13: 0.14966712 | DH13: 2.6695285 | DI13: 32.255091 | DJ13: 0 | DK13: 0 | DL13: 0 | DM13: 8.9973258 | DN13: 0.34926922 | DO13: 0.6271524 | DP13: 5.2498626 | DQ13: 4.2171609 | DR13: 0.34964544 | DS13: 33.252598 | DT13: 2.9616279 | DU13: 0.0096527883 | DV13: 5.6390203 | DW13: 10.558769 | DX13: -4.3767844 | DY13: 12.534543 | DZ13: 0 | EA13: 0 | EB13: 1.4787731 | EC13: 1.1221082 | ED13: 0.68825933 | EE13: 24.900217 | EF13: 28.452682 | EG13: 71.452959 | EH13: 188.36428 | EI13: 2.3652053 | EJ13: 0 | EK13: 0 | EL13: 0 | EM13: 0 | EN13: 0 | EO13: 83.626156 | EP13: 0 | EQ13: 67.985097 | ER13: 227.8251 | ES13: 1.2668371 | ET13: 30.475585 | EU13: 257.51728 | EV13: 8.9465241 | EW13: 6.2425632 | EX13: 0 | EY13: -0.76425986 | EZ13: 41.167439
B14: 3 | C14: 7 | D14: Upstream | E14: Employee commuting | F14: 3379.0944 | G14: 0 | H14: 0 | I14: 86.841374 | J14: 36.666358 | K14: 0 | L14: 116.7534 | M14: 0 | N14: 0 | O14: 0 | P14: 0 | Q14: 64.648579 | R14: 0 | S14: 114.8236 | T14: 28.947125 | U14: 22.192796 | V14: 0 | W14: 1.9298083 | X14: 0 | Y14: 47.280304 | Z14: 0 | AA14: 39.561071 | AB14: 0.96490416 | AC14: 0 | AD14: 17.368275 | AE14: 0 | AF14: 69.4731 | AG14: 21.227892 | AH14: 0 | AI14: 42.455783 | AJ14: 68.508195 | AK14: 10.613946 | AL14: 0 | AM14: 0 | AN14: 0.96490416 | AO14: 2.8947125 | AP14: 4.8245208 | AQ14: 0 | AR14: 14.473562 | AS14: 0 | AT14: 233.50681 | AU14: 4.8245208 | AV14: 18.333179 | AW14: 0 | AX14: 12.543754 | AY14: 0 | AZ14: 0 | BA14: 2.8947125 | BB14: 30.876933 | BC14: 0.96490416 | BD14: 100.35003 | BE14: 0 | BF14: 0 | BG14: 0 | BH14: 123.50773 | BI14: 0 | BJ14: 0 | BK14: 0 | BL14: 0 | BM14: 0 | BN14: 0 | BO14: 0 | BP14: 0 | BQ14: 0 | BR14: 182.36689 | BS14: 0 | BT14: 44.385591 | BU14: 0 | BV14: 0 | BW14: 0 | BX14: 0 | BY14: 6.7543291 | BZ14: 0 | CA14: 2.8947125 | CB14: -4.8245208 | CC14: 1.9298083 | CD14: 1.9298083 | CE14: 1.9298083 | CF14: 0 | CG14: 0 | CH14: 0 | CI14: 25.087508 | CJ14: 24.122604 | CK14: 67.543291 | CL14: 11.57885 | CM14: 32.806741 | CN14: 8.6841374 | CO14: 0 | CP14: 0 | CQ14: 55.964441 | CR14: 36.666358 | CS14: 34.73655 | CT14: 102.27984 | CU14: 17.368275 | CV14: 17.368275 | CW14: 19.298083 | CX14: 11.57885 | CY14: 9.6490416 | CZ14: 7.7192333 | DA14: 0 | DB14: 8.6841374 | DC14: 0 | DD14: 4.8245208 | DE14: 10.613946 | DF14: 4.8245208 | DG14: 3.8596166 | DH14: 67.543291 | DI14: 30.876933 | DJ14: 0 | DK14: 0 | DL14: 0 | DM14: 51.139921 | DN14: 7.7192333 | DO14: 8.6841374 | DP14: 20.262987 | DQ14: 28.947125 | DR14: 17.368275 | DS14: 69.4731 | DT14: 20.262987 | DU14: 56.929345 | DV14: 0 | DW14: 0 | DX14: 0 | DY14: 0 | DZ14: 0 | EA14: 0 | EB14: 0 | EC14: 0 | ED14: 0 | EE14: 8.6841374 | EF14: 19.298083 | EG14: 61.753866 | EH14: 306.83952 | EI14: 6.7543291 | EJ14: 0 | EK14: 0.96490416 | EL14: 0 | EM14: 0.96490416 | EN14: 0 | EO14: 109.03417 | EP14: 0 | EQ14: 10.613946 | ER14: 185.2616 | ES14: 0 | ET14: 34.73655 | EU14: 131.22697 | EV14: 3.8596166 | EW14: 22.192796 | EX14: 0 | EY14: 0 | EZ14: 3.8596166
B15: 3 | C15: 8 | D15: Upstream | E15: Upstream leased assets | F15: 1436.436 | G15: 0 | H15: 0 | I15: 23.437325 | J15: 14.379551 | K15: 0 | L15: 40.872918 | M15: 1.0702224 | N15: 1.6219169 | O15: 0 | P15: 0 | Q15: 10.04183 | R15: 0 | S15: 58.744947 | T15: 12.411337 | U15: 15.136777 | V15: 1.6429786 | W15: 0.91379378 | X15: 0 | Y15: 13.086631 | Z15: 0 | AA15: 41.348205 | AB15: 0 | AC15: 3.8302778 | AD15: 2.9295296 | AE15: 0.57411038 | AF15: 31.515103 | AG15: 4.6853484 | AH15: 0 | AI15: 5.3540884 | AJ15: 14.844576 | AK15: 4.1437688 | AL15: 0 | AM15: 0 | AN15: 0 | AO15: 2.5244423 | AP15: 5.9332223 | AQ15: 0 | AR15: 4.3374907 | AS15: 0 | AT15: 47.595315 | AU15: 0.52295857 | AV15: 13.67145 | AW15: 0 | AX15: 1.7445952 | AY15: 6.8725178 | AZ15: 0 | BA15: 1.0334105 | BB15: 9.6379626 | BC15: 0 | BD15: 4.0368435 | BE15: 3.6002592 | BF15: 1.1555744 | BG15: 9.2908661 | BH15: 30.273803 | BI15: 0 | BJ15: 0 | BK15: 0 | BL15: 0 | BM15: 0 | BN15: 0 | BO15: 0 | BP15: 0 | BQ15: 0 | BR15: 79.597276 | BS15: 0 | BT15: 30.243062 | BU15: 0 | BV15: 0 | BW15: 0 | BX15: 0 | BY15: 0 | BZ15: 0 | CA15: 0 | CB15: 0 | CC15: 0 | CD15: 0 | CE15: 1.2276399 | CF15: 0 | CG15: 0 | CH15: 0 | CI15: 5.4686493 | CJ15: 7.5479624 | CK15: 29.890529 | CL15: 4.6276777 | CM15: 10.428291 | CN15: 1.6341155 | CO15: 0 | CP15: 0 | CQ15: 21.086228 | CR15: 9.0175263 | CS15: 7.764375 | CT15: 33.612607 | CU15: 0.92615709 | CV15: 1.1764301 | CW15: 3.5874619 | CX15: 3.8370325 | CY15: 10.423483 | CZ15: 0.54752516 | DA15: 3.7802002 | DB15: 3.4060575 | DC15: 0.8032104 | DD15: 2.0664121 | DE15: 6.4302294 | DF15: 1.8341631 | DG15: 1.2373836 | DH15: 0 | DI15: 1.9613609 | DJ15: -6.1336067 | DK15: 0 | DL15: 0 | DM15: 16.821932 | DN15: 1.5752343 | DO15: 4.702093 | DP15: 8.0010592 | DQ15: 5.482279 | DR15: 4.1097694 | DS15: 20.756023 | DT15: 4.7908363 | DU15: 1.8647041 | DV15: 15.324812 | DW15: 0 | DX15: 0 | DY15: 0 | DZ15: 0 | EA15: 3.5434651 | EB15: 2.5636428 | EC15: 2.2823881 | ED15: 0 | EE15: 2.0748982 | EF15: 10.659286 | EG15: 0 | EH15: 362.20617 | EI15: 0 | EJ15: 0 | EK15: 0 | EL15: 0 | EM15: 0 | EN15: 0 | EO15: 72.974325 | EP15: 0 | EQ15: 0 | ER15: 65.648533 | ES15: 0 | ET15: 23.544192 | EU15: 59.159038 | EV15: 10.184911 | EW15: 15.2867 | EX15: 0 | EY15: 0 | EZ15: 0.034310991
B16: 3 | C16: 9 | D16: Downstream | E16: Downstream transportation and distribution | F16: 0 | G16: 0 | H16: 0 | I16: 0 | J16: 0 | K16: 0 | L16: 0 | M16: 0 | N16: 0 | O16: 0 | P16: 0 | Q16: 0 | R16: 0 | S16: 0 | T16: 0 | U16: 0 | V16: 0 | W16: 0 | X16: 0 | Y16: 0 | Z16: 0 | AA16: 0 | AB16: 0 | AC16: 0 | AD16: 0 | AE16: 0 | AF16: 0 | AG16: 0 | AH16: 0 | AI16: 0 | AJ16: 0 | AK16: 0 | AL16: 0 | AM16: 0 | AN16: 0 | AO16: 0 | AP16: 0 | AQ16: 0 | AR16: 0 | AS16: 0 | AT16: 0 | AU16: 0 | AV16: 0 | AW16: 0 | AX16: 0 | AY16: 0 | AZ16: 0 | BA16: 0 | BB16: 0 | BC16: 0 | BD16: 0 | BE16: 0 | BF16: 0 | BG16: 0 | BH16: 0 | BI16: 0 | BJ16: 0 | BK16: 0 | BL16: 0 | BM16: 0 | BN16: 0 | BO16: 0 | BP16: 0 | BQ16: 0 | BR16: 0 | BS16: 0 | BT16: 0 | BU16: 0 | BV16: 0 | BW16: 0 | BX16: 0 | BY16: 0 | BZ16: 0 | CA16: 0 | CB16: 0 | CC16: 0 | CD16: 0 | CE16: 0 | CF16: 0 | CG16: 0 | CH16: 0 | CI16: 0 | CJ16: 0 | CK16: 0 | CL16: 0 | CM16: 0 | CN16: 0 | CO16: 0 | CP16: 0 | CQ16: 0 | CR16: 0 | CS16: 0 | CT16: 0 | CU16: 0 | CV16: 0 | CW16: 0 | CX16: 0 | CY16: 0 | CZ16: 0 | DA16: 0 | DB16: 0 | DC16: 0 | DD16: 0 | DE16: 0 | DF16: 0 | DG16: 0 | DH16: 0 | DI16: 0 | DJ16: 0 | DK16: 0 | DL16: 0 | DM16: 0 | DN16: 0 | DO16: 0 | DP16: 0 | DQ16: 0 | DR16: 0 | DS16: 0 | DT16: 0 | DU16: 0 | DV16: 0 | DW16: 0 | DX16: 0 | DY16: 0 | DZ16: 0 | EA16: 0 | EB16: 0 | EC16: 0 | ED16: 0 | EE16: 0 | EF16: 0 | EG16: 0 | EH16: 0 | EI16: 0 | EJ16: 0 | EK16: 0 | EL16: 0 | EM16: 0 | EN16: 0 | EO16: 0 | EP16: 0 | EQ16: 0 | ER16: 0 | ES16: 0 | ET16: 0 | EU16: 0 | EV16: 0 | EW16: 0 | EX16: 0 | EY16: 0 | EZ16: 0
B17: 3 | C17: 10 | D17: Downstream | E17: Processing of sold products | F17: 0 | G17: 0 | H17: 0 | I17: 0 | J17: 0 | K17: 0 | L17: 0 | M17: 0 | N17: 0 | O17: 0 | P17: 0 | Q17: 0 | R17: 0 | S17: 0 | T17: 0 | U17: 0 | V17: 0 | W17: 0 | X17: 0 | Y17: 0 | Z17: 0 | AA17: 0 | AB17: 0 | AC17: 0 | AD17: 0 | AE17: 0 | AF17: 0 | AG17: 0 | AH17: 0 | AI17: 0 | AJ17: 0 | AK17: 0 | AL17: 0 | AM17: 0 | AN17: 0 | AO17: 0 | AP17: 0 | AQ17: 0 | AR17: 0 | AS17: 0 | AT17: 0 | AU17: 0 | AV17: 0 | AW17: 0 | AX17: 0 | AY17: 0 | AZ17: 0 | BA17: 0 | BB17: 0 | BC17: 0 | BD17: 0 | BE17: 0 | BF17: 0 | BG17: 0 | BH17: 0 | BI17: 0 | BJ17: 0 | BK17: 0 | BL17: 0 | BM17: 0 | BN17: 0 | BO17: 0 | BP17: 0 | BQ17: 0 | BR17: 0 | BS17: 0 | BT17: 0 | BU17: 0 | BV17: 0 | BW17: 0 | BX17: 0 | BY17: 0 | BZ17: 0 | CA17: 0 | CB17: 0 | CC17: 0 | CD17: 0 | CE17: 0 | CF17: 0 | CG17: 0 | CH17: 0 | CI17: 0 | CJ17: 0 | CK17: 0 | CL17: 0 | CM17: 0 | CN17: 0 | CO17: 0 | CP17: 0 | CQ17: 0 | CR17: 0 | CS17: 0 | CT17: 0 | CU17: 0 | CV17: 0 | CW17: 0 | CX17: 0 | CY17: 0 | CZ17: 0 | DA17: 0 | DB17: 0 | DC17: 0 | DD17: 0 | DE17: 0 | DF17: 0 | DG17: 0 | DH17: 0 | DI17: 0 | DJ17: 0 | DK17: 0 | DL17: 0 | DM17: 0 | DN17: 0 | DO17: 0 | DP17: 0 | DQ17: 0 | DR17: 0 | DS17: 0 | DT17: 0 | DU17: 0 | DV17: 0 | DW17: 0 | DX17: 0 | DY17: 0 | DZ17: 0 | EA17: 0 | EB17: 0 | EC17: 0 | ED17: 0 | EE17: 0 | EF17: 0 | EG17: 0 | EH17: 0 | EI17: 0 | EJ17: 0 | EK17: 0 | EL17: 0 | EM17: 0 | EN17: 0 | EO17: 0 | EP17: 0 | EQ17: 0 | ER17: 0 | ES17: 0 | ET17: 0 | EU17: 0 | EV17: 0 | EW17: 0 | EX17: 0 | EY17: 0 | EZ17: 0
B18: 3 | C18: 11 | D18: Downstream | E18: Use of sold products | F18: 861.11502 | G18: 0 | H18: 0 | I18: 418.42447 | J18: 0 | K18: 0 | L18: 0 | M18: 0 | N18: 0 | O18: 0 | P18: 0 | Q18: 237.41245 | R18: 0 | S18: 0 | T18: 0 | U18: 0 | V18: 0 | W18: 0 | X18: 0 | Y18: 0 | Z18: 0 | AA18: 0 | AB18: 0 | AC18: 0 | AD18: 0 | AE18: 0 | AF18: 0 | AG18: 0 | AH18: 0 | AI18: 0 | AJ18: 0 | AK18: 0 | AL18: 0 | AM18: 0 | AN18: 0 | AO18: 0 | AP18: 0 | AQ18: 0 | AR18: 205.27811 | AS18: 0 | AT18: 0 | AU18: 0 | AV18: 0 | AW18: 0 | AX18: 0 | AY18: 0 | AZ18: 0 | BA18: 0 | BB18: 0 | BC18: 0 | BD18: 0 | BE18: 0 | BF18: 0 | BG18: 0 | BH18: 0 | BI18: 0 | BJ18: 0 | BK18: 0 | BL18: 0 | BM18: 0 | BN18: 0 | BO18: 0 | BP18: 0 | BQ18: 0 | BR18: 0 | BS18: 0 | BT18: 0 | BU18: 0 | BV18: 0 | BW18: 0 | BX18: 0 | BY18: 0 | BZ18: 0 | CA18: 0 | CB18: 0 | CC18: 0 | CD18: 0 | CE18: 0 | CF18: 0 | CG18: 0 | CH18: 0 | CI18: 0 | CJ18: 0 | CK18: 0 | CL18: 0 | CM18: 0 | CN18: 0 | CO18: 0 | CP18: 0 | CQ18: 0 | CR18: 0 | CS18: 0 | CT18: 0 | CU18: 0 | CV18: 0 | CW18: 0 | CX18: 0 | CY18: 0 | CZ18: 0 | DA18: 0 | DB18: 0 | DC18: 0 | DD18: 0 | DE18: 0 | DF18: 0 | DG18: 0 | DH18: 0 | DI18: 0 | DJ18: 0 | DK18: 0 | DL18: 0 | DM18: 0 | DN18: 0 | DO18: 0 | DP18: 0 | DQ18: 0 | DR18: 0 | DS18: 0 | DT18: 0 | DU18: 0 | DV18: 0 | DW18: 0 | DX18: 0 | DY18: 0 | DZ18: 0 | EA18: 0 | EB18: 0 | EC18: 0 | ED18: 0 | EE18: 0 | EF18: 0 | EG18: 0 | EH18: 0 | EI18: 0 | EJ18: 0 | EK18: 0 | EL18: 0 | EM18: 0 | EN18: 0 | EO18: 0 | EP18: 0 | EQ18: 0 | ER18: 0 | ES18: 0 | ET18: 0 | EU18: 0 | EV18: 0 | EW18: 0 | EX18: 0 | EY18: 0 | EZ18: 0
B19: 3 | C19: 12 | D19: Downstream | E19: End of life treatment of sold products | F19: 20.476429 | G19: 0 | H19: 0.017645739 | I19: 0.27349999 | J19: 0.016436531 | K19: 0 | L19: 0 | M19: 0.00032415285 | N19: 0.0044751005 | O19: 0 | P19: 0 | Q19: 0.34248743 | R19: 0 | S19: 0.74772242 | T19: 0.15942786 | U19: 0.093362117 | V19: 0 | W19: 0.0011661225 | X19: 0 | Y19: 0.28307137 | Z19: 0 | AA19: 0.16713003 | AB19: 0 | AC19: 0.026432254 | AD19: 0.019780292 | AE19: 0.092102775 | AF19: 0.46018525 | AG19: 0.03053028 | AH19: 0 | AI19: 0.27023752 | AJ19: 0.14706438 | AK19: 0.023187657 | AL19: 0 | AM19: 0 | AN19: 0 | AO19: 0.025958863 | AP19: 0 | AQ19: 0.011532157 | AR19: 0.024567655 | AS19: 0.0032449338 | AT19: 1.913999 | AU19: 0.02321387 | AV19: 0.085896104 | AW19: 0 | AX19: 0.027579128 | AY19: 0.035325623 | AZ19: 0 | BA19: 0 | BB19: 0.21773548 | BC19: 0 | BD19: 0.52664249 | BE19: 0.00089595383 | BF19: 0 | BG19: 0 | BH19: 0.40070767 | BI19: 0 | BJ19: 0 | BK19: 0 | BL19: 0 | BM19: 0 | BN19: 0.067741116 | BO19: 0 | BP19: 0 | BQ19: 0.74598778 | BR19: 0.3689986 | BS19: 0.24843304 | BT19: 0 | BU19: 0 | BV19: 0 | BW19: 0 | BX19: 0 | BY19: 0 | BZ19: 0 | CA19: 0 | CB19: 0 | CC19: 0 | CD19: 0 | CE19: 0 | CF19: 0 | CG19: 0 | CH19: 0 | CI19: 0 | CJ19: 0 | CK19: 0.028241343 | CL19: 0 | CM19: 0 | CN19: 0.0093305046 | CO19: 0 | CP19: 0 | CQ19: 0 | CR19: 0 | CS19: 0 | CT19: 0.18514747 | CU19: 0 | CV19: 0 | CW19: 0.00013331324 | CX19: 0.016327926 | CY19: 0 | CZ19: 0 | DA19: 0 | DB19: 0 | DC19: 0.0092385947 | DD19: 0.001141885 | DE19: 0 | DF19: 0 | DG19: 0.0054560157 | DH19: 0.21173794 | DI19: 0 | DJ19: 0 | DK19: 0 | DL19: 0 | DM19: 0.27596518 | DN19: 0.020375798 | DO19: 0.0033722409 | DP19: 0.052748569 | DQ19: 0 | DR19: 0 | DS19: 0 | DT19: 0 | DU19: 0 | DV19: 0.19112163 | DW19: 0 | DX19: 0 | DY19: 0 | DZ19: 0 | EA19: 0 | EB19: 0 | EC19: 0 | ED19: 0 | EE19: 0.011786578 | EF19: 0.092123557 | EG19: 0 | EH19: 7.2158518 | EI19: 0 | EJ19: 0 | EK19: 0 | EL19: 0 | EM19: 0 | EN19: 0 | EO19: 0.12350719 | EP19: 0.022541482 | EQ19: 0 | ER19: 3.4188551 | ES19: 0 | ET19: 0.31132118 | EU19: 0.36537521 | EV19: 0 | EW19: 0 | EX19: 0 | EY19: 0 | EZ19: 0
... B22: 3 | C22: 15 | D22: Downstream | E22: Investments | F22: 0 | G22: 0 | H22: 0 | I22: 0 | J22: 0 | K22: 0 | L22: 0 | M22: 0 | N22: 0 | O22: 0 | P22: 0 | Q22: 0 | R22: 0 | S22: 0 | T22: 0 | U22: 0 | V22: 0 | W22: 0 | X22: 0 | Y22: 0 | Z22: 0 | AA22: 0 | AB22: 0 | AC22: 0 | AD22: 0 | AE22: 0 | AF22: 0 | AG22: 0 | AH22: 0 | AI22: 0 | AJ22: 0 | AK22: 0 | AL22: 0 | AM22: 0 | AN22: 0 | AO22: 0 | AP22: 0 | AQ22: 0 | AR22: 0 | AS22: 0 | AT22: 0 | AU22: 0 | AV22: 0 | AW22: 0 | AX22: 0 | AY22: 0 | AZ22: 0 | BA22: 0 | BB22: 0 | BC22: 0 | BD22: 0 | BE22: 0 | BF22: 0 | BG22: 0 | BH22: 0 | BI22: 0 | BJ22: 0 | BK22: 0 | BL22: 0 | BM22: 0 | BN22: 0 | BO22: 0 | BP22: 0 | BQ22: 0 | BR22: 0 | BS22: 0 | BT22: 0 | BU22: 0 | BV22: 0 | BW22: 0 | BX22: 0 | BY22: 0 | BZ22: 0 | CA22: 0 | CB22: 0 | CC22: 0 | CD22: 0 | CE22: 0 | CF22: 0 | CG22: 0 | CH22: 0 | CI22: 0 | CJ22: 0 | CK22: 0 | CL22: 0 | CM22: 0 | CN22: 0 | CO22: 0 | CP22: 0 | CQ22: 0 | CR22: 0 | CS22: 0 | CT22: 0 | CU22: 0 | CV22: 0 | CW22: 0 | CX22: 0 | CY22: 0 | CZ22: 0 | DA22: 0 | DB22: 0 | DC22: 0 | DD22: 0 | DE22: 0 | DF22: 0 | DG22: 0 | DH22: 0 | DI22: 0 | DJ22: 0 | DK22: 0 | DL22: 0 | DM22: 0 | DN22: 0 | DO22: 0 | DP22: 0 | DQ22: 0 | DR22: 0 | DS22: 0 | DT22: 0 | DU22: 0 | DV22: 0 | DW22: 0 | DX22: 0 | DY22: 0 | DZ22: 0 | EA22: 0 | EB22: 0 | EC22: 0 | ED22: 0 | EE22: 0 | EF22: 0 | EG22: 0 | EH22: 0 | EI22: 0 | EJ22: 0 | EK22: 0 | EL22: 0 | EM22: 0 | EN22: 0 | EO22: 0 | EP22: 0 | EQ22: 0 | ER22: 0 | ES22: 0 | ET22: 0 | EU22: 0 | EV22: 0 | EW22: 0 | EX22: 0 | EY22: 0 | EZ22: 0
E23: Total LB | F23: 119158.19 | G23: 0.8714176 | H23: 765.68387 | I23: 4801.8 | J23: 751.09079 | K23: -3.9444069 | L23: 1935.8916 | M23: 6.696795 | N23: 65.158064 | O23: 0 | P23: 0 | Q23: 4930.0055 | R23: 0 | S23: 8254.1127 | T23: 763.76977 | U23: 855.87144 | V23: 1.992886 | W23: 9.2539648 | X23: -57.844455 | Y23: 2270.2716 | Z23: 0 | AA23: 920.22427 | AB23: 3.2556637 | AC23: 95.432208 | AD23: 248.20057 | AE23: 183.04224 | AF23: 1876.7403 | AG23: 1161.5231 | AH23: 2.0094466 | AI23: 3104.481 | AJ23: 4007.4226 | AK23: 594.68132 | AL23: 116.19232 | AM23: 0 | AN23: 2.7652732 | AO23: 93.397569 | AP23: 53.430224 | AQ23: 179.67979 | AR23: 811.84205 | AS23: 98.063117 | AT23: 5394.8148 | AU23: 191.29286 | AV23: 1721.8194 | AW23: 0 | AX23: 313.59576 | AY23: 150.59831 | AZ23: 0 | BA23: 11.284582 | BB23: 1125.1949 | BC23: 3.8120209 | BD23: 1509.4068 | BE23: -16.09549 | BF23: 19.279776 | BG23: 98.803169 | BH23: 2040.0037 | BI23: 20.578679 | BJ23: 3.0722256 | BK23: 1.016279 | BL23: 4.7213537 | BM23: 8.4942802 | BN23: 443.37301 | BO23: 0 | BP23: 0 | BQ23: 932.5367 | BR23: 1957.4155 | BS23: 657.54603 | BT23: 1406.6791 | BU23: 0 | BV23: 0.058196984 | BW23: 0.014047579 | BX23: 0.63661389 | BY23: 6.7543291 | BZ23: 2464.2223 | CA23: 503.67036 | CB23: -182.31914 | CC23: 47.731905 | CD23: -116.874 | CE23: 374.38029 | CF23: 0 | CG23: 0 | CH23: 0 | CI23: 312.34446 | CJ23: 383.01048 | CK23: 938.52136 | CL23: 245.38029 | CM23: 322.41655 | CN23: 146.97126 | CO23: 0 | CP23: 0 | CQ23: 828.77523 | CR23: 511.52073 | CS23: 329.00807 | CT23: 1058.3869 | CU23: 33.646564 | CV23: 232.08722 | CW23: 293.58926 | CX23: 141.099 | CY23: 500.65957 | CZ23: 80.980283 | DA23: 223.3548 | DB23: 128.70385 | DC23: 40.673407 | DD23: 60.174587 | DE23: 123.55878 | DF23: 97.701916 | DG23: 68.38884 | DH23: 1016.1086 | DI23: 165.23888 | DJ23: -5.8118498 | DK23: 0 | DL23: 0 | DM23: 724.27633 | DN23: 81.756014 | DO23: 66.497918 | DP23: 348.36852 | DQ23: 222.2552 | DR23: 443.16469 | DS23: 1174.5632 | DT23: 385.35694 | DU23: 1091.8223 | DV23: 765.92452 | DW23: 28.684052 | DX23: -1.800443 | DY23: 28.085429 | DZ23: 2.6657774 | EA23: 10.279806 | EB23: 34.926693 | EC23: 10.889677 | ED23: 2.0464742 | EE23: 431.85603 | EF23: 842.11216 | EG23: 3880.5902 | EH23: 7965.28 | EI23: 92.218992 | EJ23: 220.26643 | EK23: -159.95689 | EL23: -53.591333 | EM23: 0.96490416 | EN23: 0 | EO23: 11161.036 | EP23: 184.9399 | EQ23: 173.45297 | ER23: 10721.772 | ES23: 4.2260243 | ET23: 852.14223 | EU23: 7939.3565 | EV23: 185.25968 | EW23: 904.80777 | EX23: 5.2008623 | EY23: 20.913131 | EZ23: 88.508107
E24: Total MB | F24: 119766.32 | G24: 0.8714176 | H24: 765.68387 | I24: 4801.8 | J24: 751.09079 | K24: -3.9444069 | L24: 1935.8916 | M24: 6.696795 | N24: 65.158064 | O24: 0 | P24: 0 | Q24: 4930.0055 | R24: 0 | S24: 8254.1127 | T24: 763.76977 | U24: 855.87144 | V24: 1.992886 | W24: 9.2539648 | X24: -57.844455 | Y24: 2288.6125 | Z24: 0 | AA24: 962.13086 | AB24: 3.2556637 | AC24: 95.432208 | AD24: 255.8276 | AE24: 183.04224 | AF24: 1892.1224 | AG24: 1168.2543 | AH24: 2.0094466 | AI24: 3121.5781 | AJ24: 4019.9734 | AK24: 596.43317 | AL24: 116.19232 | AM24: 0 | AN24: 2.7652732 | AO24: 94.622255 | AP24: 53.093165 | AQ24: 179.67979 | AR24: 811.84205 | AS24: 98.063117 | AT24: 5496.5131 | AU24: 191.65724 | AV24: 1724.4872 | AW24: 0 | AX24: 313.8584 | AY24: 150.59831 | AZ24: 0 | BA24: 11.284582 | BB24: 1136.0216 | BC24: 3.8120209 | BD24: 1523.4658 | BE24: -16.09549 | BF24: 19.279776 | BG24: 98.803169 | BH24: 2072.0094 | BI24: 20.578679 | BJ24: 3.0722256 | BK24: 1.016279 | BL24: 4.7213537 | BM24: 8.4942802 | BN24: 443.37301 | BO24: 0 | BP24: 0 | BQ24: 992.03705 | BR24: 1957.4155 | BS24: 659.33722 | BT24: 1414.6913 | BU24: 0 | BV24: 0.058196984 | BW24: 0.014047579 | BX24: 0.63661389 | BY24: 6.7543291 | BZ24: 2464.2223 | CA24: 503.67036 | CB24: -182.31914 | CC24: 47.731905 | CD24: -116.874 | CE24: 374.38029 | CF24: 0 | CG24: 0 | CH24: 0 | CI24: 318.48081 | CJ24: 388.22694 | CK24: 947.17247 | CL24: 247.09578 | CM24: 329.76696 | CN24: 148.70435 | CO24: 0 | CP24: 0 | CQ24: 835.43426 | CR24: 515.49674 | CS24: 330.89067 | CT24: 1077.7594 | CU24: 44.014942 | CV24: 240.52307 | CW24: 295.34002 | CX24: 142.713 | CY24: 502.36902 | CZ24: 84.85075 | DA24: 223.3548 | DB24: 130.2178 | DC24: 43.436432 | DD24: 61.384457 | DE24: 125.50856 | DF24: 99.300211 | DG24: 69.59871 | DH24: 1034.0623 | DI24: 165.64615 | DJ24: -5.8118498 | DK24: 0 | DL24: 0 | DM24: 743.14497 | DN24: 84.4669 | DO24: 68.452647 | DP24: 354.87895 | DQ24: 234.94689 | DR24: 443.59148 | DS24: 1174.0602 | DT24: 386.38166 | DU24: 1093.3176 | DV24: 765.92452 | DW24: 28.684052 | DX24: -1.800443 | DY24: 28.085429 | DZ24: 2.6657774 | EA24: 10.279806 | EB24: 34.926693 | EC24: 10.889677 | ED24: 2.0464742 | EE24: 431.91168 | EF24: 842.25689 | EG24: 3880.905 | EH24: 8023.8493 | EI24: 92.218992 | EJ24: 220.26643 | EK24: -159.95689 | EL24: -53.591333 | EM24: 0.96490416 | EN24: 0 | EO24: 11165.479 | EP24: 184.9399 | EQ24: 173.45297 | ER24: 10722.59 | ES24: 4.2260243 | ET24: 853.97633 | EU24: 7960.1367 | EV24: 187.24453 | EW24: 905.27482 | EX24: 6.2308867 | EY24: 20.913131 | EZ24: 88.508107
B26: FY25 Summary (H1)
B28: Scope | C28: Category | D28: Upstream/Downstream | E28: Emission Source | F28: tCO2e Market | G28: tCO2e Location
B29: 1 | C29: - | D29: Internal | E29: Stationary combustion | F29: 1336.419 | G29: 1336.419
B30: 1 | C30: - | D30: Internal | E30: Company vehicles | F30: 936.81688 | G30: 936.81688
B31: 1 | C31: - | D31: Internal | E31: Fugitive emissions | F31: 0 | G31: 0
B32: 1 | C32: - | D32: Internal | E32: Refrigerants | F32: 6.410566 | G32: 6.410566
B33: 1 | C33: - | D33: Internal | E33: Extrapolated tCo2e | F33: 0 | G33: 0
B34: 2 | C34: - | D34: Internal | E34: Electricity usage | F34: 3365.3929 | G34: 2757.2595
B35: 2 | C35: - | D35: Internal | E35: Heating | F35: 53.952952 | G35: 53.952952
B36: 2 | C36: - | D36: Internal | E36: Cooling | F36: 0 | G36: 0
B37: 2 | C37: - | D37: Internal | E37: Extrapolated tCo2e | F37: 0 | G37: 0
B38: 3 | C38: 1 | D38: Upstream | E38: Purchased goods and services | F38: 79412.202 | G38: 79412.202
B39: 3 | C39: 2 | D39: Upstream | E39: Capital goods | F39: 1553.4786 | G39: 1553.4786
B40: 3 | C40: 3 | D40: Upstream | E40: Fuel and energy related activities | F40: 1173.4546 | G40: 1173.4546
B41: 3 | C41: 4 | D41: Upstream | E41: Upstream transportation and distribution | F41: 22660.451 | G41: 22660.451
B42: 3 | C42: 5 | D42: Upstream | E42: Waste generated in operations | F42: 398.82427 | G42: 398.82427
B43: 3 | C43: 6 | D43: Upstream | E43: Business travel | F43: 3171.7995 | G43: 3171.7995
B44: 3 | C44: 7 | D44: Upstream | E44: Employee commuting | F44: 3379.0944 | G44: 3379.0944
B45: 3 | C45: 8 | D45: Upstream | E45: Upstream leased assets | F45: 1436.436 | G45: 1436.436
B46: 3 | C46: 9 | D46: Downstream | E46: Downstream transportation and distribution | F46: 0 | G46: 0
B47: 3 | C47: 10 | D47: Downstream | E47: Processing of sold products | F47: 0 | G47: 0
B48: 3 | C48: 11 | D48: Downstream | E48: Use of sold products | F48: 861.11502 | G48: 861.11502
B49: 3 | C49: 12 | D49: Downstream | E49: End of life treatment of sold products | F49: 20.476429 | G49: 20.476429
... B52: 3 | C52: 15 | D52: Downstream | E52: Investments | F52: 0 | G52: 0
B53: Total | F53: 119766.32 | G53: 119158.19

Sheet FY24
B2: FY24 Footprint by Entity Code
BO3: Divested | BP3: Divested
B4: Scope | C4: Category | D4: Upstream/Downstream | E4: Emission Source | F4: Diploma Total | G4: G3010 | H4: L2050 | I4: L3015 | J4: S7030 | K4: S7040 | L4: S7060 | M4: S7090 | N4: S6040 | O4: G5020 | P4: L2010 | Q4: L2020 | R4: L2030 | S4: L2040 | T4: S2050 | U4: S2060 | V4: C5520 | W4: S4030 | X4: G5040 | Y4: L2500 | Z4: L7010 | AA4: S4010 | AB4: C2540 | AC4: C4050 | AD4: C2090 | AE4: C2091 | AF4: c4030 | AG4: C7010 | AH4: G3045 | AI4: L2090 | AJ4: L5010 | AK4: S1030 | AL4: G5025 | AM4: HoIntSealsE | AN4: S1040 | AO4: S2210 | AP4: S7020 | AQ4: L2060 | AR4: L3025 | AS4: L7030 | AT4: S1010 | AU4: L2510 | AV4: L2700 | AW4: L7020 | AX4: S4020 | AY4: S6020 | AZ4: S6070 | BA4: C2530 | BB4: c1010 | BC4: C1040 | BD4: C2040 | BE4: C2041 | BF4: C2042 | BG4: C2043 | BH4: C2080 | BI4: C2551 | BJ4: C2552 | BK4: C2553 | BL4: C2554 | BM4: C2555 | BN4: C3510 | BO4: C5010 | BP4: C6020 | BQ4: C8010 | BR4: C9010 | BS4: C9050 | BT4: G2010 | BU4: G3015 | BV4: G3020 | BW4: G3041 | BX4: G4010 | BY4: G5005 | BZ4: G5010 | CA4: HoControls | CB4: HoGrp | CC4: HoIntSeals | CD4: HoLS | CE4: L5020 | CF4: R1100 | CG4: R1120 | CH4: R1140 | CI4: R1170 | CJ4: R1180 | CK4: R1190 | CL4: R1210 | CM4: R1220 | CN4: R1230 | CO4: R1240 | CP4: R2100 | CQ4: R2110 | CR4: R2120 | CS4: R2130 | CT4: R2150 | CU4: R2160 | CV4: R2170 | CW4: R2180 | CX4: R2190 | CY4: R2210 | CZ4: R2220 | DA4: R3100 | DB4: R4100 | DC4: R4110 | DD4: R4120 | DE4: R4130 | DF4: R4140 | DG4: R4150 | DH4: R4160 | DI4: R5100 | DJ4: R5110 | DK4: R5120 | DL4: R9100 | DM4: S3010 | DN4: S3030 | DO4: S4040 | DP4: S4050 | DQ4: S9010 | DR4: C1510 | DS4: C1520 | DT4: C1530 | DU4: C2045 | DV4: C2046 | DW4: C2571 | DX4: C2572 | DY4: C2573 | DZ4: C2574 | EA4: C2575 | EB4: C2576 | EC4: C2577 | ED4: C2578 | EE4: C3040 | EF4: C4510 | EG4: C5510 | EH4: C8500 | EI4: G3025 | EJ4: G5015 | EK4: HoControlsU | EL4: HoDHI | EM4: HoLSU | EN4: HoNaSeals | EO4: LCAoem | EP4: S1020 | EQ4: S2010 | ER4: S2025 | ES4: S2026 | ET4: S2310 | EU4: S8010 | EV4: S8020 | EW4: S8030
B5: 1 | C5: - | D5: Internal | E5: All Scope 1 | F5: 3875.1797 | G5: 0 | H5: 0 | I5: 0.603811 | J5: 31.250352 | K5: 0 | L5: 359.71836 | M5: 0 | N5: 16.293485 | O5: 0 | P5: 0 | Q5: 61.688106 | R5: 67.284091 | S5: 57.991748 | T5: 1.7636592 | U5: 0.23839808 | V5: 0 | W5: 0 | X5: 0 | Y5: 69.583192 | Z5: 0 | AA5: 47.56803 | AB5: 0 | AC5: 41.879823 | AD5: 19.794807 | AE5: 0 | AF5: 77.90626 | AG5: 22.504836 | AH5: 0 | AI5: 86.711815 | AJ5: 387.94081 | AK5: 15.857309 | AL5: 0 | AM5: 0 | AN5: 0 | AO5: 10.317098 | AP5: 2.8020755 | AQ5: 0 | AR5: 8.2696834 | AS5: 0 | AT5: 60.870391 | AU5: 3.7419149 | AV5: 27.955154 | AW5: 0 | AX5: 12.958316 | AY5: 25.703715 | AZ5: 0 | BA5: 0 | BB5: 12.826717 | BC5: 0 | BD5: 35.470791 | BE5: 0 | BF5: 0 | BG5: 0 | BH5: 65.968327 | BI5: 0 | BJ5: 0 | BK5: 0 | BL5: 0 | BM5: 0 | BN5: 0 | BO5: 0 | BP5: 0 | BQ5: 10.844279 | BR5: 2.0692019 | BS5: 10.030795 | BT5: 0 | BU5: 0 | BV5: 0 | BW5: 0 | BX5: 0 | BY5: 0 | BZ5: 0 | CA5: 0 | CB5: 0 | CC5: 0 | CD5: 0 | CE5: 50.127875 | CF5: 9.1817347 | CG5: 0.84429744 | CH5: 3.2942677 | CI5: 116.67087 | CJ5: 58.568671 | CK5: 121.04779 | CL5: 6.4973492 | CM5: 53.279166 | CN5: 24.441489 | CO5: 0.77645211 | CP5: 0 | CQ5: 1.1139373 | CR5: 20.93273 | CS5: 75.5578 | CT5: 45.004928 | CU5: 9.4170109 | CV5: 2.1150556 | CW5: 0.60500428 | CX5: 6.0488837 | CY5: 19.532842 | CZ5: 2.298595 | DA5: 299.19743 | DB5: 17.518367 | DC5: 1.834125 | DD5: 10.61409 | DE5: 19.534766 | DF5: 1.2685995 | DG5: 7.9055066 | DH5: 5.4479694 | DI5: 13.976011 | DJ5: 0 | DK5: 0 | DL5: 0 | DM5: 21.213638 | DN5: 1.8687369 | DO5: 9.2364518 | DP5: 9.0207752 | DQ5: 10.318549 | DR5: 32.892946 | DS5: 72.016061 | DT5: 34.394964 | DU5: 1.330162 | DV5: 4.4244245 | DW5: 0 | DX5: 0 | DY5: 0 | DZ5: 0 | EA5: 0 | EB5: 0 | EC5: 0 | ED5: 0 | EE5: 8.7181577 | EF5: 0.42302362 | EG5: 0 | EH5: 584.04009 | EI5: 0 | EJ5: 0 | EK5: 0 | EL5: 0 | EM5: 0 | EN5: 0 | EO5: 85.604518 | EP5: 0 | EQ5: 0 | ER5: 87.557771 | ES5: 0 | ET5: 50.662481 | EU5: 98.309505 | EV5: 17.725172 | EW5: 84.361255
B6: 2 | C6: - | D6: Internal | E6: All Scope 2 MB | F6: 3806.853 | G6: 0 | H6: 0 | I6: 95.811883 | J6: 17.267135 | K6: 0 | L6: 96.247731 | M6: 8.466403 | N6: 25.573495 | O6: 0 | P6: 0 | Q6: 19.604748 | R6: 10.041526 | S6: 22.481846 | T6: 10.395673 | U6: 13.879195 | V6: 0 | W6: 0 | X6: 0 | Y6: 58.382975 | Z6: 14.578841 | AA6: 122.70358 | AB6: 0 | AC6: 4.4504834 | AD6: 30.667872 | AE6: 0 | AF6: 63.797452 | AG6: 3.461258 | AH6: 0 | AI6: 61.099649 | AJ6: 56.421951 | AK6: 9.3335469 | AL6: 0 | AM6: 0 | AN6: 0 | AO6: 4.7763971 | AP6: 1.0650326 | AQ6: 0 | AR6: 3.62881 | AS6: 2.4047923 | AT6: 24.862685 | AU6: 0.86675784 | AV6: 6.3703897 | AW6: 0.92973845 | AX6: 0.63308136 | AY6: 68.174637 | AZ6: 0 | BA6: 3.2130198 | BB6: 37.936628 | BC6: 0 | BD6: 3.3037332 | BE6: 0 | BF6: 0 | BG6: 0 | BH6: 138.6884 | BI6: 0 | BJ6: 0 | BK6: 0 | BL6: 0 | BM6: 0 | BN6: 0 | BO6: 0 | BP6: 0 | BQ6: 73.299494 | BR6: 40.19687 | BS6: 33.988108 | BT6: 29.780134 | BU6: 0 | BV6: 0 | BW6: 0 | BX6: 0 | BY6: 0 | BZ6: 0 | CA6: 0 | CB6: 0 | CC6: 0 | CD6: 0 | CE6: 4.02683 | CF6: 0 | CG6: 0 | CH6: 0 | CI6: 21.965864 | CJ6: 20.995397 | CK6: 61.582691 | CL6: 6.7272039 | CM6: 25.292987 | CN6: 5.7968199 | CO6: 1.2642565 | CP6: 0 | CQ6: 25.150548 | CR6: 15.941614 | CS6: 18.006896 | CT6: 90.340661 | CU6: 33.476075 | CV6: 25.219722 | CW6: 6.4507881 | CX6: 6.8423853 | CY6: 2.463696 | CZ6: 2.8590452 | DA6: 61.216775 | DB6: 11.929207 | DC6: 13.215034 | DD6: 3.9018723 | DE6: 8.7507523 | DF6: 6.5332347 | DG6: 3.6450204 | DH6: 21.737444 | DI6: 4.7414862 | DJ6: 0 | DK6: 0 | DL6: 0 | DM6: 71.001297 | DN6: 12.71675 | DO6: 7.4887874 | DP6: 26.08877 | DQ6: 73.349182 | DR6: 15.505511 | DS6: 173.44904 | DT6: 53.381662 | DU6: 17.005805 | DV6: 13.099644 | DW6: 0 | DX6: 0 | DY6: 0 | DZ6: 0 | EA6: 0 | EB6: 0 | EC6: 0 | ED6: 0 | EE6: 13.58332 | EF6: 17.376125 | EG6: 301.56429 | EH6: 662.94928 | EI6: 0 | EJ6: 0 | EK6: 0 | EL6: 0 | EM6: 0 | EN6: 0 | EO6: 94.946748 | EP6: 0 | EQ6: 0 | ER6: 0.16905365 | ES6: 0 | ET6: 40.437292 | EU6: 355.492 | EV6: 67.921801 | EW6: 60.466327
B7: 2 | D7: Internal | E7: All Scope 2 LB | F7: 5832.2143 | G7: 0 | H7: 0 | I7: 165.39869 | J7: 41.257148 | K7: 0 | L7: 96.247731 | M7: 8.466403 | N7: 25.573495 | O7: 0 | P7: 0 | Q7: 19.604748 | R7: 10.041526 | S7: 22.481846 | T7: 10.395673 | U7: 13.879195 | V7: 0 | W7: 0 | X7: 0 | Y7: 28.920978 | Z7: 2.4867296 | AA7: 57.624148 | AB7: 0 | AC7: 7.0017712 | AD7: 15.62568 | AE7: 0 | AF7: 32.505633 | AG7: 11.775399 | AH7: 0 | AI7: 58.353325 | AJ7: 45.14072 | AK7: 5.8324688 | AL7: 0 | AM7: 0 | AN7: 0 | AO7: 2.7937267 | AP7: 1.675574 | AQ7: 0 | AR7: 3.62881 | AS7: 0.0281211 | AT7: 337.43962 | AU7: 0.14353938 | AV7: 1.054968 | AW7: 0.15396928 | AX7: 0.1048414 | AY7: 68.174637 | AZ7: 0 | BA7: 3.2130198 | BB7: 20.223195 | BC7: 0 | BD7: 31.448188 | BE7: 0 | BF7: 0 | BG7: 0 | BH7: 83.031067 | BI7: 0 | BJ7: 0 | BK7: 0 | BL7: 0 | BM7: 0 | BN7: 0 | BO7: 0 | BP7: 0 | BQ7: 96.347301 | BR7: 21.428081 | BS7: 18.118324 | BT7: 15.875145 | BU7: 0 | BV7: 0 | BW7: 0 | BX7: 0 | BY7: 0 | BZ7: 0 | CA7: 0 | CB7: 0 | CC7: 0 | CD7: 0 | CE7: 2.6222139 | CF7: 0 | CG7: 0 | CH7: 0 | CI7: 11.709526 | CJ7: 11.192191 | CK7: 32.828399 | CL7: 3.5861267 | CM7: 13.483144 | CN7: 3.0901591 | CO7: 0.67394775 | CP7: 0 | CQ7: 13.407212 | CR7: 8.4981291 | CS7: 9.5990865 | CT7: 48.15865 | CU7: 17.84537 | CV7: 13.444088 | CW7: 3.4387754 | CX7: 3.6475274 | CY7: 1.313343 | CZ7: 1.5240951 | DA7: 32.633337 | DB7: 8.3088661 | DC7: 7.0446485 | DD7: 2.0800036 | DE7: 4.6648365 | DF7: 3.4827259 | DG7: 1.9430814 | DH7: 11.58776 | DI7: 2.5275836 | DJ7: 0 | DK7: 0 | DL7: 0 | DM7: 37.849253 | DN7: 6.7790241 | DO7: 3.9921103 | DP7: 13.907358 | DQ7: 39.10086 | DR7: 27.958673 | DS7: 174.71997 | DT7: 51.229222 | DU7: 15.312588 | DV7: 11.812422 | DW7: 0 | DX7: 0 | DY7: 0 | DZ7: 0 | EA7: 0 | EB7: 0 | EC7: 0 | ED7: 0 | EE7: 13.035617 | EF7: 17.048447 | EG7: 298.29474 | EH7: 2515.132 | EI7: 0 | EJ7: 0 | EK7: 0 | EL7: 0 | EM7: 0 | EN7: 0 | EO7: 162.57693 | EP7: 0 | EQ7: 0 | ER7: 313.15167 | ES7: 0 | ET7: 37.461143 | EU7: 311.79972 | EV7: 63.896299 | EW7: 59.326055
B8: 3 | C8: 1 | D8: Upstream | E8: Purchased goods and services | F8: 176935.41 | G8: 0.8721947 | H8: 2010.3685 | I8: 7647.2866 | J8: 1262.0902 | K8: 15.433206 | L8: 2209.6274 | M8: 29.538877 | N8: 859.01725 | O8: -29.180723 | P8: 139.30915 | Q8: 8316.4093 | R8: 0 | S8: 11663.825 | T8: 1036.6033 | U8: 1233.7951 | V8: 0.16646869 | W8: 26.973066 | X8: -18.18906 | Y8: 2863.2553 | Z8: 426.03582 | AA8: 908.91212 | AB8: 1.8756326 | AC8: 745.37167 | AD8: 465.77633 | AE8: 263.12712 | AF8: 4385.563 | AG8: 2160.1081 | AH8: 7.5213041 | AI8: 5122.6784 | AJ8: 5653.9814 | AK8: 1211.1992 | AL8: 69.083754 | AM8: 1.7456557 | AN8: 7.3613004 | AO8: 109.97745 | AP8: 186.09602 | AQ8: 385.76593 | AR8: 1027.5266 | AS8: 85.289998 | AT8: 4332.8271 | AU8: 89.184021 | AV8: 2567.1051 | AW8: 197.28824 | AX8: 548.28511 | AY8: 1764.6961 | AZ8: -97.108868 | BA8: 2.9498422 | BB8: 1719.616 | BC8: 0.71183374 | BD8: 3349.1334 | BE8: -36.361797 | BF8: 19.307441 | BG8: 131.72537 | BH8: 5793.1111 | BI8: 6.252059 | BJ8: 5.5354051 | BK8: 0.98738488 | BL8: 6.1653801 | BM8: 11.026682 | BN8: 1182.8719 | BO8: 0 | BP8: 0 | BQ8: 1012.3631 | BR8: 2285.934 | BS8: 905.15701 | BT8: 1311.5468 | BU8: -352.30999 | BV8: 0.14167143 | BW8: -206.98527 | BX8: 1.0407747 | BY8: 0 | BZ8: -161.08845 | CA8: 13.219823 | CB8: -16.90234 | CC8: 3.1256798 | CD8: 3.2925178 | CE8: 874.16528 | CF8: -0.058718258 | CG8: 0 | CH8: 0 | CI8: 327.9224 | CJ8: 407.7939 | CK8: 1227.561 | CL8: 321.55196 | CM8: 344.19157 | CN8: 196.63274 | CO8: 15.34475 | CP8: 0 | CQ8: 699.80879 | CR8: 422.45111 | CS8: 475.44476 | CT8: 1235.1104 | CU8: -36.016819 | CV8: 237.30294 | CW8: 379.73902 | CX8: 214.13676 | CY8: 343.96222 | CZ8: 31.530502 | DA8: 1830.1142 | DB8: 138.34436 | DC8: 174.53012 | DD8: 95.047558 | DE8: 214.20053 | DF8: 130.01545 | DG8: 83.899871 | DH8: 369.0978 | DI8: 224.69234 | DJ8: 0.33025397 | DK8: 1.573045 | DL8: 0 | DM8: 621.34634 | DN8: 106.48322 | DO8: 63.124836 | DP8: 435.97491 | DQ8: 187.39171 | DR8: 609.62816 | DS8: 1440.3883 | DT8: 491.94533 | DU8: 1817.2731 | DV8: 1094.8987 | DW8: 19.223449 | DX8: 6.8161928 | DY8: 27.943824 | DZ8: 5.7423369 | EA8: 15.348146 | EB8: 59.571898 | EC8: 11.074176 | ED8: 3.0586101 | EE8: 945.59798 | EF8: 1785.7581 | EG8: 5097.5533 | EH8: 15102.957 | EI8: 426.63942 | EJ8: 423.71104 | EK8: 51.384639 | EL8: -78.231483 | EM8: 26.846844 | EN8: 0 | EO8: 18717.241 | EP8: 184.0452 | EQ8: 137.56175 | ER8: 11780.202 | ES8: 0.037366398 | ET8: 1068.6979 | EU8: 12762.097 | EV8: 259.42519 | EW8: 1360.1896
B9: 3 | C9: 2 | D9: Upstream | E9: Capital goods | F9: 6973.2078 | G9: 0 | H9: 0 | I9: 348.20845 | J9: 34.71215 | K9: 0 | L9: 93.780348 | M9: -10.655506 | N9: 3.1111982 | O9: 0 | P9: 4.6198864 | Q9: 164.84878 | R9: 0 | S9: 2513.8795 | T9: 3.0406871 | U9: 0.98931676 | V9: 0 | W9: 0 | X9: 0 | Y9: 34.156703 | Z9: 3.7576343 | AA9: 132.03883 | AB9: 0 | AC9: 3.1755286 | AD9: 11.155968 | AE9: 0 | AF9: 41.860002 | AG9: 3.3563669 | AH9: 0 | AI9: 56.567215 | AJ9: 46.870157 | AK9: 2.2906976 | AL9: 0 | AM9: 0 | AN9: 0 | AO9: 0 | AP9: 5.0600965 | AQ9: 0 | AR9: 32.169846 | AS9: 0 | AT9: 314.79994 | AU9: 0 | AV9: 60.91277 | AW9: 0 | AX9: 0 | AY9: 72.896653 | AZ9: 0 | BA9: 0.86844155 | BB9: 38.851851 | BC9: 0 | BD9: 36.434441 | BE9: 0 | BF9: 0 | BG9: 0 | BH9: 24.513469 | BI9: 0 | BJ9: 0 | BK9: 0 | BL9: 0 | BM9: 0 | BN9: 0 | BO9: 0 | BP9: 0 | BQ9: 0 | BR9: 1045.4001 | BS9: 0 | BT9: 28.866299 | BU9: 0 | BV9: 0 | BW9: 0 | BX9: 0 | BY9: 0 | BZ9: 0 | CA9: 0 | CB9: 0 | CC9: 0 | CD9: 0 | CE9: 0 | CF9: 0 | CG9: 0 | CH9: 0 | CI9: 21.975727 | CJ9: 19.192587 | CK9: 74.756951 | CL9: 18.912969 | CM9: 6.9732393 | CN9: 10.912111 | CO9: -10.803325 | CP9: 0 | CQ9: 0.52626622 | CR9: 7.3713153 | CS9: 2.9622342 | CT9: 99.629711 | CU9: 0 | CV9: 14.322131 | CW9: 9.3869463 | CX9: 14.787441 | CY9: 0 | CZ9: 0 | DA9: 80.846966 | DB9: 2.0807742 | DC9: 0 | DD9: 0 | DE9: 0 | DF9: 0 | DG9: 0 | DH9: 64.669516 | DI9: 63.066634 | DJ9: 0 | DK9: 0 | DL9: 0 | DM9: 0 | DN9: 0 | DO9: 0 | DP9: 0 | DQ9: 72.225444 | DR9: 0 | DS9: 132.94017 | DT9: 15.797961 | DU9: 44.846276 | DV9: 0 | DW9: 0 | DX9: 0 | DY9: 0 | DZ9: 0 | EA9: 0 | EB9: 0 | EC9: 0 | ED9: 0 | EE9: 5.8449131 | EF9: 46.045781 | EG9: 0 | EH9: 638.64136 | EI9: 0 | EJ9: 0 | EK9: 0 | EL9: 0 | EM9: 0 | EN9: 0 | EO9: 34.878088 | EP9: 0 | EQ9: 0 | ER9: 193.02898 | ES9: 0 | ET9: 10.59269 | EU9: 124.25809 | EV9: 0 | EW9: 0
B10: 3 | C10: 3 | D10: Upstream | E10: Fuel and energy related activities | F10: 2303.622 | G10: 0 | H10: 0 | I10: 40.415306 | J10: 17.514953 | K10: 0 | L10: 111.09041 | M10: 2.0614103 | N10: 10.850961 | O10: 0 | P10: 0 | Q10: 16.131968 | R10: 14.116355 | S10: 16.358227 | T10: 3.4414831 | U10: 4.2464453 | V10: 0 | W10: 0 | X10: 0 | Y10: 26.476384 | Z10: 1.4885631 | AA10: 27.975271 | AB10: 0 | AC10: 13.235116 | AD10: 7.7821898 | AE10: 0 | AF10: 26.270696 | AG10: 8.0468179 | AH10: 0 | AI10: 37.476628 | AJ10: 97.244416 | AK10: 4.7552268 | AL10: 0 | AM10: 0 | AN10: 0 | AO10: 2.5848988 | AP10: 1.271227 | AQ10: 0 | AR10: 3.0908974 | AS10: 0.0050777621 | AT10: 126.90289 | AU10: 1.0800854 | AV10: 8.048932 | AW10: 0.17874703 | AX10: 3.3880062 | AY10: 24.535875 | AZ10: 0 | BA10: 0.88421056 | BB10: 9.6359794 | BC10: 0 | BD10: 17.223867 | BE10: 0 | BF10: 0 | BG10: 0 | BH10: 38.00683 | BI10: 0 | BJ10: 0 | BK10: 0 | BL10: 0 | BM10: 0 | BN10: 0 | BO10: 0 | BP10: 0 | BQ10: 34.372264 | BR10: 7.6136358 | BS10: 8.4246454 | BT10: 5.3588627 | BU10: 0 | BV10: 0 | BW10: 0 | BX10: 0 | BY10: 0 | BZ10: 0 | CA10: 0 | CB10: 0 | CC10: 0 | CD10: 0 | CE10: 13.067979 | CF10: 2.2326305 | CG10: 0.20529936 | CH10: 0.80103411 | CI10: 31.300351 | CJ10: 17.60405 | CK10: 35.36991 | CL10: 2.3657466 | CM10: 15.037998 | CN10: 6.3610408 | CO10: 0.41630197 | CP10: 0 | CQ10: 4.7189347 | CR10: 7.2755846 | CS10: 18.667309 | CT10: 26.592738 | CU10: 8.3137784 | CV10: 4.8875761 | CW10: 1.2942186 | CX10: 2.4150691 | CY10: 5.00433 | CZ10: 1.1104532 | DA10: 82.749267 | DB10: 5.9525214 | DC10: 2.8262432 | DD10: 2.8342866 | DE10: 5.770231 | DF10: 1.4863242 | DG10: 2.3001524 | DH10: 5.1999261 | DI10: 4.2506557 | DJ10: 0 | DK10: 0 | DL10: 0 | DM10: 16.546573 | DN10: 2.5970116 | DO10: 3.1458829 | DP10: 7.0339859 | DQ10: 15.277428 | DR10: 12.928057 | DS10: 52.099037 | DT10: 17.368085 | DU10: 6.0450314 | DV10: 5.2493412 | DW10: 0 | DX10: 0 | DY10: 0 | DZ10: 0 | EA10: 0 | EB10: 0 | EC10: 0 | ED10: 0 | EE10: 4.2177422 | EF10: 5.6239787 | EG10: 66.42807 | EH10: 667.61581 | EI10: 0 | EJ10: 0 | EK10: 0 | EL10: 0 | EM10: 0 | EN10: 0 | EO10: 49.925633 | EP10: 0 | EQ10: 0 | ER10: 87.293075 | ES10: 0 | ET10: 21.62343 | EU10: 112.89389 | EV10: 12.104171 | EW10: 39.608035
B11: 3 | C11: 4 | D11: Upstream | E11: Upstream transportation and distribution | F11: 38920.499 | G11: 0 | H11: -40.501054 | I11: 265.00559 | J11: 34.632583 | K11: 0.096040127 | L11: -158.69976 | M11: -1.3125124 | N11: -29.480306 | O11: 0 | P11: 0 | Q11: 604.79704 | R11: 0 | S11: 2021.1734 | T11: 439.55136 | U11: 320.55799 | V11: 0 | W11: 1.8055484 | X11: 0 | Y11: 165.19699 | Z11: 172.43907 | AA11: 571.27706 | AB11: 0 | AC11: 211.37554 | AD11: 0.23726395 | AE11: 63.865557 | AF11: 39.303191 | AG11: 70.38 | AH11: 0 | AI11: 656.40885 | AJ11: 438.37502 | AK11: 32.709627 | AL11: 0 | AM11: 0 | AN11: 0 | AO11: 29.713849 | AP11: 5.7555091 | AQ11: -19.352695 | AR11: 19.881039 | AS11: 1.1389487 | AT11: 10102.633 | AU11: 40.120768 | AV11: 219.5635 | AW11: 2.4166476 | AX11: 60.746784 | AY11: 92.036233 | AZ11: 0 | BA11: 0.061851562 | BB11: 379.2778 | BC11: 0 | BD11: 735.62315 | BE11: 6.4975291 | BF11: 0 | BG11: 0 | BH11: 657.41934 | BI11: 0 | BJ11: 0 | BK11: 0 | BL11: 0 | BM11: 0 | BN11: 269.8217 | BO11: 0 | BP11: 0 | BQ11: 1020.5954 | BR11: 585.36536 | BS11: 504.43269 | BT11: 0 | BU11: 0 | BV11: 0 | BW11: 0 | BX11: 0 | BY11: 0 | BZ11: 0 | CA11: 0 | CB11: 0 | CC11: 0 | CD11: 0 | CE11: 3.5819875 | CF11: 0 | CG11: 0 | CH11: 0 | CI11: 37.480556 | CJ11: 161.76313 | CK11: 177.60861 | CL11: 178.09119 | CM11: 28.959928 | CN11: 16.063947 | CO11: 0.80060942 | CP11: 0 | CQ11: 612.327 | CR11: 62.846634 | CS11: 53.204699 | CT11: 496.13173 | CU11: 56.60694 | CV11: 166.72339 | CW11: 0 | CX11: 24.036026 | CY11: 6.2233198 | CZ11: 0 | DA11: 255.01915 | DB11: 52.19935 | DC11: 49.931313 | DD11: 15.628482 | DE11: 21.255478 | DF11: 62.004521 | DG11: 15.204353 | DH11: 101.05658 | DI11: 0 | DJ11: 0 | DK11: 0 | DL11: 0 | DM11: 518.01847 | DN11: 62.824399 | DO11: 12.72797 | DP11: 166.3494 | DQ11: 125.5742 | DR11: 76.022625 | DS11: 413.64332 | DT11: 120.4121 | DU11: 22.101756 | DV11: 119.22582 | DW11: 0 | DX11: 0 | DY11: 0 | DZ11: 0 | EA11: 0.087841033 | EB11: 0 | EC11: 0 | ED11: 0 | EE11: 398.45291 | EF11: 313.8516 | EG11: 818.57858 | EH11: 708.67011 | EI11: 0 | EJ11: 0 | EK11: 0 | EL11: 0 | EM11: 0 | EN11: 0 | EO11: 2844.6972 | EP11: 173.29456 | EQ11: 0 | ER11: 6858.5142 | ES11: 0 | ET11: 371.07753 | EU11: 988.83404 | EV11: 9.098579 | EW11: 550.75082
B12: 3 | C12: 5 | D12: Upstream | E12: Waste generated in operations | F12: 625.92365 | G12: 0 | H12: 0 | I12: 4.645268 | J12: 6.033954 | K12: 0 | L12: 20.820421 | M12: 0 | N12: 0 | O12: 0 | P12: 0 | Q12: 10.559898 | R12: 0 | S12: 6.7825016 | T12: 3.8490409 | U12: 3.6754289 | V12: 0 | W12: 0 | X12: 0 | Y12: 0.15239302 | Z12: 0 | AA12: 16.713785 | AB12: 0 | AC12: 0.3561799 | AD12: 0.33120514 | AE12: 0 | AF12: 0.16359236 | AG12: 0.066404453 | AH12: 0 | AI12: 0.43396653 | AJ12: 0.29836261 | AK12: 0.18707556 | AL12: 0 | AM12: 0 | AN12: 0 | AO12: 0.023991069 | AP12: 0 | AQ12: 0 | AR12: 2.0479987 | AS12: 0 | AT12: 13.605443 | AU12: 0.0014103342 | AV12: 0.03541221 | AW12: 0 | AX12: 0.43731151 | AY12: 0.43941526 | AZ12: 0 | BA12: 0 | BB12: 0.14328354 | BC12: 0 | BD12: 1.7672723 | BE12: 0 | BF12: 0 | BG12: 0 | BH12: 0.53509362 | BI12: 0 | BJ12: 0 | BK12: 0 | BL12: 0 | BM12: 0 | BN12: 0 | BO12: 0 | BP12: 0 | BQ12: 14.567852 | BR12: 1.4368834 | BS12: 2.3900161 | BT12: 0.42990367 | BU12: 0 | BV12: 0 | BW12: 0 | BX12: 0 | BY12: 0 | BZ12: 0 | CA12: 0 | CB12: 0 | CC12: 0 | CD12: 0 | CE12: 0.0026027077 | CF12: 0 | CG12: 0 | CH12: 0 | CI12: 0.076933731 | CJ12: 0.076208755 | CK12: 0.22872242 | CL12: 0.045672391 | CM12: 0.056302208 | CN12: 0.017917655 | CO12: 0 | CP12: 0 | CQ12: 11.211539 | CR12: 4.2134073 | CS12: 0.025972586 | CT12: 34.882264 | CU12: 0 | CV12: 3.3755734 | CW12: 0.088693804 | CX12: 1.2300059 | CY12: 0.035848131 | CZ12: 0.034792945 | DA12: 16.454826 | DB12: 0.067006798 | DC12: 1.2937811 | DD12: 0.66227326 | DE12: 0.90486117 | DF12: 0.32601323 | DG12: 0.23857961 | DH12: 0.24212874 | DI12: 0 | DJ12: 0 | DK12: 0 | DL12: 0 | DM12: 0.17067704 | DN12: 0.25799939 | DO12: 0.086931013 | DP12: 0.31287778 | DQ12: 8.8947534 | DR12: 16.599201 | DS12: 35.474267 | DT12: 49.787398 | DU12: 5.6593702 | DV12: 5.4080686 | DW12: 0 | DX12: 0 | DY12: 0 | DZ12: 0 | EA12: 0 | EB12: 0 | EC12: 0 | ED12: 0 | EE12: 0.096816879 | EF12: 6.2961992 | EG12: 0 | EH12: 224.61131 | EI12: 0 | EJ12: 0 | EK12: 0 | EL12: 0 | EM12: 0 | EN12: 0 | EO12: 11.716549 | EP12: 0 | EQ12: 0 | ER12: 4.0045948 | ES12: 0 | ET12: 4.0552247 | EU12: 43.365435 | EV12: 10.645705 | EW12: 9.7575787
B13: 3 | C13: 6 | D13: Upstream | E13: Business travel | F13: 6734.7391 | G13: 0 | H13: 0.31218678 | I13: 494.18678 | J13: 30.64501 | K13: 0.0028441781 | L13: 274.35464 | M13: 0.66492137 | N13: 23.83833 | O13: 0 | P13: 104.8295 | Q13: 415.44569 | R13: 0 | S13: 408.77813 | T13: 36.462516 | U13: 21.232443 | V13: 0.13659834 | W13: 1.2075906 | X13: 0 | Y13: 105.18752 | Z13: 45.37167 | AA13: 54.764349 | AB13: 5.3543504 | AC13: 19.627662 | AD13: 17.847096 | AE13: 13.97817 | AF13: 37.297435 | AG13: 11.306089 | AH13: 0 | AI13: 106.4044 | AJ13: 118.93782 | AK13: 3.748238 | AL13: 0 | AM13: 0 | AN13: 6.935096 | AO13: 0.12949656 | AP13: 7.7992108 | AQ13: 0 | AR13: 95.014983 | AS13: 0.16375331 | AT13: 98.451603 | AU13: 3.6841406 | AV13: 79.236526 | AW13: 4.0009755 | AX13: 13.889709 | AY13: 82.331408 | AZ13: 0 | BA13: 10.810296 | BB13: 36.960135 | BC13: 0 | BD13: 0 | BE13: 0.84516469 | BF13: 17.894337 | BG13: 88.433488 | BH13: 206.57922 | BI13: 33.09702 | BJ13: 3.7237806 | BK13: 4.5899532 | BL13: 5.9614622 | BM13: 18.351565 | BN13: 30.295876 | BO13: 0 | BP13: 0 | BQ13: 0 | BR13: 127.09267 | BS13: 0 | BT13: 845.83811 | BU13: 0 | BV13: 0 | BW13: 0 | BX13: 0 | BY13: 0 | BZ13: 0 | CA13: 69.244379 | CB13: -334.18737 | CC13: 98.743867 | CD13: 143.98194 | CE13: 13.989611 | CF13: 0.75516878 | CG13: 0 | CH13: 0 | CI13: 50.093368 | CJ13: 20.513426 | CK13: 60.329215 | CL13: 0.83498807 | CM13: 17.977318 | CN13: 9.5361844 | CO13: 0 | CP13: 0 | CQ13: 23.80685 | CR13: 4.097923 | CS13: 39.709521 | CT13: 42.561778 | CU13: 5.6089168 | CV13: 3.4274847 | CW13: 4.2169593 | CX13: 4.0565082 | CY13: 19.350766 | CZ13: 10.561155 | DA13: 111.23318 | DB13: 10.163621 | DC13: 2.9989626 | DD13: 4.5504753 | DE13: 1.0814925 | DF13: 0.17392959 | DG13: 1.5707149 | DH13: 3.1577053 | DI13: 65.477326 | DJ13: 0 | DK13: 0 | DL13: 0 | DM13: 16.715899 | DN13: 3.3994578 | DO13: 0.96310734 | DP13: 4.4461155 | DQ13: 6.3758635 | DR13: 2.4344969 | DS13: 77.245197 | DT13: 6.0542016 | DU13: 0 | DV13: 39.405869 | DW13: 35.97314 | DX13: 7.7892868 | DY13: 8.6321819 | DZ13: 0.93722185 | EA13: 0 | EB13: 13.028306 | EC13: 1.9304315 | ED13: 3.185055 | EE13: 60.553848 | EF13: 37.397679 | EG13: 65.362976 | EH13: 366.05318 | EI13: 12.710589 | EJ13: 0 | EK13: 0 | EL13: 0 | EM13: 0 | EN13: 0 | EO13: 197.9463 | EP13: 0 | EQ13: 88.69466 | ER13: 444.5822 | ES13: 0 | ET13: 79.885349 | EU13: 431.29619 | EV13: 26.916358 | EW13: 11.17461
B14: 3 | C14: 7 | D14: Upstream | E14: Employee commuting | F14: 6955.0292 | G14: 0 | H14: 0 | I14: 235.02868 | J14: 105.01638 | K14: 0 | L14: 260.18484 | M14: 0 | N14: 36.964505 | O14: 0 | P14: 5.789425 | Q14: 137.01639 | R14: 0 | S14: 191.05102 | T14: 51.634637 | U14: 40.036995 | V14: 0 | W14: 0 | X14: 0 | Y14: 72.968117 | Z14: 11.57885 | AA14: 65.357196 | AB14: 1.9298083 | AC14: 35.473985 | AD14: 17.247428 | AE14: 0 | AF14: 141.90248 | AG14: 44.06172 | AH14: 0 | AI14: 150.78718 | AJ14: 199.03145 | AK14: 21.227892 | AL14: 0 | AM14: 0 | AN14: 0 | AO14: 5.789425 | AP14: 9.6490416 | AQ14: 0 | AR14: 21.070718 | AS14: 0 | AT14: 165.23651 | AU14: 5.0919359 | AV14: 35.541673 | AW14: 1.9298083 | AX14: 20.823211 | AY14: 153.43004 | AZ14: 0 | BA14: 5.789425 | BB14: 62.70779 | BC14: 1.9298083 | BD14: 167.25192 | BE14: 0 | BF14: 0 | BG14: 0 | BH14: 153.4869 | BI14: 0 | BJ14: 0 | BK14: 0 | BL14: 0 | BM14: 0 | BN14: 0 | BO14: 0 | BP14: 0 | BQ14: 0 | BR14: 369.51388 | BS14: 0 | BT14: 30.501764 | BU14: 0 | BV14: 0 | BW14: 0 | BX14: 0 | BY14: 11.57885 | BZ14: 0 | CA14: 5.789425 | CB14: 0 | CC14: 3.8596166 | CD14: 1.9298083 | CE14: 9.6490416 | CF14: 0 | CG14: 0 | CH14: 0 | CI14: 62.159937 | CJ14: 21.470944 | CK14: 138.05535 | CL14: 22.179089 | CM14: 39.995232 | CN14: 11.184519 | CO14: 0 | CP14: 0 | CQ14: 34.527686 | CR14: 28.977873 | CS14: 82.447725 | CT14: 78.856703 | CU14: 12.055882 | CV14: 10.976564 | CW14: 14.902218 | CX14: 5.4646721 | CY14: 17.384166 | CZ14: 17.368275 | DA14: 147.16414 | DB14: 12.935142 | DC14: 2.8128372 | DD14: 6.7566512 | DE14: 22.49746 | DF14: 9.1324412 | DG14: 3.2862438 | DH14: 131.22697 | DI14: 72.051124 | DJ14: 0 | DK14: 0 | DL14: 0 | DM14: 56.178116 | DN14: 15.438467 | DO14: 10.120996 | DP14: 33.657907 | DQ14: 64.363207 | DR14: 76.919226 | DS14: 185.52437 | DT14: 96.591199 | DU14: 93.72205 | DV14: 0 | DW14: 0 | DX14: 0 | DY14: 0 | DZ14: 0 | EA14: 0 | EB14: 0 | EC14: 0 | ED14: 0 | EE14: 24.726529 | EF14: 38.467201 | EG14: 119.64812 | EH14: 850.34221 | EI14: 9.6490416 | EJ14: 0 | EK14: 1.9298083 | EL14: 0 | EM14: 1.9298083 | EN14: 1.9298083 | EO14: 253.78324 | EP14: 0 | EQ14: 19.298083 | ER14: 443.47951 | ES14: 1.9298083 | ET14: 83.029441 | EU14: 341.76739 | EV14: 9.6490416 | EW14: 48.245208
B15: 3 | C15: 8 | D15: Upstream | E15: Upstream leased assets | F15: 2922.6612 | G15: 0 | H15: 0 | I15: 47.464027 | J15: 27.063455 | K15: 0 | L15: 67.035659 | M15: 3.1014448 | N15: 20.096701 | O15: 0 | P15: 2.1994779 | Q15: 11.338805 | R15: 0 | S15: 63.69127 | T15: 26.582746 | U15: 16.098465 | V15: 1.3994076 | W15: 1.8549607 | X15: 0 | Y15: 26.406405 | Z15: 3.5752459 | AA15: 76.724584 | AB15: 0 | AC15: 45.55548 | AD15: 6.421945 | AE15: 1.1851917 | AF15: 64.984249 | AG15: 9.7738499 | AH15: 0 | AI15: 10.207651 | AJ15: 31.138451 | AK15: 8.642342 | AL15: 0 | AM15: 0 | AN15: 0 | AO15: 5.1218884 | AP15: 16.43 | AQ15: 0 | AR15: 8.9700599 | AS15: 0 | AT15: 105.2735 | AU15: 4.1465538 | AV15: 27.675826 | AW15: 0 | AX15: 3.6553416 | AY15: 84.460048 | AZ15: 0 | BA15: 1.9129315 | BB15: 15.992137 | BC15: 0 | BD15: 7.9337396 | BE15: 6.4135779 | BF15: 1.3793996 | BG15: 18.739242 | BH15: 57.55861 | BI15: 0 | BJ15: 0 | BK15: 0 | BL15: 0 | BM15: 0 | BN15: 0 | BO15: 0 | BP15: 0 | BQ15: 0 | BR15: 172.29352 | BS15: 0 | BT15: 61.66856 | BU15: 0 | BV15: 0 | BW15: 0 | BX15: 0 | BY15: 0 | BZ15: 0 | CA15: 0 | CB15: 0 | CC15: 0 | CD15: 0 | CE15: 3.8196361 | CF15: 0 | CG15: 0 | CH15: 0 | CI15: 10.467295 | CJ15: 14.998202 | CK15: 64.110869 | CL15: 9.3791391 | CM15: 20.173697 | CN15: 3.4862703 | CO15: 1.0465967 | CP15: 0 | CQ15: 39.344857 | CR15: 12.223541 | CS15: 16.007723 | CT15: 64.944389 | CU15: 1.8885248 | CV15: 1.9672655 | CW15: 4.9134736 | CX15: 5.7014577 | CY15: 12.190224 | CZ15: 3.7096934 | DA15: 45.898558 | DB15: 8.2195757 | DC15: 5.3208392 | DD15: 3.8642832 | DE15: 9.2854183 | DF15: 3.7633128 | DG15: 2.1518438 | DH15: 0 | DI15: 2.0606498 | DJ15: -8.7846951 | DK15: 0 | DL15: 0 | DM15: 35.284909 | DN15: 2.9155837 | DO15: 8.4257495 | DP15: 15.914858 | DQ15: 12.375314 | DR15: 7.281695 | DS15: 35.184835 | DT15: 9.7160662 | DU15: 3.5034516 | DV15: 29.827735 | DW15: 0 | DX15: 0 | DY15: 0 | DZ15: 0 | EA15: 6.9525544 | EB15: 5.441413 | EC15: 3.0858681 | ED15: 0 | EE15: 4.8625801 | EF15: 20.802004 | EG15: 0 | EH15: 696.14387 | EI15: 0 | EJ15: 0 | EK15: 0 | EL15: 0 | EM15: 0 | EN15: 0 | EO15: 138.24755 | EP15: 0 | EQ15: 0 | ER15: 132.42198 | ES15: 0 | ET15: 45.90264 | EU15: 122.7708 | EV15: 20.013203 | EW15: 31.267139
B16: 3 | C16: 9 | D16: Downstream | E16: Downstream transportation and distribution | F16: 0 | G16: 0 | H16: 0 | I16: 0 | J16: 0 | K16: 0 | L16: 0 | M16: 0 | N16: 0 | O16: 0 | P16: 0 | Q16: 0 | R16: 0 | S16: 0 | T16: 0 | U16: 0 | V16: 0 | W16: 0 | X16: 0 | Y16: 0 | Z16: 0 | AA16: 0 | AB16: 0 | AC16: 0 | AD16: 0 | AE16: 0 | AF16: 0 | AG16: 0 | AH16: 0 | AI16: 0 | AJ16: 0 | AK16: 0 | AL16: 0 | AM16: 0 | AN16: 0 | AO16: 0 | AP16: 0 | AQ16: 0 | AR16: 0 | AS16: 0 | AT16: 0 | AU16: 0 | AV16: 0 | AW16: 0 | AX16: 0 | AY16: 0 | AZ16: 0 | BA16: 0 | BB16: 0 | BC16: 0 | BD16: 0 | BE16: 0 | BF16: 0 | BG16: 0 | BH16: 0 | BI16: 0 | BJ16: 0 | BK16: 0 | BL16: 0 | BM16: 0 | BN16: 0 | BO16: 0 | BP16: 0 | BQ16: 0 | BR16: 0 | BS16: 0 | BT16: 0 | BU16: 0 | BV16: 0 | BW16: 0 | BX16: 0 | BY16: 0 | BZ16: 0 | CA16: 0 | CB16: 0 | CC16: 0 | CD16: 0 | CE16: 0 | CF16: 0 | CG16: 0 | CH16: 0 | CI16: 0 | CJ16: 0 | CK16: 0 | CL16: 0 | CM16: 0 | CN16: 0 | CO16: 0 | CP16: 0 | CQ16: 0 | CR16: 0 | CS16: 0 | CT16: 0 | CU16: 0 | CV16: 0 | CW16: 0 | CX16: 0 | CY16: 0 | CZ16: 0 | DA16: 0 | DB16: 0 | DC16: 0 | DD16: 0 | DE16: 0 | DF16: 0 | DG16: 0 | DH16: 0 | DI16: 0 | DJ16: 0 | DK16: 0 | DL16: 0 | DM16: 0 | DN16: 0 | DO16: 0 | DP16: 0 | DQ16: 0 | DR16: 0 | DS16: 0 | DT16: 0 | DU16: 0 | DV16: 0 | DW16: 0 | DX16: 0 | DY16: 0 | DZ16: 0 | EA16: 0 | EB16: 0 | EC16: 0 | ED16: 0 | EE16: 0 | EF16: 0 | EG16: 0 | EH16: 0 | EI16: 0 | EJ16: 0 | EK16: 0 | EL16: 0 | EM16: 0 | EN16: 0 | EO16: 0 | EP16: 0 | EQ16: 0 | ER16: 0 | ES16: 0 | ET16: 0 | EU16: 0 | EV16: 0 | EW16: 0
B17: 3 | C17: 10 | D17: Downstream | E17: Processing of sold products | F17: 0 | G17: 0 | H17: 0 | I17: 0 | J17: 0 | K17: 0 | L17: 0 | M17: 0 | N17: 0 | O17: 0 | P17: 0 | Q17: 0 | R17: 0 | S17: 0 | T17: 0 | U17: 0 | V17: 0 | W17: 0 | X17: 0 | Y17: 0 | Z17: 0 | AA17: 0 | AB17: 0 | AC17: 0 | AD17: 0 | AE17: 0 | AF17: 0 | AG17: 0 | AH17: 0 | AI17: 0 | AJ17: 0 | AK17: 0 | AL17: 0 | AM17: 0 | AN17: 0 | AO17: 0 | AP17: 0 | AQ17: 0 | AR17: 0 | AS17: 0 | AT17: 0 | AU17: 0 | AV17: 0 | AW17: 0 | AX17: 0 | AY17: 0 | AZ17: 0 | BA17: 0 | BB17: 0 | BC17: 0 | BD17: 0 | BE17: 0 | BF17: 0 | BG17: 0 | BH17: 0 | BI17: 0 | BJ17: 0 | BK17: 0 | BL17: 0 | BM17: 0 | BN17: 0 | BO17: 0 | BP17: 0 | BQ17: 0 | BR17: 0 | BS17: 0 | BT17: 0 | BU17: 0 | BV17: 0 | BW17: 0 | BX17: 0 | BY17: 0 | BZ17: 0 | CA17: 0 | CB17: 0 | CC17: 0 | CD17: 0 | CE17: 0 | CF17: 0 | CG17: 0 | CH17: 0 | CI17: 0 | CJ17: 0 | CK17: 0 | CL17: 0 | CM17: 0 | CN17: 0 | CO17: 0 | CP17: 0 | CQ17: 0 | CR17: 0 | CS17: 0 | CT17: 0 | CU17: 0 | CV17: 0 | CW17: 0 | CX17: 0 | CY17: 0 | CZ17: 0 | DA17: 0 | DB17: 0 | DC17: 0 | DD17: 0 | DE17: 0 | DF17: 0 | DG17: 0 | DH17: 0 | DI17: 0 | DJ17: 0 | DK17: 0 | DL17: 0 | DM17: 0 | DN17: 0 | DO17: 0 | DP17: 0 | DQ17: 0 | DR17: 0 | DS17: 0 | DT17: 0 | DU17: 0 | DV17: 0 | DW17: 0 | DX17: 0 | DY17: 0 | DZ17: 0 | EA17: 0 | EB17: 0 | EC17: 0 | ED17: 0 | EE17: 0 | EF17: 0 | EG17: 0 | EH17: 0 | EI17: 0 | EJ17: 0 | EK17: 0 | EL17: 0 | EM17: 0 | EN17: 0 | EO17: 0 | EP17: 0 | EQ17: 0 | ER17: 0 | ES17: 0 | ET17: 0 | EU17: 0 | EV17: 0 | EW17: 0
B18: 3 | C18: 11 | D18: Downstream | E18: Use of sold products | F18: 1722.23 | G18: 0 | H18: 0 | I18: 836.84893 | J18: 0 | K18: 0 | L18: 0 | M18: 0 | N18: 0 | O18: 0 | P18: 0 | Q18: 474.82489 | R18: 0 | S18: 0 | T18: 0 | U18: 0 | V18: 0 | W18: 0 | X18: 0 | Y18: 0 | Z18: 0 | AA18: 0 | AB18: 0 | AC18: 0 | AD18: 0 | AE18: 0 | AF18: 0 | AG18: 0 | AH18: 0 | AI18: 0 | AJ18: 0 | AK18: 0 | AL18: 0 | AM18: 0 | AN18: 0 | AO18: 0 | AP18: 0 | AQ18: 0 | AR18: 410.55622 | AS18: 0 | AT18: 0 | AU18: 0 | AV18: 0 | AW18: 0 | AX18: 0 | AY18: 0 | AZ18: 0 | BA18: 0 | BB18: 0 | BC18: 0 | BD18: 0 | BE18: 0 | BF18: 0 | BG18: 0 | BH18: 0 | BI18: 0 | BJ18: 0 | BK18: 0 | BL18: 0 | BM18: 0 | BN18: 0 | BO18: 0 | BP18: 0 | BQ18: 0 | BR18: 0 | BS18: 0 | BT18: 0 | BU18: 0 | BV18: 0 | BW18: 0 | BX18: 0 | BY18: 0 | BZ18: 0 | CA18: 0 | CB18: 0 | CC18: 0 | CD18: 0 | CE18: 0 | CF18: 0 | CG18: 0 | CH18: 0 | CI18: 0 | CJ18: 0 | CK18: 0 | CL18: 0 | CM18: 0 | CN18: 0 | CO18: 0 | CP18: 0 | CQ18: 0 | CR18: 0 | CS18: 0 | CT18: 0 | CU18: 0 | CV18: 0 | CW18: 0 | CX18: 0 | CY18: 0 | CZ18: 0 | DA18: 0 | DB18: 0 | DC18: 0 | DD18: 0 | DE18: 0 | DF18: 0 | DG18: 0 | DH18: 0 | DI18: 0 | DJ18: 0 | DK18: 0 | DL18: 0 | DM18: 0 | DN18: 0 | DO18: 0 | DP18: 0 | DQ18: 0 | DR18: 0 | DS18: 0 | DT18: 0 | DU18: 0 | DV18: 0 | DW18: 0 | DX18: 0 | DY18: 0 | DZ18: 0 | EA18: 0 | EB18: 0 | EC18: 0 | ED18: 0 | EE18: 0 | EF18: 0 | EG18: 0 | EH18: 0 | EI18: 0 | EJ18: 0 | EK18: 0 | EL18: 0 | EM18: 0 | EN18: 0 | EO18: 0 | EP18: 0 | EQ18: 0 | ER18: 0 | ES18: 0 | ET18: 0 | EU18: 0 | EV18: 0 | EW18: 0
B19: 3 | C19: 12 | D19: Downstream | E19: End of life treatment of sold products | F19: 41.126644 | G19: 0 | H19: 0.13351087 | I19: 0.55060462 | J19: 0.038586405 | K19: 0 | L19: 0.23349915 | M19: 0.022755932 | N19: 0.073636838 | O19: 0 | P19: 0 | Q19: 0.69212601 | R19: 0 | S19: 1.1492134 | T19: 0.35103609 | U19: 0.16503498 | V19: 0 | W19: 0.0044876826 | X19: 0 | Y19: 0.45966793 | Z19: 0.12969616 | AA19: 0.31753578 | AB19: 0 | AC19: 0.25985902 | AD19: 0.089151338 | AE19: 0.14812371 | AF19: 0.91858168 | AG19: 0.062500774 | AH19: 0 | AI19: 0.5519176 | AJ19: 0.34562971 | AK19: 0.033362403 | AL19: 0 | AM19: 0 | AN19: 0 | AO19: 0.050122827 | AP19: 0 | AQ19: 0.028199126 | AR19: 0.061549146 | AS19: 0.0019252164 | AT19: 3.9153211 | AU19: 0.016691874 | AV19: 0.17039275 | AW19: 0 | AX19: 0.062584836 | AY19: 0.37801866 | AZ19: 0 | BA19: 0.00014346911 | BB19: 0.48691387 | BC19: 0 | BD19: 0.86279697 | BE19: 0 | BF19: 0 | BG19: 0 | BH19: 0.79210268 | BI19: 0 | BJ19: 0 | BK19: 0 | BL19: 0 | BM19: 0 | BN19: 0.13243491 | BO19: 0 | BP19: 0 | BQ19: 1.8509529 | BR19: 0.29813815 | BS19: 0.56838971 | BT19: 0 | BU19: 0 | BV19: 0 | BW19: 0 | BX19: 0 | BY19: 0 | BZ19: 0 | CA19: 0 | CB19: 0 | CC19: 0 | CD19: 0 | CE19: 0.0014282406 | CF19: 0 | CG19: 0 | CH19: 0 | CI19: 0 | CJ19: 0 | CK19: 0.1592027 | CL19: 0.060758945 | CM19: 0 | CN19: 0.017774913 | CO19: 0 | CP19: 0 | CQ19: 0 | CR19: 0 | CS19: 0 | CT19: 0.34970944 | CU19: 0 | CV19: 0.034484593 | CW19: 0 | CX19: 0.022806622 | CY19: 0 | CZ19: 0 | DA19: 0 | DB19: 0 | DC19: 0.027303106 | DD19: 0.0014805761 | DE19: 0.018894345 | DF19: 0 | DG19: 0.011204856 | DH19: 0.18564159 | DI19: 0 | DJ19: 0 | DK19: 0 | DL19: 0 | DM19: 0.57834579 | DN19: 0.024073274 | DO19: 0.0071063432 | DP19: 0.13169042 | DQ19: 0 | DR19: 0 | DS19: 0 | DT19: 0 | DU19: 0.047690899 | DV19: 0.26140621 | DW19: 0 | DX19: 0 | DY19: 0 | DZ19: 0 | EA19: 0.00020375354 | EB19: 0 | EC19: 0 | ED19: 0 | EE19: 0.023509601 | EF19: 0.22195174 | EG19: 0 | EH19: 14.411159 | EI19: 0 | EJ19: 0 | EK19: 0 | EL19: 0 | EM19: 0 | EN19: 0 | EO19: 0.27297358 | EP19: 0.051337396 | EQ19: 0 | ER19: 6.618004 | ES19: 0 | ET19: 0.57941266 | EU19: 0.59858824 | EV19: 0.0013056791 | EW19: 0
... B22: 3 | C22: 15 | D22: Downstream | E22: Investments | F22: 0 | G22: 0 | H22: 0 | I22: 0 | J22: 0 | K22: 0 | L22: 0 | M22: 0 | N22: 0 | O22: 0 | P22: 0 | Q22: 0 | R22: 0 | S22: 0 | T22: 0 | U22: 0 | V22: 0 | W22: 0 | X22: 0 | Y22: 0 | Z22: 0 | AA22: 0 | AB22: 0 | AC22: 0 | AD22: 0 | AE22: 0 | AF22: 0 | AG22: 0 | AH22: 0 | AI22: 0 | AJ22: 0 | AK22: 0 | AL22: 0 | AM22: 0 | AN22: 0 | AO22: 0 | AP22: 0 | AQ22: 0 | AR22: 0 | AS22: 0 | AT22: 0 | AU22: 0 | AV22: 0 | AW22: 0 | AX22: 0 | AY22: 0 | AZ22: 0 | BA22: 0 | BB22: 0 | BC22: 0 | BD22: 0 | BE22: 0 | BF22: 0 | BG22: 0 | BH22: 0 | BI22: 0 | BJ22: 0 | BK22: 0 | BL22: 0 | BM22: 0 | BN22: 0 | BO22: 0 | BP22: 0 | BQ22: 0 | BR22: 0 | BS22: 0 | BT22: 0 | BU22: 0 | BV22: 0 | BW22: 0 | BX22: 0 | BY22: 0 | BZ22: 0 | CA22: 0 | CB22: 0 | CC22: 0 | CD22: 0 | CE22: 0 | CF22: 0 | CG22: 0 | CH22: 0 | CI22: 0 | CJ22: 0 | CK22: 0 | CL22: 0 | CM22: 0 | CN22: 0 | CO22: 0 | CP22: 0 | CQ22: 0 | CR22: 0 | CS22: 0 | CT22: 0 | CU22: 0 | CV22: 0 | CW22: 0 | CX22: 0 | CY22: 0 | CZ22: 0 | DA22: 0 | DB22: 0 | DC22: 0 | DD22: 0 | DE22: 0 | DF22: 0 | DG22: 0 | DH22: 0 | DI22: 0 | DJ22: 0 | DK22: 0 | DL22: 0 | DM22: 0 | DN22: 0 | DO22: 0 | DP22: 0 | DQ22: 0 | DR22: 0 | DS22: 0 | DT22: 0 | DU22: 0 | DV22: 0 | DW22: 0 | DX22: 0 | DY22: 0 | DZ22: 0 | EA22: 0 | EB22: 0 | EC22: 0 | ED22: 0 | EE22: 0 | EF22: 0 | EG22: 0 | EH22: 0 | EI22: 0 | EJ22: 0 | EK22: 0 | EL22: 0 | EM22: 0 | EN22: 0 | EO22: 0 | EP22: 0 | EQ22: 0 | ER22: 0 | ES22: 0 | ET22: 0 | EU22: 0 | EV22: 0 | EW22: 0
E23: Total LB | F23: 253841.84 | G23: 0.8721947 | H23: 1970.3132 | I23: 10085.643 | J23: 1590.2548 | K23: 15.53209 | L23: 3334.3936 | M23: 31.887794 | N23: 966.33926 | O23: -29.180723 | P23: 256.74744 | Q23: 10233.358 | R23: 91.441972 | S23: 16967.162 | T23: 1613.6761 | U23: 1654.9149 | V23: 1.7024746 | W23: 31.845653 | X23: -18.18906 | Y23: 3392.7637 | Z23: 666.86328 | AA23: 1959.2729 | AB23: 9.1597914 | AC23: 1123.3126 | AD23: 562.30906 | AE23: 342.30416 | AF23: 4848.6751 | AG23: 2341.4421 | AH23: 7.5213041 | AI23: 6286.5814 | AJ23: 7019.3042 | AK23: 1306.4834 | AL23: 69.083754 | AM23: 1.7456557 | AN23: 14.296396 | AO23: 166.50195 | AP23: 236.53876 | AQ23: 366.44143 | AR23: 1632.2884 | AS23: 86.627824 | AT23: 15661.955 | AU23: 147.21106 | AV23: 3027.3002 | AW23: 205.96839 | AX23: 664.35122 | AY23: 2369.0821 | AZ23: -97.108868 | BA23: 26.490162 | BB23: 2296.7218 | BC23: 2.6416421 | BD23: 4383.1495 | BE23: -22.605525 | BF23: 38.581178 | BG23: 238.8981 | BH23: 7081.002 | BI23: 39.349079 | BJ23: 9.2591857 | BK23: 5.5773381 | BL23: 12.126842 | BM23: 29.378247 | BN23: 1483.1219 | BO23: 0 | BP23: 0 | BQ23: 2190.9412 | BR23: 4618.4456 | BS23: 1449.1219 | BT23: 2300.0855 | BU23: -352.30999 | BV23: 0.14167143 | BW23: -206.98527 | BX23: 1.0407747 | BY23: 11.57885 | BZ23: -161.08845 | CA23: 88.253627 | CB23: -351.08971 | CC23: 105.72916 | CD23: 149.20426 | CE23: 971.02765 | CF23: 12.110816 | CG23: 1.0495968 | CH23: 4.0953018 | CI23: 669.85697 | CJ23: 733.17332 | CK23: 1932.056 | CL23: 563.50499 | CM23: 540.12759 | CN23: 281.74415 | CO23: 8.2553326 | CP23: 0 | CQ23: 1440.7931 | CR23: 578.88825 | CS23: 773.62683 | CT23: 2172.223 | CU23: 75.719605 | CV23: 458.57656 | CW23: 418.58531 | CX23: 281.54716 | CY23: 424.99706 | CZ23: 68.137561 | DA23: 2901.311 | DB23: 255.78958 | DC23: 248.62017 | DD23: 142.03958 | DE23: 299.21397 | DF23: 211.65332 | DG23: 118.51155 | DH23: 691.87199 | DI23: 448.10233 | DJ23: -8.4544412 | DK23: 1.573045 | DL23: 0 | DM23: 1323.9022 | DN23: 202.58797 | DO23: 111.83114 | DP23: 686.74988 | DQ23: 541.89734 | DR23: 862.66508 | DS23: 2619.2355 | DT23: 893.29653 | DU23: 2009.8415 | DV23: 1310.5138 | DW23: 55.19659 | DX23: 14.60548 | DY23: 36.576006 | DZ23: 6.6795588 | EA23: 22.388745 | EB23: 78.041618 | EC23: 16.090475 | ED23: 6.243665 | EE23: 1466.1306 | EF23: 2271.9359 | EG23: 6465.8658 | EH23: 22368.618 | EI23: 448.99905 | EJ23: 423.71104 | EK23: 53.314447 | EL23: -78.231483 | EM23: 28.776652 | EN23: 1.9298083 | EO23: 22496.89 | EP23: 357.3911 | EQ23: 245.55449 | ER23: 20350.854 | ES23: 1.9671747 | ET23: 1773.5672 | EU23: 15337.99 | EV23: 429.47503 | EW23: 2194.6803
E24: Total MB | F24: 251816.48 | G24: 0.8721947 | H24: 1970.3132 | I24: 10016.056 | J24: 1566.2648 | K24: 15.53209 | L24: 3334.3936 | M24: 31.887794 | N24: 966.33926 | O24: -29.180723 | P24: 256.74744 | Q24: 10233.358 | R24: 91.441972 | S24: 16967.162 | T24: 1613.6761 | U24: 1654.9149 | V24: 1.7024746 | W24: 31.845653 | X24: -18.18906 | Y24: 3422.2257 | Z24: 678.95539 | AA24: 2024.3523 | AB24: 9.1597914 | AC24: 1120.7613 | AD24: 577.35125 | AE24: 342.30416 | AF24: 4879.967 | AG24: 2333.1279 | AH24: 7.5213041 | AI24: 6289.3277 | AJ24: 7030.5855 | AK24: 1309.9845 | AL24: 69.083754 | AM24: 1.7456557 | AN24: 14.296396 | AO24: 168.48462 | AP24: 235.92821 | AQ24: 366.44143 | AR24: 1632.2884 | AS24: 89.004496 | AT24: 15349.378 | AU24: 147.93428 | AV24: 3032.6156 | AW24: 206.74416 | AX24: 664.87946 | AY24: 2369.0821 | AZ24: -97.108868 | BA24: 26.490162 | BB24: 2314.4353 | BC24: 2.6416421 | BD24: 4355.0051 | BE24: -22.605525 | BF24: 38.581178 | BG24: 238.8981 | BH24: 7136.6594 | BI24: 39.349079 | BJ24: 9.2591857 | BK24: 5.5773381 | BL24: 12.126842 | BM24: 29.378247 | BN24: 1483.1219 | BO24: 0 | BP24: 0 | BQ24: 2167.8934 | BR24: 4637.2144 | BS24: 1464.9917 | BT24: 2313.9905 | BU24: -352.30999 | BV24: 0.14167143 | BW24: -206.98527 | BX24: 1.0407747 | BY24: 11.57885 | BZ24: -161.08845 | CA24: 88.253627 | CB24: -351.08971 | CC24: 105.72916 | CD24: 149.20426 | CE24: 972.43227 | CF24: 12.110816 | CG24: 1.0495968 | CH24: 4.0953018 | CI24: 680.1133 | CJ24: 742.97652 | CK24: 1960.8103 | CL24: 566.64606 | CM24: 551.93744 | CN24: 284.45081 | CO24: 8.8456414 | CP24: 0 | CQ24: 1452.5364 | CR24: 586.33173 | CS24: 782.03464 | CT24: 2214.405 | CU24: 91.350309 | CV24: 470.35219 | CW24: 421.59733 | CX24: 284.74201 | CY24: 426.14741 | CZ24: 69.472511 | DA24: 2929.8944 | DB24: 259.40992 | DC24: 254.79056 | DD24: 143.86145 | DE24: 303.29989 | DF24: 214.70383 | DG24: 120.21349 | DH24: 702.02167 | DI24: 450.31623 | DJ24: -8.4544412 | DK24: 1.573045 | DL24: 0 | DM24: 1357.0543 | DN24: 208.5257 | DO24: 115.32782 | DP24: 698.93129 | DQ24: 576.14566 | DR24: 850.21192 | DS24: 2617.9646 | DT24: 895.44897 | DU24: 2011.5347 | DV24: 1311.801 | DW24: 55.19659 | DX24: 14.60548 | DY24: 36.576006 | DZ24: 6.6795588 | EA24: 22.388745 | EB24: 78.041618 | EC24: 16.090475 | ED24: 6.243665 | EE24: 1466.6783 | EF24: 2272.2636 | EG24: 6469.1353 | EH24: 20516.435 | EI24: 448.99905 | EJ24: 423.71104 | EK24: 53.314447 | EL24: -78.231483 | EM24: 28.776652 | EN24: 1.9298083 | EO24: 22429.26 | EP24: 357.3911 | EQ24: 245.55449 | ER24: 20037.871 | ES24: 1.9671747 | ET24: 1776.5434 | EU24: 15381.683 | EV24: 433.50053 | EW24: 2195.8206
B26: FY24 Summary | F26: =SUM(F8:F22) -> 244134.45 | G26: =+F26-F8-F9-F11-F13-F14 -> 7615.5635
B28: Scope | C28: Category | D28: Upstream/Downstream | E28: Emission Source | F28: tCO2e Market | G28: tCO2e Location
B29: 1 | C29: - | D29: Internal | E29: Stationary combustion | F29: 1736.4822 | G29: 1736.4822
B30: 1 | C30: - | D30: Internal | E30: Company vehicles | F30: 2120.6171 | G30: 2120.6171
B31: 1 | C31: - | D31: Internal | E31: Fugitive emissions | F31: 0 | G31: 0
B32: 1 | C32: - | D32: Internal | E32: Refrigerants | F32: 18.080351 | G32: 18.080351
B33: 1 | C33: - | D33: Internal | E33: Extrapolated tCo2e | F33: 0 | G33: 0
B34: 2 | C34: - | D34: Internal | E34: Electricity usage | F34: 3667.1893 | G34: 5692.5506
B35: 2 | C35: - | D35: Internal | E35: Heating | F35: 139.6637 | G35: 139.6637
B36: 2 | C36: - | D36: Internal | E36: Cooling | F36: 0 | G36: 0
B37: 2 | C37: - | D37: Internal | E37: Extrapolated tCo2e | F37: 0 | G37: 0
B38: 3 | C38: 1 | D38: Upstream | E38: Purchased goods and services | F38: 176935.41 | G38: 176935.41
B39: 3 | C39: 2 | D39: Upstream | E39: Capital goods | F39: 6973.2078 | G39: 6973.2078
B40: 3 | C40: 3 | D40: Upstream | E40: Fuel and energy related activities | F40: 2303.622 | G40: 2303.622
B41: 3 | C41: 4 | D41: Upstream | E41: Upstream transportation and distribution | F41: 38920.499 | G41: 38920.499
B42: 3 | C42: 5 | D42: Upstream | E42: Waste generated in operations | F42: 625.92365 | G42: 625.92365
B43: 3 | C43: 6 | D43: Upstream | E43: Business travel | F43: 6734.7391 | G43: 6734.7391
B44: 3 | C44: 7 | D44: Upstream | E44: Employee commuting | F44: 6955.0292 | G44: 6955.0292
B45: 3 | C45: 8 | D45: Upstream | E45: Upstream leased assets | F45: 2922.6612 | G45: 2922.6612
B46: 3 | C46: 9 | D46: Downstream | E46: Downstream transportation and distribution | F46: 0 | G46: 0
B47: 3 | C47: 10 | D47: Downstream | E47: Processing of sold products | F47: 0 | G47: 0
B48: 3 | C48: 11 | D48: Downstream | E48: Use of sold products | F48: 1722.23 | G48: 1722.23
B49: 3 | C49: 12 | D49: Downstream | E49: End of life treatment of sold products | F49: 41.126644 | G49: 41.126644
... B52: 3 | C52: 15 | D52: Downstream | E52: Investments | F52: 0 | G52: 0
B53: Total | F53: 251816.48 | G53: 253841.84

Sheet FY24 + HFM
A1: Emission Source | B1: Business Entity | C1: Sector | D1: Business | E1: All Scope 1 | F1: All Scope 2 MB | G1: All Scope 2 LB | H1: 1 Purchased goods and services | I1: 2 Capital goods | J1: 3 Fuel and energy related activities | K1: 4 Upstream transportation and distribution | L1: 5 Waste generated in operations | M1: 6 Business travel | N1: 7 Employee commuting | O1: 8 Upstream leased assets | P1: 9 Downstream transportation and distribution | Q1: 10 Processing of sold products | R1: 11 Use of sold products | S1: 12 End of life treatment of sold products | T1: 13 Downstream leased assets | U1: 14 Franchises | V1: 15 Investments | W1: Total LB | X1: Total MB
A2: C8500 | B2: =+VLOOKUP(A2,'HFM Codes'!$B$2:$C$432,2, FALSE) -> Windy City Wire | C2: =+VLOOKUP(A2,'HFM Codes'!$B$2:$E$432,4,FALSE) -> Windy City Wire | D2: =+VLOOKUP(A2,'HFM Codes'!$B$2:$D$432,3,FALSE) -> Windy City Wire | E2: 584.04009 | F2: 662.94928 | G2: 2515.132 | H2: 15102.957 | I2: 638.64136 | J2: 667.61581 | K2: 708.67011 | L2: 224.61131 | M2: 366.05318 | N2: 850.34221 | O2: 696.14387 | P2: 0 | Q2: 0 | R2: 0 | S2: 14.411159 | T2: 0 | U2: 0 | V2: 0 | W2: 22368.618 | X2: 20516.435
A3: S2025 | B3: =+VLOOKUP(A3,'HFM Codes'!$B$2:$C$432,2, FALSE) -> Hercules US - Louisville | C3: =+VLOOKUP(A3,'HFM Codes'!$B$2:$E$432,4,FALSE) -> North American Seals | D3: =+VLOOKUP(A3,'HFM Codes'!$B$2:$D$432,3,FALSE) -> Aftermarket | E3: 87.557771 | F3: 0.16905365 | G3: 313.15167 | H3: 11780.202 | I3: 193.02898 | J3: 87.293075 | K3: 6858.5142 | L3: 4.0045948 | M3: 444.5822 | N3: 443.47951 | O3: 132.42198 | P3: 0 | Q3: 0 | R3: 0 | S3: 6.618004 | T3: 0 | U3: 0 | V3: 0 | W3: 20350.854 | X3: 20037.871
A4: C9010 | B4: =+VLOOKUP(A4,'HFM Codes'!$B$2:$C$432,2, FALSE) -> FS Cables | C4: =+VLOOKUP(A4,'HFM Codes'!$B$2:$E$432,4,FALSE) -> Controls | D4: =+VLOOKUP(A4,'HFM Codes'!$B$2:$D$432,3,FALSE) -> Shoal group | E4: 2.0692019 | F4: 40.19687 | G4: 21.428081 | H4: 2285.934 | I4: 1045.4001 | J4: 7.6136358 | K4: 585.36536 | L4: 1.4368834 | M4: 127.09267 | N4: 369.51388 | O4: 172.29352 | P4: 0 | Q4: 0 | R4: 0 | S4: 0.29813815 | T4: 0 | U4: 0 | V4: 0 | W4: 4618.4456 | X4: 4637.2144
A5: S8010 | B5: =+VLOOKUP(A5,'HFM Codes'!$B$2:$C$432,2, FALSE) -> VSP | C5: =+VLOOKUP(A5,'HFM Codes'!$B$2:$E$432,4,FALSE) -> North American Seals | D5: =+VLOOKUP(A5,'HFM Codes'!$B$2:$D$432,3,FALSE) -> VSP group | E5: 98.309505 | F5: 355.492 | G5: 311.79972 | H5: 12762.097 | I5: 124.25809 | J5: 112.89389 | K5: 988.83404 | L5: 43.365435 | M5: 431.29619 | N5: 341.76739 | O5: 122.7708 | P5: 0 | Q5: 0 | R5: 0 | S5: 0.59858824 | T5: 0 | U5: 0 | V5: 0 | W5: 15337.99 | X5: 15381.683
A6: S7060 | B6: =+VLOOKUP(A6,'HFM Codes'!$B$2:$C$432,2, FALSE) -> FITT Resources | C6: =+VLOOKUP(A6,'HFM Codes'!$B$2:$E$432,4,FALSE) -> International Seals (excl Disposals) | D6: =+VLOOKUP(A6,'HFM Codes'!$B$2:$D$432,3,FALSE) -> Diploma Australia Seals | E6: 359.71836 | F6: 96.247731 | G6: 96.247731 | H6: 2209.6274 | I6: 93.780348 | J6: 111.09041 | K6: -158.69976 | L6: 20.820421 | M6: 274.35464 | N6: 260.18484 | O6: 67.035659 | P6: 0 | Q6: 0 | R6: 0 | S6: 0.23349915 | T6: 0 | U6: 0 | V6: 0 | W6: 3334.3936 | X6: 3334.3936
A7: LCAoem | B7: =+VLOOKUP(A7,'HFM Codes'!$B$2:$C$432,2, FALSE) -> Hercules OEM group | C7: =+VLOOKUP(A7,'HFM Codes'!$B$2:$E$432,4,FALSE) -> North American Seals | D7: =+VLOOKUP(A7,'HFM Codes'!$B$2:$D$432,3,FALSE) -> OEM | E7: 85.604518 | F7: 94.946748 | G7: 162.57693 | H7: 18717.241 | I7: 34.878088 | J7: 49.925633 | K7: 2844.6972 | L7: 11.716549 | M7: 197.9463 | N7: 253.78324 | O7: 138.24755 | P7: 0 | Q7: 0 | R7: 0 | S7: 0.27297358 | T7: 0 | U7: 0 | V7: 0 | W7: 22496.89 | X7: 22429.26
A8: L3015 | B8: =+VLOOKUP(A8,'HFM Codes'!$B$2:$C$432,2, FALSE) -> Abacus-Dx Pty Ltd | C8: =+VLOOKUP(A8,'HFM Codes'!$B$2:$E$432,4,FALSE) -> Life Sciences | D8: =+VLOOKUP(A8,'HFM Codes'!$B$2:$D$432,3,FALSE) -> Life Sciences Australasia | E8: 0.603811 | F8: 95.811883 | G8: 165.39869 | H8: 7647.2866 | I8: 348.20845 | J8: 40.415306 | K8: 265.00559 | L8: 4.645268 | M8: 494.18678 | N8: 235.02868 | O8: 47.464027 | P8: 0 | Q8: 0 | R8: 836.84893 | S8: 0.55060462 | T8: 0 | U8: 0 | V8: 0 | W8: 10085.643 | X8: 10016.056
A9: L5010 | B9: =+VLOOKUP(A9,'HFM Codes'!$B$2:$C$432,2, FALSE) -> Accuscience | C9: =+VLOOKUP(A9,'HFM Codes'!$B$2:$E$432,4,FALSE) -> Life Sciences | D9: =+VLOOKUP(A9,'HFM Codes'!$B$2:$D$432,3,FALSE) -> Life Sciences Ireland | E9: 387.94081 | F9: 56.421951 | G9: 45.14072 | H9: 5653.9814 | I9: 46.870157 | J9: 97.244416 | K9: 438.37502 | L9: 0.29836261 | M9: 118.93782 | N9: 199.03145 | O9: 31.138451 | P9: 0 | Q9: 0 | R9: 0 | S9: 0.34562971 | T9: 0 | U9: 0 | V9: 0 | W9: 7019.3042 | X9: 7030.5855
A10: L2040 | B10: =+VLOOKUP(A10,'HFM Codes'!$B$2:$C$432,2, FALSE) -> Vantage | C10: =+VLOOKUP(A10,'HFM Codes'!$B$2:$E$432,4,FALSE) -> Life Sciences | D10: =+VLOOKUP(A10,'HFM Codes'!$B$2:$D$432,3,FALSE) -> Life Sciences North America | E10: 57.991748 | F10: 22.481846 | G10: 22.481846 | H10: 11663.825 | I10: 2513.8795 | J10: 16.358227 | K10: 2021.1734 | L10: 6.7825016 | M10: 408.77813 | N10: 191.05102 | O10: 63.69127 | P10: 0 | Q10: 0 | R10: 0 | S10: 1.1492134 | T10: 0 | U10: 0 | V10: 0 | W10: 16967.162 | X10: 16967.162
A11: C1520 | B11: =+VLOOKUP(A11,'HFM Codes'!$B$2:$C$432,2, FALSE) -> Fanucworld | C11: =+VLOOKUP(A11,'HFM Codes'!$B$2:$E$432,4,FALSE) -> Controls | D11: =+VLOOKUP(A11,'HFM Codes'!$B$2:$D$432,3,FALSE) -> TIE | E11: 72.016061 | F11: 173.44904 | G11: 174.71997 | H11: 1440.3883 | I11: 132.94017 | J11: 52.099037 | K11: 413.64332 | L11: 35.474267 | M11: 77.245197 | N11: 185.52437 | O11: 35.184835 | P11: 0 | Q11: 0 | R11: 0 | S11: 0 | T11: 0 | U11: 0 | V11: 0 | W11: 2619.2355 | X11: 2617.9646
A12: C2040 | B12: =+VLOOKUP(A12,'HFM Codes'!$B$2:$C$432,2, FALSE) -> CSF Ltd - Leics site | C12: =+VLOOKUP(A12,'HFM Codes'!$B$2:$E$432,4,FALSE) -> Controls | D12: =+VLOOKUP(A12,'HFM Codes'!$B$2:$D$432,3,FALSE) -> Specialty Fasteners | E12: 35.470791 | F12: 3.3037332 | G12: 31.448188 | H12: 3349.1334 | I12: 36.434441 | J12: 17.223867 | K12: 735.62315 | L12: 1.7672723 | M12: 0 | N12: 167.25192 | O12: 7.9337396 | P12: 0 | Q12: 0 | R12: 0 | S12: 0.86279697 | T12: 0 | U12: 0 | V12: 0 | W12: 4383.1495 | X12: 4355.0051
A13: S1010 | B13: =+VLOOKUP(A13,'HFM Codes'!$B$2:$C$432,2, FALSE) -> Dicsa Spain | C13: =+VLOOKUP(A13,'HFM Codes'!$B$2:$E$432,4,FALSE) -> International Seals (excl Disposals) | D13: =+VLOOKUP(A13,'HFM Codes'!$B$2:$D$432,3,FALSE) -> Dicsa Group | E13: 60.870391 | F13: 24.862685 | G13: 337.43962 | H13: 4332.8271 | I13: 314.79994 | J13: 126.90289 | K13: 10102.633 | L13: 13.605443 | M13: 98.451603 | N13: 165.23651 | O13: 105.2735 | P13: 0 | Q13: 0 | R13: 0 | S13: 3.9153211 | T13: 0 | U13: 0 | V13: 0 | W13: 15661.955 | X13: 15349.378
... A148: HoGrp | B148: =+VLOOKUP(A148,'HFM Codes'!$B$2:$C$432,2, FALSE) -> Head Office Allocation | C148: =+VLOOKUP(A148,'HFM Codes'!$B$2:$E$432,4,FALSE) -> Head Office | D148: =+VLOOKUP(A148,'HFM Codes'!$B$2:$D$432,3,FALSE) -> Head Office | E148: 0 | F148: 0 | G148: 0 | H148: -16.90234 | I148: 0 | J148: 0 | K148: 0 | L148: 0 | M148: -334.18737 | N148: 0 | O148: 0 | P148: 0 | Q148: 0 | R148: 0 | S148: 0 | T148: 0 | U148: 0 | V148: 0 | W148: -351.08971 | X148: -351.08971

Sheet HFM Codes
A1: Currency | B1: Code | C1: HFM Entity Structure | D1: Business | E1: Sector
A2: CAD | B2: L2020 | C2: Somagen | D2: Life Sciences North America | E2: Life Sciences
A3: CAD | B3: L2030 | C3: AMT | D3: Life Sciences North America | E3: Life Sciences
A4: CAD | B4: L2031 | C4: AMT - ES Division | D4: Life Sciences North America | E4: Life Sciences
A5: CAD | B5: L2032 | C5: AMT - MI Division | D5: Life Sciences North America | E5: Life Sciences
A6: CAD | B6: AMT | C6: AMT | D6: Life Sciences North America | E6: Life Sciences
A7: CAD | B7: L2040 | C7: Vantage | D7: Life Sciences North America | E7: Life Sciences
A8: CAD | B8: AMTV | C8: Acernis | D8: Life Sciences North America | E8: Life Sciences
A9: CAD | B9: LSNAxHO | C9: Life Sciences North America (exc HO) | D9: Life Sciences North America | E9: Life Sciences
A10: CAD | B10: HoLSNA | C10: LS North America HO | D10: Life Sciences North America | E10: Life Sciences
A11: CAD | B11: HoLSDCHI | C11: DCHI North America | D11: Life Sciences North America | E11: Life Sciences
A12: CAD | B12: LSNA | C12: Life Sciences North America | D12: Life Sciences North America | E12: Life Sciences
... A198: EUR | B198: IntsealHo | C198: International Seals HO | D198: International Seals HO | E198: International Seals (excl Disposals)
A199: EUR | B199: IntSealsg | C199: International Seals (excl Disposals) | E199: International Seals (excl Disposals)
A200: EUR | B200: S5010 | C200: Kentek - Finland | D200: International Seals- Disposal | E200: International Seals
A201: RUB | B201: S5020 | C201: Kentek - St Petersburg | D201: International Seals- Disposal | E201: International Seals
A202: RUB | B202: S5025 | C202: Kentek - Trade | D202: International Seals- Disposal | E202: International Seals
A203: RUB | B203: S5030 | C203: Kentek - Moscow | D203: International Seals- Disposal | E203: International Seals
A204: RUB | B204: KENR | C204: Kentek - Russia | D204: International Seals- Disposal | E204: International Seals
A205: EUR | B205: S5040 | C205: Kentek - Estonia | D205: International Seals- Disposal | E205: International Seals
A206: EUR | B206: S5050 | C206: Kentek - Latvia | D206: International Seals- Disposal | E206: International Seals
A207: LTL | B207: S5060 | C207: Kentek - Lithuania LTL | D207: International Seals- Disposal | E207: International Seals
A208: EUR | B208: S5070 | C208: Kentek - Lithuania EUR | D208: International Seals- Disposal | E208: International Seals
A209: EUR | B209: KENL | C209: Kentek - Lithuania | D209: International Seals- Disposal | E209: International Seals
A210: EUR | B210: KENB | C210: Kentek - Baltics | D210: International Seals- Disposal | E210: International Seals
A211: EUR | B211: KEN | C211: Kentek | D211: International Seals- Disposal | E211: International Seals
... A236: EUR | B236: INTsealsgrp | C236: International Seals | D236: International Seals- Disposal | E236: International Seals
A237: GBP | B237: Seals | C237: Seals
A238: USD | B238: C8500 | C238: Windy City Wire | D238: Windy City Wire | E238: Windy City Wire
A239: GBP | B239: GCANAC | C239: GCA NA Controls | D239: North American Controls | E239: North American Controls
A240: USD | B240: NAcontrols | C240: North American Controls | D240: North American Controls | E240: North American Controls
A241: GBP | B241: C2080 | C241: IS-Rayfast Ltd | D241: ISG | E241: Controls
A242: GBP | B242: C2010 | C242: ISR Core | D242: ISG | E242: Controls
A243: GBP | B243: C2020 | C243: ISR International | D243: ISG | E243: Controls
A244: GBP | B244: C2030 | C244: ISR Motorsport | D244: ISG | E244: Controls
A245: GBP | B245: C2070 | C245: Intercompany | D245: ISG | E245: Controls
A246: GBP | B246: C2050 | C246: IS-Cabletec | D246: ISG | E246: Controls
A247: GBP | B247: C2060 | C247: Support | D247: ISG | E247: Controls
A248: GBP | B248: ISR | C248: ISR (no longer used) | D248: ISG | E248: Controls
A249: GBP | B249: ISRLtd | C249: IS-Rayfast Ltd | D249: ISG | E249: Controls
... A362: GBP | B362: GCAIntC | C362: GCA International Controls | D362: Controls Disposal | E362: Controls
A363: GBP | B363: INTcontrols | C363: International Controls | E363: Controls
A364: GBP | B364: Controls | C364: Controls | E364: Controls
A365: GBP | B365: OpBus | C365: Operating Businesses | D365: Head Office | E365: Head Office
A366: GBP | B366: G2010 | C366: Diploma Holdings PLC | D366: Head Office | E366: Head Office
A367: EUR | B367: G2015 | C367: Diploma Italy (Branch) | D367: Head Office | E367: Head Office
A368: GBP | B368: HoGrp | C368: Head Office Allocation | D368: Head Office | E368: Head Office
A369: EUR | B369: HoGrpE | C369: Head Office Allocation EUR | D369: Head Office | E369: Head Office
A370: GBP | B370: HeadOff | C370: Head Office | D370: Head Office | E370: Head Office
A371: AUD | B371: G3010 | C371: Diploma Australia Healthcare Pty Ltd | D371: Head Office | E371: Head Office
A372: AUD | B372: G3080 | C372: Diploma Australia Seals Pty Ltd | D372: Head Office | E372: Head Office
A373: EUR | B373: G3045 | C373: Diploma Germany Holding GmbH | D373: Head Office | E373: Head Office
A374: EUR | B374: G3085 | C374: Diploma Iberia Holdings (no longer used) | D374: Head Office | E374: Head Office
A375: USD | B375: G3025 | C375: Diploma Holdings | D375: Head Office | E375: Head Office
A376: USD | B376: HoDHI | C376: Diploma Holdings Allocation | D376: Head Office | E376: Head Office
... A431: GBP | B431: HeadOffice | C431: Head Office | D431: Head Office | E431: Head Office
A432: GBP | B432: DipGroup | C432: Diploma Group

Sheet FY23
B2: FY23 Footprint by Entity Code
BR3: Divested | BS3: Divested
B4: Scope | C4: Category | D4: Upstream/Downstream | E4: Emission Source | F4: Diploma Total (excl. Divestments) | G4: G3010 | H4: L2050 | I4: L3015 | J4: S7030 | K4: S7040 | L4: S7060 | M4: S7090 | N4: G3015 | O4: G5035 | P4: G5020 | Q4: L2010 | R4: L2020 | S4: L2030 | T4: L2040 | U4: S2050 | V4: S2060 | W4: C5520 | X4: S4030 | Y4: G5040 | Z4: L2500 | AA4: L7010 | AB4: S4010 | AC4: C2540 | AD4: C4050 | AE4: c4030 | AF4: C2090 | AG4: C2091 | AH4: C7010 | AI4: G3045 | AJ4: C1040 | AK4: L2090 | AL4: L5010 | AM4: S1030 | AN4: G5025 | AO4: HoIntSealsE | AP4: S1040 | AQ4: S2210 | AR4: S7020 | AS4: L2060 | AT4: L3025 | AU4: L7030 | AV4: S1010 | AW4: L2510 | AX4: L2700 | AY4: L7020 | AZ4: S4020 | BA4: G5045 | BB4: S6040 | BC4: S6020 | BD4: S6070 | BE4: C2530 | BF4: c1010 | BG4: C2040 | BH4: C2041 | BI4: C2042 | BJ4: C2043 | BK4: C2080 | BL4: C2551 | BM4: C2552 | BN4: C2553 | BO4: C2554 | BP4: C2555 | BQ4: C3510 | BR4: C5010 | BS4: C6020 | BT4: C8010 | BU4: C9010 | BV4: C9050 | BW4: G2010 | BX4: G3041 | BY4: G4010 | BZ4: G5005 | CA4: G5010 | CB4: HoControls | CC4: HoGrp | CD4: HoIntSeals | CE4: HoLS | CF4: L5020 | CG4: R1100 | CH4: R1120 | CI4: R1140 | CJ4: R1170 | CK4: R1180 | CL4: R1190 | CM4: R1210 | CN4: R1220 | CO4: R1230 | CP4: R1240 | CQ4: R2100 | CR4: R2110 | CS4: R2120 | CT4: R2130 | CU4: R2150 | CV4: R2160 | CW4: R2170 | CX4: R2180 | CY4: R2190 | CZ4: R2210 | DA4: R2220 | DB4: R3100 | DC4: R4100 | DD4: R4110 | DE4: R4120 | DF4: R4130 | DG4: R4140 | DH4: R4150 | DI4: R4160 | DJ4: R5100 | DK4: R5110 | DL4: R5120 | DM4: R9100 | DN4: S3010 | DO4: S3030 | DP4: S4040 | DQ4: S4050 | DR4: S9010 | DS4: R1160 | DT4: G3020 | DU4: C1510 | DV4: C1520 | DW4: C1530 | DX4: C2045 | DY4: C2046 | DZ4: C2571 | EA4: C2572 | EB4: C2573 | EC4: C2574 | ED4: C2575 | EE4: C2576 | EF4: C2577 | EG4: C2578 | EH4: C3040 | EI4: C4510 | EJ4: C5510 | EK4: C8500 | EL4: G3025 | EM4: G5015 | EN4: HoControlsU | EO4: HoDHI | EP4: HoLSU | EQ4: HoNaSeals | ER4: LCAoem | ES4: S1020 | ET4: S2010 | EU4: S2025 | EV4: S2026 | EW4: S2310 | EX4: S8010 | EY4: S8020 | EZ4: S8030
B5: 1 | C5: - | D5: Internal | E5: All Scope 1 | F5: 3603.6118 | G5: 0 | H5: 0 | I5: 2.3415972 | J5: 36.949506 | K5: 0 | L5: 263.92419 | M5: 9.4338592 | N5: 0 | O5: 0 | P5: 0 | Q5: 0 | R5: 63.232432 | S5: 0 | T5: 24.140687 | U5: 2.0190731 | V5: 0.2438126 | W5: 0 | X5: 0 | Y5: 0 | Z5: 79.277174 | AA5: 0 | AB5: 89.826518 | AC5: 0 | AD5: 43.634144 | AE5: 79.721404 | AF5: 41.04121 | AG5: 0 | AH5: 23.565358 | AI5: 0 | AJ5: 0 | AK5: 129.07593 | AL5: 181.9197 | AM5: 13.960584 | AN5: 0 | AO5: 0 | AP5: 0 | AQ5: 21.939195 | AR5: 1.2489337 | AS5: 0 | AT5: 8.4053574 | AU5: 0 | AV5: 53.589563 | AW5: 4.641187 | AX5: 87.555554 | AY5: 0 | AZ5: 16.092035 | BA5: 0 | BB5: 26.365857 | BC5: 35.569999 | BD5: 0 | BE5: 0 | BF5: 5.5243695 | BG5: 28.957182 | BH5: 0 | BI5: 0 | BJ5: 0 | BK5: 38.651243 | BL5: 0 | BM5: 0 | BN5: 0 | BO5: 0 | BP5: 0 | BQ5: 0 | BR5: 19.772744 | BS5: 19.338778 | BT5: 15.070965 | BU5: 7.073657 | BV5: 39.512939 | BW5: 0 | BX5: 0 | BY5: 0 | BZ5: 0 | CA5: 0 | CB5: 0 | CC5: 0 | CD5: 0 | CE5: 0 | CF5: 20.823744 | CG5: 92.052167 | CH5: 9.8221698 | CI5: 14.21673 | CJ5: 126.59247 | CK5: 48.578883 | CL5: 63.016931 | CM5: 3.9766865 | CN5: 35.551059 | CO5: 25.263342 | CP5: 3.7710153 | CQ5: 6.6699545 | CR5: 1.9281567 | CS5: 7.6121173 | CT5: 86.243709 | CU5: 38.226914 | CV5: 8.2150267 | CW5: 18.904424 | CX5: 0.53263851 | CY5: 5.3253646 | CZ5: 22.991631 | DA5: 4.8594358 | DB5: 263.18141 | DC5: 17.549563 | DD5: 5.1933096 | DE5: 13.530312 | DF5: 15.582274 | DG5: 2.5268947 | DH5: 6.9599132 | DI5: 11.517496 | DJ5: 12.304313 | DK5: 0 | DL5: 0 | DM5: 0 | DN5: 26.976107 | DO5: 2.9310903 | DP5: 6.4937143 | DQ5: 6.9957034 | DR5: 16.561782 | DS5: 0 | DT5: 0 | DU5: 28.958556 | DV5: 63.402076 | DW5: 30.280914 | DX5: 0 | DY5: 8.030998 | DZ5: 0 | EA5: 0 | EB5: 0 | EC5: 0 | ED5: 0 | EE5: 0 | EF5: 0 | EG5: 0 | EH5: 4.0759623 | EI5: 0.9437504 | EJ5: 0 | EK5: 557.65272 | EL5: 0 | EM5: 0 | EN5: 0 | EO5: 0 | EP5: 0 | EQ5: 0 | ER5: 101.10625 | ES5: 0 | ET5: 0 | EU5: 51.128981 | EV5: 0 | EW5: 54.018417 | EX5: 81.460942 | EY5: 20.29796 | EZ5: 74.270638
B6: 2 | C6: - | D6: Internal | E6: All Scope 2 MB | F6: 6350.4729 | G6: 0 | H6: 0 | I6: 180.07268 | J6: 35.639512 | K6: 0 | L6: 99.194185 | M6: 11.724814 | N6: 0 | O6: 0 | P6: 0 | Q6: 0 | R6: 23.522465 | S6: 0 | T6: 22.140942 | U6: 10.614438 | V6: 15.613601 | W6: 0 | X6: 0 | Y6: 0 | Z6: 47.957245 | AA6: 12.835037 | AB6: 93.956719 | AC6: 0 | AD6: 14.755777 | AE6: 56.921898 | AF6: 30.439335 | AG6: 0 | AH6: 16.95512 | AI6: 0 | AJ6: 0 | AK6: 74.122524 | AL6: 107.08625 | AM6: 8.2171428 | AN6: 0 | AO6: 0 | AP6: 0 | AQ6: 7.7135808 | AR6: 19.682882 | AS6: 0 | AT6: 4.7199024 | AU6: 2.1171503 | AV6: 21.88881 | AW6: 0.4498357 | AX6: 3.491517 | AY6: 0.81853058 | AZ6: 0.30268045 | BA6: 0 | BB6: 21.230339 | BC6: 35.51891 | BD6: 0 | BE6: 2.43509 | BF6: 24.547209 | BG6: 27.111143 | BH6: 0 | BI6: 0 | BJ6: 0 | BK6: 142.23129 | BL6: 0 | BM6: 0 | BN6: 0 | BO6: 0 | BP6: 0 | BQ6: 0 | BR6: 18.701157 | BS6: 4.4749132 | BT6: 146.87209 | BU6: 90.923445 | BV6: 35.975673 | BW6: 26.625643 | BX6: 0 | BY6: 0 | BZ6: 0 | CA6: 0 | CB6: 0 | CC6: 0 | CD6: 0 | CE6: 0 | CF6: 12.035258 | CG6: 12.426785 | CH6: 1.5007665 | CI6: 0.2300445 | CJ6: 15.078468 | CK6: 10.588985 | CL6: 42.297015 | CM6: 6.7789002 | CN6: 29.131046 | CO6: 5.9649991 | CP6: 4.5147146 | CQ6: 17.499668 | CR6: 5.6734086 | CS6: 2.7342797 | CT6: 16.019861 | CU6: 50.92108 | CV6: 22.223978 | CW6: 18.989662 | CX6: 5.6791965 | CY6: 6.0239539 | CZ6: 2.8999564 | DA6: 6.0442777 | DB6: 43.121659 | DC6: 18.016793 | DD6: 9.9249231 | DE6: 4.1102014 | DF6: 8.0763512 | DG6: 5.1880512 | DH6: 3.2090323 | DI6: 45.954904 | DJ6: 4.1743476 | DK6: 0 | DL6: 0 | DM6: 0 | DN6: 70.172124 | DO6: 17.449666 | DP6: 7.0405923 | DQ6: 24.16161 | DR6: 67.40176 | DS6: 0 | DT6: 0 | DU6: 13.650866 | DV6: 152.70246 | DW6: 46.996575 | DX6: 0 | DY6: 27.994182 | DZ6: 0 | EA6: 0 | EB6: 0 | EC6: 0 | ED6: 0 | EE6: 0 | EF6: 0 | EG6: 0 | EH6: 16.69768 | EI6: 23.359268 | EJ6: 637.53393 | EK6: 2540.601 | EL6: 0 | EM6: 0 | EN6: 0 | EO6: 0 | EP6: 0 | EQ6: 0 | ER6: 68.695943 | ES6: 0 | ET6: 0 | EU6: 241.15796 | EV6: 0 | EW6: 39.139611 | EX6: 328.69375 | EY6: 60.332163 | EZ6: 53.233829
B7: 2 | D7: Internal | E7: All Scope 2 LB | F7: 6068.329 | G7: 0 | H7: 0 | I7: 180.07268 | J7: 35.639512 | K7: 0 | L7: 99.194185 | M7: 11.724814 | N7: 0 | O7: 0 | P7: 0 | Q7: 0 | R7: 23.522465 | S7: 0 | T7: 22.140942 | U7: 10.614438 | V7: 15.613601 | W7: 0 | X7: 0 | Y7: 0 | Z7: 22.915244 | AA7: 2.1892869 | AB7: 16.64017 | AC7: 0 | AD7: 6.0695176 | AE7: 26.021487 | AF7: 13.91515 | AG7: 0 | AH7: 10.14183 | AI7: 0 | AJ7: 0 | AK7: 41.66309 | AL7: 60.191478 | AM7: 5.1348356 | AN7: 0 | AO7: 0 | AP7: 0 | AQ7: 5.3208016 | AR7: 18.538656 | AS7: 0 | AT7: 4.7199024 | AU7: 0.024757479 | AV7: 297.0778 | AW7: 0.12011017 | AX7: 0.9322664 | AY7: 0.13555271 | AZ7: 0.0808184 | BA7: 0 | BB7: 21.230339 | BC7: 35.51891 | BD7: 0 | BE7: 2.43509 | BF7: 13.920569 | BG7: 34.617226 | BH7: 0 | BI7: 0 | BJ7: 0 | BK7: 80.658479 | BL7: 0 | BM7: 0 | BN7: 0 | BO7: 0 | BP7: 0 | BQ7: 0 | BR7: 10.60531 | BS7: 2.5376954 | BT7: 83.290249 | BU7: 51.562119 | BV7: 20.40158 | BW7: 15.099236 | BX7: 0 | BY7: 0 | BZ7: 0 | CA7: 0 | CB7: 0 | CC7: 0 | CD7: 0 | CE7: 0 | CF7: 6.8073764 | CG7: 7.0471522 | CH7: 0.85107533 | CI7: 0.1304568 | CJ7: 8.550905 | CK7: 6.0049473 | CL7: 23.986374 | CM7: 3.844272 | CN7: 16.520035 | CO7: 3.3827138 | CP7: 2.5602665 | CQ7: 9.9239525 | CR7: 3.2173546 | CS7: 1.550593 | CT7: 9.0847632 | CU7: 28.877027 | CV7: 12.60308 | CW7: 10.768919 | CX7: 3.0274567 | CY7: 3.2112394 | CZ7: 1.5459039 | DA7: 3.2220735 | DB7: 24.454024 | DC7: 10.217211 | DD7: 5.628362 | DE7: 2.3308696 | DF7: 4.5800484 | DG7: 2.9421115 | DH7: 1.7106656 | DI7: 24.497564 | DJ7: 2.2252543 | DK7: 0 | DL7: 0 | DM7: 0 | DN7: 39.794174 | DO7: 9.8955971 | DP7: 3.992676 | DQ7: 13.701899 | DR7: 38.223118 | DS7: 0 | DT7: 0 | DU7: 24.61448 | DV7: 153.82136 | DW7: 45.101593 | DX7: 0 | DY7: 27.994182 | DZ7: 0 | EA7: 0 | EB7: 0 | EC7: 0 | ED7: 0 | EE7: 0 | EF7: 0 | EG7: 0 | EH7: 16.69768 | EI7: 23.359268 | EJ7: 630.62181 | EK7: 2540.601 | EL7: 0 | EM7: 0 | EN7: 0 | EO7: 0 | EP7: 0 | EQ7: 0 | ER7: 179.90159 | ES7: 0 | ET7: 0 | EU7: 305.21991 | EV7: 0 | EW7: 39.139611 | EX7: 328.69375 | EY7: 60.332163 | EZ7: 52.229948
B8: 3 | C8: 1 | D8: Upstream | E8: Purchased goods and services | F8: 191705.14 | G8: 0.28440293 | H8: 2347.6935 | I8: 6355.2733 | J8: 1274.7047 | K8: 2.4841353 | L8: 2088.7677 | M8: 274.06541 | N8: 0 | O8: 27.413034 | P8: 0 | Q8: -29.895176 | R8: 8638.0227 | S8: 0 | T8: 11197.196 | U8: 1160.5588 | V8: 1369.2688 | W8: 0.35192973 | X8: 35.882688 | Y8: 4.831987 | Z8: 2913.8311 | AA8: 375.07683 | AB8: 957.31463 | AC8: 1.9894212 | AD8: 907.35721 | AE8: 4422.9594 | AF8: 355.40068 | AG8: 200.49617 | AH8: 2483.7005 | AI8: 8.6253776 | AJ8: 1.0639154 | AK8: 5366.5059 | AL8: 11287.13 | AM8: 1066.3252 | AN8: 372.11704 | AO8: 1.3245968 | AP8: 6.4808006 | AQ8: 99.128434 | AR8: 312.86767 | AS8: 398.53359 | AT8: 883.8132 | AU8: 75.088292 | AV8: 3814.569 | AW8: 116.68406 | AX8: 3604.7615 | AY8: 173.6902 | AZ8: 567.72886 | BA8: -535.5776 | BB8: 1000.4855 | BC8: 1856.576 | BD8: 0 | BE8: 5.3587513 | BF8: 1962.992 | BG8: 3077.2796 | BH8: -14.741075 | BI8: 24.161759 | BJ8: 137.56416 | BK8: 4909.0995 | BL8: 8.533482 | BM8: 3.0258951 | BN8: -0.029977605 | BO8: 6.230526 | BP8: 0 | BQ8: 1277.009 | BR8: 1560.4899 | BS8: 493.61442 | BT8: 1516.0998 | BU8: 2008.4581 | BV8: 1306.1834 | BW8: 1335.3758 | BX8: 0.017700869 | BY8: 0.0031054156 | BZ8: 0 | CA8: 3002.3639 | CB8: 200.73728 | CC8: 0 | CD8: -76.491101 | CE8: 0 | CF8: 1162.3393 | CG8: 146.05216 | CH8: 7.0920979 | CI8: 30.604294 | CJ8: 395.32676 | CK8: 352.27362 | CL8: 1410.0583 | CM8: 369.73729 | CN8: 299.12465 | CO8: 216.6668 | CP8: 95.192016 | CQ8: 186.93249 | CR8: 610.06654 | CS8: 520.16579 | CT8: 478.69722 | CU8: 1381.1429 | CV8: -17.240456 | CW8: 227.03047 | CX8: 334.31768 | CY8: 188.52343 | CZ8: 404.86952 | DA8: 66.658307 | DB8: 1835.9914 | DC8: 151.68431 | DD8: 130.21463 | DE8: 98.901599 | DF8: 291.90008 | DG8: 123.98851 | DH8: 73.86444 | DI8: 780.30582 | DJ8: 121.4804 | DK8: 1.1331259 | DL8: 0.0031054156 | DM8: 0 | DN8: 760.28645 | DO8: 100.78218 | DP8: 61.420879 | DQ8: 501.72646 | DR8: 228.45164 | DS8: -0.70499171 | DT8: 0.049376107 | DU8: 536.70932 | DV8: 1268.1006 | DW8: 433.10277 | DX8: 1433.8965 | DY8: 944.72252 | DZ8: 7.7819132 | EA8: 1.6707878 | EB8: 7.7549155 | EC8: 2.2586382 | ED8: 17.85496 | EE8: 75.236495 | EF8: 2.9117147 | EG8: 1.2692943 | EH8: 890.65559 | EI8: 2062.4464 | EJ8: 10776.685 | EK8: 12645.696 | EL8: 749.95395 | EM8: 167.56362 | EN8: 3.1484654 | EO8: -3.2396455 | EP8: 0.091180055 | EQ8: 0 | ER8: 19553.826 | ES8: 162.03119 | ET8: 181.03192 | EU8: 12582.76 | EV8: 0 | EW8: 1175.6266 | EX8: 11886.759 | EY8: 280.04512 | EZ8: 1197.4946
B9: 3 | C9: 2 | D9: Upstream | E9: Capital goods | F9: 8445.8016 | G9: 0 | H9: 25.854385 | I9: 442.09117 | J9: 33.210614 | K9: 0 | L9: 54.731234 | M9: 6.1377915 | N9: 0 | O9: 0 | P9: 0 | Q9: 5.7587261 | R9: 145.60681 | S9: 0 | T9: 2199.7452 | U9: 26.782739 | V9: 1.6885182 | W9: 0 | X9: 0 | Y9: 0 | Z9: 24.954877 | AA9: 3.3081761 | AB9: 75.648316 | AC9: 0 | AD9: 49.828941 | AE9: 36.675184 | AF9: 15.566319 | AG9: 0 | AH9: 5.3149192 | AI9: 0 | AJ9: 0 | AK9: 18.962888 | AL9: 39.756368 | AM9: 2.0167027 | AN9: 0 | AO9: 0 | AP9: 0 | AQ9: 0 | AR9: 1.1259146 | AS9: 0 | AT9: 102.74983 | AU9: 0 | AV9: 277.14609 | AW9: 9.9652898 | AX9: 18.619614 | AY9: 0 | AZ9: 0 | BA9: 0 | BB9: 88.437971 | BC9: 55.256581 | BD9: 0 | BE9: 0 | BF9: 7.2350019 | BG9: 14.658353 | BH9: 0 | BI9: 0 | BJ9: 0 | BK9: 81.372719 | BL9: 0 | BM9: 0 | BN9: 0 | BO9: 0 | BP9: 0 | BQ9: 0 | BR9: 0 | BS9: 0 | BT9: 1079.4689 | BU9: 10.396794 | BV9: 6.7759415 | BW9: 69.217396 | BX9: 0 | BY9: 0 | BZ9: 0 | CA9: 0 | CB9: 0 | CC9: 0 | CD9: 0 | CE9: 0 | CF9: 0.89993022 | CG9: -75.240145 | CH9: 0 | CI9: 5.6675829 | CJ9: 118.67112 | CK9: 160.74215 | CL9: 550.01729 | CM9: 33.663428 | CN9: 17.742343 | CO9: 30.152717 | CP9: 0.80629115 | CQ9: -56.326719 | CR9: 23.696507 | CS9: 2.5571174 | CT9: 19.752977 | CU9: 264.81896 | CV9: 10.236897 | CW9: 19.685594 | CX9: 8.2641549 | CY9: 13.018686 | CZ9: 0 | DA9: 0 | DB9: 400.69397 | DC9: 0 | DD9: 113.14116 | DE9: 0 | DF9: 0.21769303 | DG9: 0.38061039 | DH9: 0 | DI9: 136.71715 | DJ9: 45.920071 | DK9: 0 | DL9: 0 | DM9: 0 | DN9: 0 | DO9: 1.245106 | DP9: 0 | DQ9: 0 | DR9: 4.1975028 | DS9: 0 | DT9: 0 | DU9: 0 | DV9: 117.03893 | DW9: 13.908335 | DX9: 20.023221 | DY9: 0 | DZ9: 0 | EA9: 0 | EB9: 0 | EC9: 0 | ED9: 0 | EE9: 0 | EF9: 0 | EG9: 0 | EH9: 1.3780418 | EI9: 18.018118 | EJ9: 0 | EK9: 269.22922 | EL9: 0 | EM9: 0 | EN9: 0 | EO9: 0 | EP9: 0 | EQ9: 0 | ER9: 35.418891 | ES9: 0 | ET9: 0 | EU9: 665.02163 | EV9: 0 | EW9: 2.6598808 | EX9: 378.40075 | EY9: 0 | EZ9: 37.298142
B10: 3 | C10: 3 | D10: Upstream | E10: Fuel and energy related activities | F10: 2299.2305 | G10: 0 | H10: 0 | I10: 39.912334 | J10: 16.778072 | K10: 0 | L10: 85.730094 | M10: 4.8597731 | N10: 0 | O10: 0 | P10: 0 | Q10: 0 | R10: 16.979274 | S10: 0 | T10: 10.139129 | U10: 3.2830679 | V10: 4.3791413 | W10: 0 | X10: 0 | Y10: 0 | Z10: 27.126484 | AA10: 1.3105131 | AB10: 26.171358 | AC10: 0 | AD10: 13.594633 | AE10: 25.985464 | AF10: 12.436453 | AG10: 0 | AH10: 7.88613 | AI10: 0 | AJ10: 0 | AK10: 43.691303 | AL10: 63.800068 | AM10: 4.1864446 | AN10: 0 | AO10: 0 | AP10: 0 | AQ10: 4.9861931 | AR10: 4.5227311 | AS10: 0 | AT10: 3.0983878 | AU10: 0.0044704009 | AV10: 111.72378 | AW10: 1.284293 | AX10: 22.545873 | AY10: 0.15736674 | AZ10: 4.1316492 | BA10: 0 | BB10: 12.26713 | BC10: 19.215591 | BD10: 0 | BE10: 0.75833476 | BF10: 5.9084976 | BG10: 16.966201 | BH10: 0 | BI10: 0 | BJ10: 0 | BK10: 33.908248 | BL10: 0 | BM10: 0 | BN10: 0 | BO10: 0 | BP10: 0 | BQ10: 0 | BR10: 7.4033709 | BS10: 4.2047407 | BT10: 30.601326 | BU10: 18.664872 | BV10: 16.236018 | BW10: 5.0963467 | BX10: 0 | BY10: 0 | BZ10: 0 | CA10: 0 | CB10: 0 | CC10: 0 | CD10: 0 | CE10: 0 | CF10: 7.3786531 | CG10: 23.303187 | CH10: 2.676307 | CI10: 3.4012702 | CJ10: 32.130039 | CK10: 13.695068 | CL10: 21.655135 | CM10: 2.0356696 | CN10: 12.822832 | CO10: 6.8030752 | CP10: 1.7005286 | CQ10: 4.451084 | CR10: 1.4722153 | CS10: 2.3512175 | CT10: 21.505219 | CU10: 17.983734 | CV10: 6.2519786 | CW10: 6.7567551 | CX10: 1.1394146 | CY10: 2.1261979 | CZ10: 5.8904744 | DA10: 2.3475976 | DB10: 72.728267 | DC10: 6.6001011 | DD10: 3.1207444 | DE10: 3.5751115 | DF10: 5.0779082 | DG10: 1.5287633 | DH10: 1.5844144 | DI10: 8.4537922 | DJ10: 3.7422263 | DK10: 0 | DL10: 0 | DM10: 0 | DN10: 18.185844 | DO10: 3.8240545 | DP10: 2.7851175 | DQ10: 6.4257877 | DR10: 16.561551 | DS10: 0 | DT10: 0 | DU10: 11.381707 | DV10: 45.867367 | DW10: 13.596558 | DX10: 0 | DY10: 11.069943 | DZ10: 0 | EA10: 0 | EB10: 0 | EC10: 0 | ED10: 0 | EE10: 0 | EF10: 0 | EG10: 0 | EH10: 4.2371619 | EI10: 5.2598043 | EJ10: 140.43489 | EK10: 669.12007 | EL10: 0 | EM10: 0 | EN10: 0 | EO10: 0 | EP10: 0 | EQ10: 0 | ER10: 54.63322 | ES10: 0 | ET10: 0 | EU10: 86.174152 | EV10: 0 | EW10: 22.42207 | EX10: 113.99405 | EY10: 11.770715 | EZ10: 34.870439
B11: 3 | C11: 4 | D11: Upstream | E11: Upstream transportation and distribution | F11: 41103.353 | G11: 0 | H11: 24.285272 | I11: 365.81882 | J11: 19.100754 | K11: 2.4411633 | L11: -16.823054 | M11: 25.249989 | N11: 0 | O11: 0 | P11: 0 | Q11: 0 | R11: 648.81721 | S11: 0 | T11: 1809.8252 | U11: 445.0154 | V11: 341.56642 | W11: 0 | X11: 1.4367101 | Y11: 0 | Z11: 174.31783 | AA11: 151.81329 | AB11: 494.99451 | AC11: 0 | AD11: 222.86582 | AE11: 34.602058 | AF11: 108.26784 | AG11: 57.169429 | AH11: 61.961708 | AI11: 0 | AJ11: 0 | AK11: 644.24517 | AL11: 401.59023 | AM11: 28.797163 | AN11: 0 | AO11: 0 | AP11: 0 | AQ11: 31.920913 | AR11: 23.762267 | AS11: 39.124516 | AT11: 7.7972681 | AU11: 1.0027168 | AV11: 8894.2369 | AW11: 38.772489 | AX11: 246.86838 | AY11: 2.1275875 | AZ11: 59.302315 | BA11: 0 | BB11: -38.680247 | BC11: 107.69319 | BD11: 0 | BE11: 0 | BF11: 569.14534 | BG11: 540.55203 | BH11: 5.8307593 | BI11: 0 | BJ11: 0 | BK11: 578.7841 | BL11: 0 | BM11: 0 | BN11: 0 | BO11: 0 | BP11: 0 | BQ11: 599.39284 | BR11: 670.11998 | BS11: 212.10209 | BT11: 511.5291 | BU11: 1152.0885 | BV11: 632.43365 | BW11: 0 | BX11: 0 | BY11: 0 | BZ11: 0 | CA11: 0 | CB11: 0 | CC11: 0 | CD11: 0 | CE11: 0 | CF11: 14.078942 | CG11: 14.832435 | CH11: 0.011914472 | CI11: 0.019896953 | CJ11: 38.987617 | CK11: 136.3185 | CL11: 182.60329 | CM11: 152.61458 | CN11: 19.092772 | CO11: 8.3091595 | CP11: 2.7993785 | CQ11: 325.74495 | CR11: 674.85506 | CS11: 108.49357 | CT11: 51.355015 | CU11: 681.88737 | CV11: 9.5020778 | CW11: 162.85442 | CX11: -19.166822 | CY11: 21.161029 | CZ11: 7.3253175 | DA11: 0 | DB11: 139.19627 | DC11: 73.140982 | DD11: 66.046244 | DE11: 21.212275 | DF11: -15.931675 | DG11: 115.93725 | DH11: 13.38573 | DI11: 213.64267 | DJ11: 0 | DK11: 0 | DL11: 0 | DM11: 0 | DN11: 615.07634 | DO11: 61.48031 | DP11: 15.426392 | DQ11: 201.23371 | DR11: 140.23395 | DS11: 0 | DT11: 0 | DU11: 66.929407 | DV11: 364.16661 | DW11: 106.00937 | DX11: 52.92167 | DY11: 135.61706 | DZ11: 0 | EA11: 0 | EB11: 0 | EC11: 0 | ED11: 0.093950706 | EE11: 0 | EF11: 0 | EG11: 0 | EH11: 589.35185 | EI11: 359.0562 | EJ11: 1730.5485 | EK11: 623.90467 | EL11: 0 | EM11: 0 | EN11: 0 | EO11: 0 | EP11: 0 | EQ11: 0 | ER11: 3758.4086 | ES11: 152.56645 | ET11: 0 | EU11: 6873.8262 | EV11: 0 | EW11: 446.27868 | EX11: 1047.1251 | EY11: 6.8696352 | EZ11: 484.87441
B12: 3 | C12: 5 | D12: Upstream | E12: Waste generated in operations | F12: 721.55269 | G12: 0 | H12: 1.255313 | I12: 3.7676416 | J12: 4.5112158 | K12: 0 | L12: 24.995804 | M12: 0 | N12: 0 | O12: 0 | P12: 0 | Q12: 0 | R12: 10.770471 | S12: 0 | T12: 8.0316047 | U12: 2.6387783 | V12: 1.9276345 | W12: 0 | X12: 0 | Y12: 0 | Z12: 0.35155894 | AA12: 0 | AB12: 8.8933938 | AC12: 0 | AD12: 27.076886 | AE12: 0.70916162 | AF12: 0.36316167 | AG12: 0 | AH12: 0.096615228 | AI12: 0 | AJ12: 0 | AK12: 1.4595396 | AL12: 8.1810599 | AM12: 0.16469908 | AN12: 0 | AO12: 0 | AP12: 0 | AQ12: 0.073197825 | AR12: 0 | AS12: 0.55438404 | AT12: 1.6623009 | AU12: 0 | AV12: 11.978068 | AW12: 0.005958626 | AX12: 0.16139364 | AY12: 0 | AZ12: 0.43793242 | BA12: 0 | BB12: 10.890234 | BC12: 1.3655468 | BD12: 0 | BE12: 0 | BF12: 0.52666198 | BG12: 1.2718518 | BH12: 0 | BI12: 0 | BJ12: 0 | BK12: 1.9331485 | BL12: 0 | BM12: 0 | BN12: 0 | BO12: 0 | BP12: 0 | BQ12: 0 | BR12: 5.2377973 | BS12: 1.6951856 | BT12: 7.4784117 | BU12: 6.7066978 | BV12: 2.3243388 | BW12: 0.48830295 | BX12: 0 | BY12: 0 | BZ12: 0 | CA12: 0 | CB12: 0 | CC12: 0 | CD12: 0 | CE12: 0 | CF12: 0.63017183 | CG12: 0 | CH12: 0.51112927 | CI12: 0.70749532 | CJ12: 0.19152727 | CK12: 0.18480253 | CL12: 0.2569019 | CM12: 0.025707215 | CN12: 0.15935068 | CO12: 0.058054042 | CP12: 0 | CQ12: 16.644295 | CR12: 4.5472658 | CS12: 10.823046 | CT12: 0.038816192 | CU12: 51.582267 | CV12: 0 | CW12: 7.7744967 | CX12: 0.078084962 | CY12: 1.0828824 | CZ12: 0.042195958 | DA12: 0.073555403 | DB12: 0.77710169 | DC12: 0.24374744 | DD12: 0.94384201 | DE12: 2.7424339 | DF12: 2.6755755 | DG12: 0.94785372 | DH12: 0.21004263 | DI12: 0.51188186 | DJ12: 0 | DK12: 0 | DL12: 0 | DM12: 0 | DN12: 0.48334683 | DO12: 0.30024694 | DP12: 0.010470157 | DQ12: 0.17984912 | DR12: 0.41497574 | DS12: 2.2265532 | DT12: 0 | DU12: 14.613738 | DV12: 31.231119 | DW12: 43.832228 | DX12: 0 | DY12: 11.423724 | DZ12: 0 | EA12: 0 | EB12: 0 | EC12: 0 | ED12: 0 | EE12: 0 | EF12: 0 | EG12: 0 | EH12: 0.30350432 | EI12: 8.0640476 | EJ12: 0 | EK12: 256.97072 | EL12: 0 | EM12: 0 | EN12: 0 | EO12: 0 | EP12: 0 | EQ12: 0 | ER12: 19.65644 | ES12: 0 | ET12: 0 | EU12: 4.4489202 | EV12: 0 | EW12: 3.6351301 | EX12: 46.924124 | EY12: 10.725596 | EZ12: 8.5904553
B13: 3 | C13: 6 | D13: Upstream | E13: Business travel | F13: 6514.0033 | G13: 0 | H13: 82.28755 | I13: 372.66034 | J13: 62.566132 | K13: 1.5276693 | L13: 168.37752 | M13: 63.973031 | N13: 0 | O13: 0 | P13: 0 | Q13: 209.13626 | R13: 387.09526 | S13: 0 | T13: 413.2964 | U13: 39.120792 | V13: 19.853743 | W13: 0.28878114 | X13: 4.599274 | Y13: 0 | Z13: 136.02966 | AA13: 39.944675 | AB13: 64.99624 | AC13: 4.4807456 | AD13: 25.875649 | AE13: 38.903379 | AF13: 12.319619 | AG13: 12.501641 | AH13: 11.271407 | AI13: 0 | AJ13: 0 | AK13: 84.535829 | AL13: 80.947535 | AM13: 3.2999038 | AN13: 0 | AO13: 0 | AP13: 6.1055754 | AQ13: 1.8416358 | AR13: 19.648612 | AS13: 11.916067 | AT13: 93.809159 | AU13: 0.14416645 | AV13: 86.675611 | AW13: 7.0870466 | AX13: 102.60817 | AY13: 3.5224108 | AZ13: 21.293514 | BA13: 0 | BB13: 24.391853 | BC13: 101.9383 | BD13: 0 | BE13: 12.902964 | BF13: 34.563063 | BG13: 0 | BH13: 0.70728011 | BI13: 19.449155 | BJ13: 103.12524 | BK13: 172.08942 | BL13: 54.622607 | BM13: 7.0567372 | BN13: 0.93737587 | BO13: 5.0076109 | BP13: 0 | BQ13: 28.749155 | BR13: 33.329653 | BS13: 3.9369763 | BT13: 19.725144 | BU13: 42.129011 | BV13: 53.642461 | BW13: 576.4345 | BX13: 0 | BY13: 0 | BZ13: 0 | CA13: 0 | CB13: 101.99383 | CC13: -215.23263 | CD13: 76.794585 | CE13: 36.444215 | CF13: 35.29495 | CG13: 29.879875 | CH13: 1.5985861 | CI13: 3.8392556 | CJ13: 46.58368 | CK13: 18.468736 | CL13: 47.65713 | CM13: 0.20979598 | CN13: 9.2022979 | CO13: 7.6530183 | CP13: 0 | CQ13: 0.19347552 | CR13: 2.0821725 | CS13: 2.4805802 | CT13: 43.94512 | CU13: 28.251632 | CV13: 4.017768 | CW13: 3.0944395 | CX13: 3.7125604 | CY13: 3.5713012 | CZ13: 22.777313 | DA13: 22.327228 | DB13: 108.63089 | DC13: 3.1302044 | DD13: 3.9733883 | DE13: 13.502959 | DF13: 7.9053171 | DG13: 0.31640881 | DH13: 1.3828386 | DI13: 6.6756721 | DJ13: 51.947558 | DK13: 0 | DL13: 0 | DM13: 0 | DN13: 16.30817 | DO13: 0.950823 | DP13: 0.7293878 | DQ13: 9.4045721 | DR13: 11.159474 | DS13: 1.023702 | DT13: 0 | DU13: 2.1433018 | DV13: 68.005745 | DW13: 5.3300465 | DX13: -1.1710403 | DY13: 71.291787 | DZ13: 20.981335 | EA13: 16.800853 | EB13: 19.080606 | EC13: 1.4909218 | ED13: 0 | EE13: 4.5738857 | EF13: 4.7358092 | EG13: 2.9675095 | EH13: 38.271485 | EI13: 31.664849 | EJ13: 138.18319 | EK13: 327.46153 | EL13: 76.939837 | EM13: 0 | EN13: 22.915658 | EO13: -22.915658 | EP13: 0 | EQ13: 0 | ER13: 169.91693 | ES13: 0 | ET13: 122.64795 | EU13: 369.84429 | EV13: 0 | EW13: 39.130568 | EX13: 412.80331 | EY13: 35.175504 | EZ13: 9.8379925
B14: 3 | C14: 7 | D14: Upstream | E14: Employee commuting | F14: 6123.1243 | G14: 0 | H14: 0 | I14: 206.91643 | J14: 92.455159 | K14: 0 | L14: 229.06361 | M14: 0 | N14: 0 | O14: 0 | P14: 0 | Q14: 5.0969403 | R14: 120.62759 | S14: 0 | T14: 168.19903 | U14: 45.458515 | V14: 35.24809 | W14: 0 | X14: 0 | Y14: 0 | Z14: 64.240255 | AA14: 10.193881 | AB14: 57.539692 | AC14: 1.6989801 | AD14: 31.230871 | AE14: 124.92924 | AF14: 15.184428 | AG14: 0 | AH14: 38.79141 | AI14: 0 | AJ14: 1.6989801 | AK14: 132.75122 | AL14: 175.2249 | AM14: 18.688781 | AN14: 0 | AO14: 0 | AP14: 0 | AQ14: 5.0969403 | AR14: 8.4949005 | AS14: 0 | AT14: 18.550408 | AU14: 0 | AV14: 145.47225 | AW14: 4.4828793 | AX14: 31.290463 | AY14: 1.6989801 | AZ14: 18.332506 | BA14: 0 | BB14: 32.543107 | BC14: 135.07796 | BD14: 0 | BE14: 5.0969403 | BF14: 55.207187 | BG14: 147.24659 | BH14: 0 | BI14: 0 | BJ14: 0 | BK14: 135.12802 | BL14: 0 | BM14: 0 | BN14: 0 | BO14: 0 | BP14: 0 | BQ14: 0 | BR14: 0 | BS14: 0 | BT14: 0 | BU14: 325.31559 | BV14: 0 | BW14: 26.853387 | BX14: 0 | BY14: 0 | BZ14: 10.193881 | CA14: 0 | CB14: 5.0969403 | CC14: 0 | CD14: 3.3979602 | CE14: 1.6989801 | CF14: 8.4949005 | CG14: 0 | CH14: 0 | CI14: 0 | CJ14: 54.724863 | CK14: 18.902761 | CL14: 121.54228 | CM14: 19.526204 | CN14: 35.211323 | CO14: 9.846716 | CP14: 0 | CQ14: 0 | CR14: 30.397761 | CS14: 25.511772 | CT14: 72.585988 | CU14: 69.424496 | CV14: 10.613854 | CW14: 9.6636349 | CX14: 13.119734 | CY14: 4.8110318 | CZ14: 15.304811 | DA14: 15.290821 | DB14: 129.56154 | DC14: 11.387943 | DD14: 2.4763881 | DE14: 5.9484747 | DF14: 19.806494 | DG14: 8.0400917 | DH14: 2.8931696 | DI14: 115.53065 | DJ14: 63.432945 | DK14: 0 | DL14: 0 | DM14: 0 | DN14: 49.458539 | DO14: 13.591841 | DP14: 8.9104033 | DQ14: 29.632018 | DR14: 56.664595 | DS14: 0 | DT14: 0 | DU14: 67.718764 | DV14: 163.33343 | DW14: 85.037733 | DX14: 82.511769 | DY14: 0 | DZ14: 0 | EA14: 0 | EB14: 0 | EC14: 0 | ED14: 0 | EE14: 0 | EF14: 0 | EG14: 0 | EH14: 21.76894 | EI14: 33.866062 | EJ14: 105.33677 | EK14: 748.63109 | EL14: 8.4949005 | EM14: 0 | EN14: 1.6989801 | EO14: 0 | EP14: 1.6989801 | EQ14: 1.6989801 | ER14: 223.42772 | ES14: 0 | ET14: 16.989801 | EU14: 390.43404 | EV14: 1.6989801 | EW14: 73.098124 | EX14: 300.88791 | EY14: 8.4949005 | EZ14: 42.474503
B15: 3 | C15: 8 | D15: Upstream | E15: Upstream leased assets | F15: 2800.9244 | G15: 0 | H15: 14.445612 | I15: 34.0596 | J15: 26.689128 | K15: 0 | L15: 59.132672 | M15: 4.896388 | N15: 0 | O15: 0 | P15: 0 | Q15: 2.3499119 | R15: 0.71078767 | S15: 0 | T15: 38.369954 | U15: 23.86132 | V15: 16.583723 | W15: 2.958473 | X15: 2.4237082 | Y15: 0 | Z15: 25.649562 | AA15: 3.1476036 | AB15: 28.879138 | AC15: 0 | AD15: 44.730631 | AE15: 67.390958 | AF15: 6.6087511 | AG15: 1.4156478 | AH15: 10.298831 | AI15: 0 | AJ15: 0 | AK15: 11.594812 | AL15: 29.998657 | AM15: 7.6086143 | AN15: 0 | AO15: 0 | AP15: 0 | AQ15: 4.9788133 | AR15: 17.314643 | AS15: 0 | AT15: 9.16225 | AU15: 0 | AV15: 92.681529 | AW15: 4.2616997 | AX15: 27.484217 | AY15: 0.0035671226 | AZ15: 3.148614 | BA15: 0 | BB15: 20.541205 | BC15: 84.70827 | BD15: 0 | BE15: 2.0780587 | BF15: 12.961554 | BG15: 7.6510055 | BH15: 6.6681251 | BI15: 1.4265953 | BJ15: 20.258713 | BK15: 59.251932 | BL15: 0 | BM15: 0 | BN15: 0 | BO15: 0 | BP15: 0 | BQ15: 0 | BR15: 17.437078 | BS15: 3.6742917 | BT15: 26.609926 | BU15: 93.295809 | BV15: 29.02276 | BW15: 63.778526 | BX15: 0 | BY15: 0 | BZ15: 0 | CA15: 0 | CB15: 0 | CC15: 0 | CD15: 0 | CE15: 0 | CF15: 6.4087517 | CG15: 10.195656 | CH15: 1.2536735 | CI15: 2.0347071 | CJ15: 12.609448 | CK15: 9.4298071 | CL15: 31.037822 | CM15: 7.9250555 | CN15: 12.576254 | CO15: 0.22142781 | CP15: 3.2799622 | CQ15: 4.8437048 | CR15: 29.577628 | CS15: 10.222816 | CT15: 17.357753 | CU15: 46.93304 | CV15: 2.3107358 | CW15: 1.9861441 | CX15: 4.3257632 | CY15: 5.019495 | CZ15: 14.348814 | DA15: 7.8426243 | DB15: 45.041023 | DC15: 9.7270368 | DD15: 5.1032738 | DE15: 2.591843 | DF15: 6.9211835 | DG15: 4.1315775 | DH15: 1.8944575 | DI15: 0 | DJ15: 1.3792703 | DK15: -15.860708 | DL15: 0 | DM15: 0 | DN15: 37.954523 | DO15: 3.0934556 | DP15: 6.9508276 | DQ15: 17.70885 | DR15: 10.432583 | DS15: 0.10536592 | DT15: 0 | DU15: 6.410717 | DV15: 30.976307 | DW15: 8.5539082 | DX15: 1.3241795 | DY15: 34.05121 | DZ15: 0 | EA15: 0 | EB15: 0 | EC15: 0 | ED15: 7.507921 | EE15: 4.5510264 | EF15: 3.0281948 | EG15: 0 | EH15: 7.132525 | EI15: 18.907479 | EJ15: 0 | EK15: 725.39049 | EL15: 0 | EM15: 0 | EN15: 0 | EO15: 0 | EP15: 0 | EQ15: 0 | ER15: 153.63266 | ES15: 0 | ET15: 0 | EU15: 140.70359 | EV15: 0 | EW15: 47.321166 | EX15: 132.73544 | EY15: 21.162404 | EZ15: 27.527215
B16: 3 | C16: 9 | D16: Downstream | E16: Downstream transportation and distribution | F16: 0 | G16: 0 | H16: 0 | I16: 0 | J16: 0 | K16: 0 | L16: 0 | M16: 0 | N16: 0 | O16: 0 | P16: 0 | Q16: 0 | R16: 0 | S16: 0 | T16: 0 | U16: 0 | V16: 0 | W16: 0 | X16: 0 | Y16: 0 | Z16: 0 | AA16: 0 | AB16: 0 | AC16: 0 | AD16: 0 | AE16: 0 | AF16: 0 | AG16: 0 | AH16: 0 | AI16: 0 | AJ16: 0 | AK16: 0 | AL16: 0 | AM16: 0 | AN16: 0 | AO16: 0 | AP16: 0 | AQ16: 0 | AR16: 0 | AS16: 0 | AT16: 0 | AU16: 0 | AV16: 0 | AW16: 0 | AX16: 0 | AY16: 0 | AZ16: 0 | BA16: 0 | BB16: 0 | BC16: 0 | BD16: 0 | BE16: 0 | BF16: 0 | BG16: 0 | BH16: 0 | BI16: 0 | BJ16: 0 | BK16: 0 | BL16: 0 | BM16: 0 | BN16: 0 | BO16: 0 | BP16: 0 | BQ16: 0 | BR16: 0 | BS16: 0 | BT16: 0 | BU16: 0 | BV16: 0 | BW16: 0 | BX16: 0 | BY16: 0 | BZ16: 0 | CA16: 0 | CB16: 0 | CC16: 0 | CD16: 0 | CE16: 0 | CF16: 0 | CG16: 0 | CH16: 0 | CI16: 0 | CJ16: 0 | CK16: 0 | CL16: 0 | CM16: 0 | CN16: 0 | CO16: 0 | CP16: 0 | CQ16: 0 | CR16: 0 | CS16: 0 | CT16: 0 | CU16: 0 | CV16: 0 | CW16: 0 | CX16: 0 | CY16: 0 | CZ16: 0 | DA16: 0 | DB16: 0 | DC16: 0 | DD16: 0 | DE16: 0 | DF16: 0 | DG16: 0 | DH16: 0 | DI16: 0 | DJ16: 0 | DK16: 0 | DL16: 0 | DM16: 0 | DN16: 0 | DO16: 0 | DP16: 0 | DQ16: 0 | DR16: 0 | DS16: 0 | DT16: 0 | DU16: 0 | DV16: 0 | DW16: 0 | DX16: 0 | DY16: 0 | DZ16: 0 | EA16: 0 | EB16: 0 | EC16: 0 | ED16: 0 | EE16: 0 | EF16: 0 | EG16: 0 | EH16: 0 | EI16: 0 | EJ16: 0 | EK16: 0 | EL16: 0 | EM16: 0 | EN16: 0 | EO16: 0 | EP16: 0 | EQ16: 0 | ER16: 0 | ES16: 0 | ET16: 0 | EU16: 0 | EV16: 0 | EW16: 0 | EX16: 0 | EY16: 0 | EZ16: 0
B17: 3 | C17: 10 | D17: Downstream | E17: Processing of sold products | F17: 0 | G17: 0 | H17: 0 | I17: 0 | J17: 0 | K17: 0 | L17: 0 | M17: 0 | N17: 0 | O17: 0 | P17: 0 | Q17: 0 | R17: 0 | S17: 0 | T17: 0 | U17: 0 | V17: 0 | W17: 0 | X17: 0 | Y17: 0 | Z17: 0 | AA17: 0 | AB17: 0 | AC17: 0 | AD17: 0 | AE17: 0 | AF17: 0 | AG17: 0 | AH17: 0 | AI17: 0 | AJ17: 0 | AK17: 0 | AL17: 0 | AM17: 0 | AN17: 0 | AO17: 0 | AP17: 0 | AQ17: 0 | AR17: 0 | AS17: 0 | AT17: 0 | AU17: 0 | AV17: 0 | AW17: 0 | AX17: 0 | AY17: 0 | AZ17: 0 | BA17: 0 | BB17: 0 | BC17: 0 | BD17: 0 | BE17: 0 | BF17: 0 | BG17: 0 | BH17: 0 | BI17: 0 | BJ17: 0 | BK17: 0 | BL17: 0 | BM17: 0 | BN17: 0 | BO17: 0 | BP17: 0 | BQ17: 0 | BR17: 0 | BS17: 0 | BT17: 0 | BU17: 0 | BV17: 0 | BW17: 0 | BX17: 0 | BY17: 0 | BZ17: 0 | CA17: 0 | CB17: 0 | CC17: 0 | CD17: 0 | CE17: 0 | CF17: 0 | CG17: 0 | CH17: 0 | CI17: 0 | CJ17: 0 | CK17: 0 | CL17: 0 | CM17: 0 | CN17: 0 | CO17: 0 | CP17: 0 | CQ17: 0 | CR17: 0 | CS17: 0 | CT17: 0 | CU17: 0 | CV17: 0 | CW17: 0 | CX17: 0 | CY17: 0 | CZ17: 0 | DA17: 0 | DB17: 0 | DC17: 0 | DD17: 0 | DE17: 0 | DF17: 0 | DG17: 0 | DH17: 0 | DI17: 0 | DJ17: 0 | DK17: 0 | DL17: 0 | DM17: 0 | DN17: 0 | DO17: 0 | DP17: 0 | DQ17: 0 | DR17: 0 | DS17: 0 | DT17: 0 | DU17: 0 | DV17: 0 | DW17: 0 | DX17: 0 | DY17: 0 | DZ17: 0 | EA17: 0 | EB17: 0 | EC17: 0 | ED17: 0 | EE17: 0 | EF17: 0 | EG17: 0 | EH17: 0 | EI17: 0 | EJ17: 0 | EK17: 0 | EL17: 0 | EM17: 0 | EN17: 0 | EO17: 0 | EP17: 0 | EQ17: 0 | ER17: 0 | ES17: 0 | ET17: 0 | EU17: 0 | EV17: 0 | EW17: 0 | EX17: 0 | EY17: 0 | EZ17: 0
B18: 3 | C18: 11 | D18: Downstream | E18: Use of sold products | F18: 1722.23 | G18: 0 | H18: 0 | I18: 836.84893 | J18: 0 | K18: 0 | L18: 0 | M18: 0 | N18: 0 | O18: 0 | P18: 0 | Q18: 0 | R18: 474.82489 | S18: 0 | T18: 0 | U18: 0 | V18: 0 | W18: 0 | X18: 0 | Y18: 0 | Z18: 0 | AA18: 0 | AB18: 0 | AC18: 0 | AD18: 0 | AE18: 0 | AF18: 0 | AG18: 0 | AH18: 0 | AI18: 0 | AJ18: 0 | AK18: 0 | AL18: 0 | AM18: 0 | AN18: 0 | AO18: 0 | AP18: 0 | AQ18: 0 | AR18: 0 | AS18: 0 | AT18: 410.55622 | AU18: 0 | AV18: 0 | AW18: 0 | AX18: 0 | AY18: 0 | AZ18: 0 | BA18: 0 | BB18: 0 | BC18: 0 | BD18: 0 | BE18: 0 | BF18: 0 | BG18: 0 | BH18: 0 | BI18: 0 | BJ18: 0 | BK18: 0 | BL18: 0 | BM18: 0 | BN18: 0 | BO18: 0 | BP18: 0 | BQ18: 0 | BR18: 0 | BS18: 0 | BT18: 0 | BU18: 0 | BV18: 0 | BW18: 0 | BX18: 0 | BY18: 0 | BZ18: 0 | CA18: 0 | CB18: 0 | CC18: 0 | CD18: 0 | CE18: 0 | CF18: 0 | CG18: 0 | CH18: 0 | CI18: 0 | CJ18: 0 | CK18: 0 | CL18: 0 | CM18: 0 | CN18: 0 | CO18: 0 | CP18: 0 | CQ18: 0 | CR18: 0 | CS18: 0 | CT18: 0 | CU18: 0 | CV18: 0 | CW18: 0 | CX18: 0 | CY18: 0 | CZ18: 0 | DA18: 0 | DB18: 0 | DC18: 0 | DD18: 0 | DE18: 0 | DF18: 0 | DG18: 0 | DH18: 0 | DI18: 0 | DJ18: 0 | DK18: 0 | DL18: 0 | DM18: 0 | DN18: 0 | DO18: 0 | DP18: 0 | DQ18: 0 | DR18: 0 | DS18: 0 | DT18: 0 | DU18: 0 | DV18: 0 | DW18: 0 | DX18: 0 | DY18: 0 | DZ18: 0 | EA18: 0 | EB18: 0 | EC18: 0 | ED18: 0 | EE18: 0 | EF18: 0 | EG18: 0 | EH18: 0 | EI18: 0 | EJ18: 0 | EK18: 0 | EL18: 0 | EM18: 0 | EN18: 0 | EO18: 0 | EP18: 0 | EQ18: 0 | ER18: 0 | ES18: 0 | ET18: 0 | EU18: 0 | EV18: 0 | EW18: 0 | EX18: 0 | EY18: 0 | EZ18: 0
B19: 3 | C19: 12 | D19: Downstream | E19: End of life treatment of sold products | F19: 93.945599 | G19: 0 | H19: 0.57680054 | I19: 1.2306791 | J19: 0.055576556 | K19: 0 | L19: 0.59764383 | M19: 0.3078373 | N19: 0 | O19: 0 | P19: 0 | Q19: 0 | R19: 1.8449892 | S19: 0 | T19: 2.9194981 | U19: 0.84914508 | V19: 0.40394729 | W19: 0 | X19: 0.0089170696 | Y19: 0 | Z19: 1.5339452 | AA19: 0.11418295 | AB19: 0.70097799 | AC19: 0 | AD19: 0.72643772 | AE19: 2.5317581 | AF19: 0.23304538 | AG19: 0.25322447 | AH19: 0.17025712 | AI19: 0 | AJ19: 0 | AK19: 1.317216 | AL19: 0.86566083 | AM19: 0.02937186 | AN19: 0 | AO19: 0 | AP19: 0 | AQ19: 0.14225297 | AR19: 0 | AS19: 0.28026266 | AT19: 0.036699654 | AU19: 0.0016949375 | AV19: 3.4470017 | AW19: 0.072060915 | AX19: 0.47045653 | AY19: 0 | AZ19: 0.1525659 | BA19: 0 | BB19: 0.21202722 | BC19: 1.0599384 | BD19: 0 | BE19: 0 | BF19: 1.1286792 | BG19: 1.1120937 | BH19: 0.012102973 | BI19: 0 | BJ19: 0 | BK19: 2.2239286 | BL19: 0 | BM19: 0 | BN19: 0 | BO19: 0 | BP19: 0 | BQ19: 0.4584399 | BR19: 0.72724682 | BS19: 0.51792517 | BT19: 2.6303222 | BU19: 2.1598601 | BV19: 1.6570273 | BW19: 0 | BX19: 0 | BY19: 0 | BZ19: 0 | CA19: 0 | CB19: 0 | CC19: 0 | CD19: 0 | CE19: 0 | CF19: 0.087382213 | CG19: 0 | CH19: 0 | CI19: 0 | CJ19: 0 | CK19: 0 | CL19: 0.34890303 | CM19: 0.26315269 | CN19: 0 | CO19: 0.040601962 | CP19: 0 | CQ19: 0 | CR19: 0 | CS19: 0 | CT19: 0 | CU19: 0 | CV19: 0 | CW19: 0 | CX19: 0 | CY19: 0.020078676 | CZ19: 0 | DA19: 0 | DB19: 0 | DC19: 0 | DD19: 0 | DE19: 2.8248762e-05 | DF19: 0 | DG19: 0 | DH19: 0.0098646205 | DI19: 0.39246296 | DJ19: 0 | DK19: 0 | DL19: 0 | DM19: 0 | DN19: 1.5902825 | DO19: 0.081742556 | DP19: 0.018774294 | DQ19: 0.35116621 | DR19: 0 | DS19: 0 | DT19: 0 | DU19: 0 | DV19: 0 | DW19: 0 | DX19: 0.23311612 | DY19: 0.42843672 | DZ19: 0 | EA19: 0 | EB19: 0 | EC19: 0 | ED19: 0.00034041723 | EE19: 0 | EF19: 0 | EG19: 0 | EH19: 0.092409843 | EI19: 0.4176582 | EJ19: 0 | EK19: 35.090592 | EL19: 0 | EM19: 0 | EN19: 0 | EO19: 0 | EP19: 0 | EQ19: 0 | ER19: 0.99872011 | ES19: 0.045196828 | ET19: 0 | EU19: 15.647099 | EV19: 0 | EW19: 1.7640913 | EX19: 1.4949719 | EY19: 0 | EZ19: 0
... B22: 3 | C22: 15 | D22: Downstream | E22: Investments | F22: 0 | G22: 0 | H22: 0 | I22: 0 | J22: 0 | K22: 0 | L22: 0 | M22: 0 | N22: 0 | O22: 0 | P22: 0 | Q22: 0 | R22: 0 | S22: 0 | T22: 0 | U22: 0 | V22: 0 | W22: 0 | X22: 0 | Y22: 0 | Z22: 0 | AA22: 0 | AB22: 0 | AC22: 0 | AD22: 0 | AE22: 0 | AF22: 0 | AG22: 0 | AH22: 0 | AI22: 0 | AJ22: 0 | AK22: 0 | AL22: 0 | AM22: 0 | AN22: 0 | AO22: 0 | AP22: 0 | AQ22: 0 | AR22: 0 | AS22: 0 | AT22: 0 | AU22: 0 | AV22: 0 | AW22: 0 | AX22: 0 | AY22: 0 | AZ22: 0 | BA22: 0 | BB22: 0 | BC22: 0 | BD22: 0 | BE22: 0 | BF22: 0 | BG22: 0 | BH22: 0 | BI22: 0 | BJ22: 0 | BK22: 0 | BL22: 0 | BM22: 0 | BN22: 0 | BO22: 0 | BP22: 0 | BQ22: 0 | BR22: 0 | BS22: 0 | BT22: 0 | BU22: 0 | BV22: 0 | BW22: 0 | BX22: 0 | BY22: 0 | BZ22: 0 | CA22: 0 | CB22: 0 | CC22: 0 | CD22: 0 | CE22: 0 | CF22: 0 | CG22: 0 | CH22: 0 | CI22: 0 | CJ22: 0 | CK22: 0 | CL22: 0 | CM22: 0 | CN22: 0 | CO22: 0 | CP22: 0 | CQ22: 0 | CR22: 0 | CS22: 0 | CT22: 0 | CU22: 0 | CV22: 0 | CW22: 0 | CX22: 0 | CY22: 0 | CZ22: 0 | DA22: 0 | DB22: 0 | DC22: 0 | DD22: 0 | DE22: 0 | DF22: 0 | DG22: 0 | DH22: 0 | DI22: 0 | DJ22: 0 | DK22: 0 | DL22: 0 | DM22: 0 | DN22: 0 | DO22: 0 | DP22: 0 | DQ22: 0 | DR22: 0 | DS22: 0 | DT22: 0 | DU22: 0 | DV22: 0 | DW22: 0 | DX22: 0 | DY22: 0 | DZ22: 0 | EA22: 0 | EB22: 0 | EC22: 0 | ED22: 0 | EE22: 0 | EF22: 0 | EG22: 0 | EH22: 0 | EI22: 0 | EJ22: 0 | EK22: 0 | EL22: 0 | EM22: 0 | EN22: 0 | EO22: 0 | EP22: 0 | EQ22: 0 | ER22: 0 | ES22: 0 | ET22: 0 | EU22: 0 | EV22: 0 | EW22: 0 | EX22: 0 | EY22: 0 | EZ22: 0
E23: Total LB | F23: 271201.24 | G23: 0.28440293 | H23: 2496.3985 | I23: 8840.9935 | J23: 1602.6604 | K23: 6.4529679 | L23: 3057.6916 | M23: 400.6489 | N23: 0 | O23: 27.413034 | P23: 0 | Q23: 192.44666 | R23: 10532.055 | S23: 0 | T23: 15894.003 | U23: 1760.202 | V23: 1806.7775 | W23: 3.5991839 | X23: 44.351298 | Y23: 4.831987 | Z23: 3470.2277 | AA23: 587.09843 | AB23: 1821.6049 | AC23: 8.1691469 | AD23: 1372.9907 | AE23: 4860.4295 | AF23: 581.33666 | AG23: 271.83611 | AH23: 2653.199 | AI23: 8.6253776 | AJ23: 2.7628955 | AK23: 6475.8029 | AL23: 12329.606 | AM23: 1150.2123 | AN23: 372.11704 | AO23: 1.3245968 | AP23: 12.586376 | AQ23: 175.42838 | AR23: 407.52433 | AS23: 450.40882 | AT23: 1544.361 | AU23: 76.266098 | AV23: 13788.598 | AW23: 187.37707 | AX23: 4143.2979 | AY23: 181.33566 | AZ23: 690.70081 | BA23: -535.5776 | BB23: 1198.685 | BC23: 2433.9803 | BD23: 0 | BE23: 28.630139 | BF23: 2669.1129 | BG23: 3870.3122 | BH23: -1.522807 | BI23: 45.03751 | BJ23: 260.94811 | BK23: 6093.1008 | BL23: 63.156089 | BM23: 10.082632 | BN23: 0.90739826 | BO23: 11.238137 | BP23: 0 | BQ23: 1905.6095 | BR23: 2325.1231 | BS23: 741.62211 | BT23: 3292.5042 | BU23: 3717.851 | BV23: 2108.1901 | BW23: 2092.3435 | BX23: 0.017700869 | BY23: 0.0031054156 | BZ23: 10.193881 | CA23: 3002.3639 | CB23: 307.82805 | CC23: -215.23263 | CD23: 3.7014442 | CE23: 38.143195 | CF23: 1263.2441 | CG23: 248.12249 | CH23: 23.816953 | CI23: 60.621688 | CJ23: 834.36843 | CK23: 764.59928 | CL23: 2452.1803 | CM23: 593.82184 | CN23: 458.00292 | CO23: 308.39762 | CP23: 110.10946 | CQ23: 499.07718 | CR23: 1381.8407 | CS23: 691.76862 | CT23: 800.56658 | CU23: 2609.1283 | CV23: 46.510961 | CW23: 468.5193 | CX23: 349.35067 | CY23: 247.87074 | CZ23: 495.09598 | DA23: 122.62164 | DB23: 3020.2558 | DC23: 283.6811 | DD23: 335.84135 | DE23: 164.33591 | DF23: 338.7349 | DG23: 260.74008 | DH23: 103.89554 | DI23: 1298.2452 | DJ23: 302.43204 | DK23: -14.727582 | DL23: 0.0031054156 | DM23: 0 | DN23: 1566.1138 | DO23: 198.17645 | DP23: 106.73864 | DQ23: 787.36002 | DR23: 522.90116 | DS23: 2.6506294 | DT23: 0.049376107 | DU23: 759.47999 | DV23: 2305.9435 | DW23: 784.75346 | DX23: 1589.7394 | DY23: 1244.6299 | DZ23: 28.763249 | EA23: 18.471641 | EB23: 26.835521 | EC23: 3.74956 | ED23: 25.457172 | EE23: 84.361408 | EF23: 10.675719 | EG23: 4.2368038 | EH23: 1573.9651 | EI23: 2562.0037 | EJ23: 13521.81 | EK23: 19399.748 | EL23: 835.38869 | EM23: 167.56362 | EN23: 27.763103 | EO23: -26.155303 | EP23: 1.7901602 | EQ23: 1.6989801 | ER23: 24250.927 | ES23: 314.64284 | ET23: 320.66967 | EU23: 21485.208 | EV23: 1.6989801 | EW23: 1905.0944 | EX23: 14731.279 | EY23: 454.87399 | EZ23: 1969.4684
E24: Total MB | F24: 271483.39 | G24: 0.28440293 | H24: 2496.3985 | I24: 8840.9935 | J24: 1602.6604 | K24: 6.4529679 | L24: 3057.6916 | M24: 400.6489 | N24: 0 | O24: 27.413034 | P24: 0 | Q24: 192.44666 | R24: 10532.055 | S24: 0 | T24: 15894.003 | U24: 1760.202 | V24: 1806.7775 | W24: 3.5991839 | X24: 44.351298 | Y24: 4.831987 | Z24: 3495.2697 | AA24: 597.74418 | AB24: 1898.9215 | AC24: 8.1691469 | AD24: 1381.677 | AE24: 4891.3299 | AF24: 597.86085 | AG24: 271.83611 | AH24: 2660.0122 | AI24: 8.6253776 | AJ24: 2.7628955 | AK24: 6508.2623 | AL24: 12376.501 | AM24: 1153.2946 | AN24: 372.11704 | AO24: 1.3245968 | AP24: 12.586376 | AQ24: 177.82116 | AR24: 408.66856 | AS24: 450.40882 | AT24: 1544.361 | AU24: 78.358491 | AV24: 13513.409 | AW24: 187.7068 | AX24: 4145.8571 | AY24: 182.01864 | AZ24: 690.92267 | BA24: -535.5776 | BB24: 1198.685 | BC24: 2433.9803 | BD24: 0 | BE24: 28.630139 | BF24: 2679.7395 | BG24: 3862.8061 | BH24: -1.522807 | BI24: 45.03751 | BJ24: 260.94811 | BK24: 6154.6736 | BL24: 63.156089 | BM24: 10.082632 | BN24: 0.90739826 | BO24: 11.238137 | BP24: 0 | BQ24: 1905.6095 | BR24: 2333.2189 | BS24: 743.55932 | BT24: 3356.086 | BU24: 3757.2124 | BV24: 2123.7642 | BW24: 2103.8699 | BX24: 0.017700869 | BY24: 0.0031054156 | BZ24: 10.193881 | CA24: 3002.3639 | CB24: 307.82805 | CC24: -215.23263 | CD24: 3.7014442 | CE24: 38.143195 | CF24: 1268.472 | CG24: 253.50213 | CH24: 24.466645 | CI24: 60.721276 | CJ24: 840.89599 | CK24: 769.18331 | CL24: 2470.491 | CM24: 596.75647 | CN24: 470.61393 | CO24: 310.97991 | CP24: 112.06391 | CQ24: 506.6529 | CR24: 1384.2967 | CS24: 692.95231 | CT24: 807.50168 | CU24: 2631.1724 | CV24: 56.13186 | CW24: 476.74004 | CX24: 352.00241 | CY24: 250.68345 | CZ24: 496.45003 | DA24: 125.44385 | DB24: 3038.9235 | DC24: 291.48068 | DD24: 340.13791 | DE24: 166.11524 | DF24: 342.2312 | DG24: 262.98602 | DH24: 105.3939 | DI24: 1319.7025 | DJ24: 304.38113 | DK24: -14.727582 | DL24: 0.0031054156 | DM24: 0 | DN24: 1596.4917 | DO24: 205.73052 | DP24: 109.78656 | DQ24: 797.81973 | DR24: 552.0798 | DS24: 2.6506294 | DT24: 0.049376107 | DU24: 748.51638 | DV24: 2304.8246 | DW24: 786.64844 | DX24: 1589.7394 | DY24: 1244.6299 | DZ24: 28.763249 | EA24: 18.471641 | EB24: 26.835521 | EC24: 3.74956 | ED24: 25.457172 | EE24: 84.361408 | EF24: 10.675719 | EG24: 4.2368038 | EH24: 1573.9651 | EI24: 2562.0037 | EJ24: 13528.722 | EK24: 19399.748 | EL24: 835.38869 | EM24: 167.56362 | EN24: 27.763103 | EO24: -26.155303 | EP24: 1.7901602 | EQ24: 1.6989801 | ER24: 24139.722 | ES24: 314.64284 | ET24: 320.66967 | EU24: 21421.146 | EV24: 1.6989801 | EW24: 1905.0944 | EX24: 14731.279 | EY24: 454.87399 | EZ24: 1970.4723
B26: FY23 Summary (excl. Divestments)
B28: Scope | C28: Category | D28: Upstream/Downstream | E28: Emission Source | F28: tCO2e Market | G28: tCO2e Location | I28: Extrapolated sites
B29: 1 | C29: - | D29: Internal | E29: Stationary combustion | F29: 1355.3302 | G29: 1355.3302 | I29: R2210 | J29: L7010 | K29: R2180 | L29: C1530 | M29: S1040
B30: 1 | C30: - | D30: Internal | E30: Company vehicles | F30: 1917.79 | G30: 1917.79 | I30: R2220 | J30: S1030 | K30: R2190 | L30: S1020
B31: 1 | C31: - | D31: Internal | E31: Fugitive emissions | F31: 0 | G31: 0 | I31: R4150 | J31: L7030 | K31: R5100 | L31: S8030
B32: 1 | C32: - | D32: Internal | E32: Refrigerants | F32: 1.5385 | G32: 1.5385 | I32: R4160 | J32: S1010 | K32: C1510 | L32: C5520
B33: 1 | C33: - | D33: Internal | E33: Extrapolated tCo2e | F33: 328.95312 | G33: 328.95312 | I33: C5510 | J33: L7020 | K33: C1520 | L33: C1040
B34: 2 | C34: - | D34: Internal | E34: Electricity usage | F34: 5272.9372 | G34: 4764.3818
B35: 2 | C35: - | D35: Internal | E35: Heating | F35: 53.555697 | G35: 53.555697 | I35: Divested sites
B36: 2 | C36: - | D36: Internal | E36: Cooling | F36: 0 | G36: 0 | I36: C5010 | J36: C6020
B37: 2 | C37: - | D37: Internal | E37: Extrapolated tCo2e | F37: 1023.98 | G37: 1250.3916
B38: 3 | C38: 1 | D38: Upstream | E38: Purchased goods and services | F38: 191705.14 | G38: 191705.14
B39: 3 | C39: 2 | D39: Upstream | E39: Capital goods | F39: 8445.8016 | G39: 8445.8016
B40: 3 | C40: 3 | D40: Upstream | E40: Fuel and energy related activities | F40: 2299.2305 | G40: 2299.2305
B41: 3 | C41: 4 | D41: Upstream | E41: Upstream transportation and distribution | F41: 41103.353 | G41: 41103.353
B42: 3 | C42: 5 | D42: Upstream | E42: Waste generated in operations | F42: 721.55269 | G42: 721.55269
B43: 3 | C43: 6 | D43: Upstream | E43: Business travel | F43: 6514.0033 | G43: 6514.0033
B44: 3 | C44: 7 | D44: Upstream | E44: Employee commuting | F44: 6123.1243 | G44: 6123.1243
B45: 3 | C45: 8 | D45: Upstream | E45: Upstream leased assets | F45: 2800.9244 | G45: 2800.9244
B46: 3 | C46: 9 | D46: Downstream | E46: Downstream transportation and distribution | F46: 0 | G46: 0
B47: 3 | C47: 10 | D47: Downstream | E47: Processing of sold products | F47: 0 | G47: 0
B48: 3 | C48: 11 | D48: Downstream | E48: Use of sold products | F48: 1722.23 | G48: 1722.23
B49: 3 | C49: 12 | D49: Downstream | E49: End of life treatment of sold products | F49: 93.945599 | G49: 93.945599
... B52: 3 | C52: 15 | D52: Downstream | E52: Investments | F52: 0 | G52: 0
B53: Total | F53: 271483.39 | G53: 271201.24

Sheet FY22
B2: FY22 Footprint by Entity Code
BO3: Divested | BP3: Divested | EX3: Divested | EZ3: Divested | FA3: Divested | FB3: Divested | FC3: Divested | FH3: Divested | FI3: Divested | FJ3: Divested
B4: Scope | C4: Category | D4: Upstream/Downstream | E4: Emission Source | F4: Diploma Total (excl. Divestments) | G4: G3010 | H4: L2050 | I4: L3015 | J4: S7030 | K4: S7040 | L4: S7060 | M4: S7090 | N4: S6040 | O4: G5020 | P4: L2010 | Q4: L2020 | R4: L2030 | S4: L2040 | T4: S2050 | U4: S2060 | V4: C5520 | W4: S4030 | X4: G5040 | Y4: L2500 | Z4: L7010 | AA4: S4010 | AB4: C2540 | AC4: C4050 | AD4: C2090 | AE4: C2091 | AF4: c4030 | AG4: C7010 | AH4: G3045 | AI4: L2090 | AJ4: L5010 | AK4: S1030 | AL4: G5025 | AM4: HoIntSealsE | AN4: S1040 | AO4: S2210 | AP4: S7020 | AQ4: L2060 | AR4: L3025 | AS4: L7030 | AT4: S1010 | AU4: L2510 | AV4: L2700 | AW4: L7020 | AX4: S4020 | AY4: S6020 | AZ4: S6070 | BA4: C2530 | BB4: c1010 | BC4: C1040 | BD4: C2040 | BE4: C2041 | BF4: C2042 | BG4: C2043 | BH4: C2080 | BI4: C2551 | BJ4: C2552 | BK4: C2553 | BL4: C2554 | BM4: C2555 | BN4: C3510 | BO4: C5010 | BP4: C6020 | BQ4: C8010 | BR4: C9010 | BS4: C9050 | BT4: G2010 | BU4: G3015 | BV4: G3020 | BW4: G3041 | BX4: G4010 | BY4: G5005 | BZ4: G5010 | CA4: HoControls | CB4: HoGrp | CC4: HoIntSeals | CD4: HoLS | CE4: L5020 | CF4: R1100 | CG4: R1120 | CH4: R1140 | CI4: R1170 | CJ4: R1180 | CK4: R1190 | CL4: R1210 | CM4: R1220 | CN4: R1230 | CO4: R1240 | CP4: R2100 | CQ4: R2110 | CR4: R2120 | CS4: R2130 | CT4: R2150 | CU4: R2160 | CV4: R2170 | CW4: R2180 | CX4: R2190 | CY4: R2210 | CZ4: R2220 | DA4: R3100 | DB4: R4100 | DC4: R4110 | DD4: R4120 | DE4: R4130 | DF4: R4140 | DG4: R4150 | DH4: R4160 | DI4: R5100 | DJ4: R5110 | DK4: R5120 | DL4: R9100 | DM4: S3010 | DN4: S3030 | DO4: S4040 | DP4: S4050 | DQ4: S9010 | DR4: C1510 | DS4: C1520 | DT4: C1530 | DU4: C2045 | DV4: C2046 | DW4: C2571 | DX4: C2572 | DY4: C2573 | DZ4: C2574 | EA4: C2575 | EB4: C2576 | EC4: C2577 | ED4: C2578 | EE4: C3040 | EF4: C4510 | EG4: C5510 | EH4: C8500 | EI4: G3025 | EJ4: G5015 | EK4: HoControlsU | EL4: HoDHI | EM4: HoLSU | EN4: HoNaSeals | EO4: LCAoem | EP4: S1020 | EQ4: S2010 | ER4: S2025 | ES4: S2026 | ET4: S2310 | EU4: S8010 | EV4: S8020 | EW4: S8030 | EX4: L4010 | EY4: S2020 | EZ4: S5010 | FA4: S5020 | FB4: S5050 | FC4: S5070 | FD4: S7050 | FE4: R1130 | FF4: R1160 | FG4: R1150 | FH4: L4040 | FI4: S5040 | FJ4: S5080 | FK4: S9020 | FL4: S7010 | FM4: R5130 | FN4: C7020 | FO4: G5075 | FP4: S7070 | FQ4: C1020
B5: 1 | C5: - | D5: Internal | E5: All Scope 1 | F5: =SUMIFS(G5:FQ5,$G$3:$FQ$3,"<>Divested") -> 3569.812 | G5: 0 | H5: 0 | I5: 0.35493936 | J5: 23.215219 | K5: 0 | L5: 163.64737 | M5: 0 | N5: 29.230127 | O5: 0 | P5: 0 | Q5: 61.76019 | R5: 1.1126664 | S5: 21.293855 | T5: 1.3626132 | U5: 0.3749202 | V5: 0 | W5: 0 | X5: 0 | Y5: 94.775422 | Z5: 0 | AA5: 98.626926 | AB5: 0 | AC5: 13.866094 | AD5: 37.2963 | AE5: 0 | AF5: 80.995908 | AG5: 30.530982 | AH5: 0 | AI5: 160.39984 | AJ5: 288.19294 | AK5: 11.780056 | AL5: 0 | AM5: 0 | AN5: 0 | AO5: 33.055464 | AP5: 2.081602 | AQ5: 0 | AR5: 9.9432714 | AS5: 0 | AT5: 45.219313 | AU5: 9.2409027 | AV5: 20.767287 | AW5: 0 | AX5: 17.069219 | AY5: 77.797463 | AZ5: 0 | BA5: 0 | BB5: 4.3531992 | BC5: 0 | BD5: 52.543112 | BE5: 0 | BF5: 0 | BG5: 0 | BH5: 50.018085 | BI5: 0 | BJ5: 0 | BK5: 0 | BL5: 0 | BM5: 0 | BN5: 0 | BO5: 42.864302 | BP5: 26.415306 | BQ5: 18.437062 | BR5: 8.8659774 | BS5: 44.535564 | BT5: 0 | BU5: 0 | BV5: 0 | BW5: 0 | BX5: 0 | BY5: 0 | BZ5: 0 | CA5: 0 | CB5: 0 | CC5: 0 | CD5: 0 | CE5: 37.238927 | CF5: 6.8209145 | CG5: 0.62721053 | CH5: 2.4472411 | CI5: 86.672297 | CJ5: 43.509415 | CK5: 89.923814 | CL5: 4.8267419 | CM5: 39.579954 | CN5: 18.15706 | CO5: 0.57680968 | CP5: 0 | CQ5: 0.82752019 | CR5: 15.550478 | CS5: 56.130275 | CT5: 33.433199 | CU5: 6.9956962 | CV5: 1.5712296 | CW5: 0.44944475 | CX5: 4.4935864 | CY5: 19.400527 | CZ5: 4.1004319 | DA5: 222.26738 | DB5: 13.01402 | DC5: 1.3625323 | DD5: 7.884981 | DE5: 14.511961 | DF5: 0.94241546 | DG5: 5.8728319 | DH5: 9.7185574 | DI5: 10.38248 | DJ5: 0 | DK5: 0 | DL5: 0 | DM5: 15.759158 | DN5: 1.3882447 | DO5: 13.766987 | DP5: 19.434978 | DQ5: 20.108879 | DR5: 24.435467 | DS5: 53.499193 | DT5: 25.551284 | DU5: 0.1022 | DV5: 8.4483127 | DW5: 0 | DX5: 0 | DY5: 0 | DZ5: 0 | EA5: 0 | EB5: 0 | EC5: 0 | ED5: 0 | EE5: 0.1242825 | EF5: 0 | EG5: 0 | EH5: 758.47546 | EI5: 0 | EJ5: 0 | EK5: 0 | EL5: 0 | EM5: 0 | EN5: 0 | EO5: 92.956886 | EP5: 0 | EQ5: 0 | ER5: 51.704258 | ES5: 0 | ET5: 58.374052 | EU5: 69.356518 | EV5: 21.621806 | EW5: 62.670174 | EX5: 103.8559 | EY5: 0 | EZ5: 0 | FA5: 0 | FB5: 0 | FC5: 0 | FD5: 0 | FE5: 0 | FF5: 0 | FG5: 0 | FH5: 0 | FI5: 0 | FJ5: 0 | FK5: 0 | FL5: 0 | FM5: 0 | FN5: 0 | FO5: 0 | FP5: 0 | FQ5: 0
B6: 2 | C6: - | D6: Internal | E6: All Scope 2 MB | F6: =SUMIFS(G6:FQ6,$G$3:$FQ$3,"<>Divested") -> 5849.8032 | G6: 0 | H6: 16.575524 | I6: 170.58699 | J6: 12.827386 | K6: 2.9100266 | L6: 74.173078 | M6: 5.7781747 | N6: 5.8716072 | O6: 0 | P6: 0 | Q6: 21.819768 | R6: 12.366229 | S6: 9.2125852 | T6: 12.193839 | U6: 15.845273 | V6: 0 | W6: 0 | X6: 0 | Y6: 36.951819 | Z6: 10.83031 | AA6: 70.418166 | AB6: 0 | AC6: 5.720866 | AD6: 26.56712 | AE6: 0 | AF6: 50.421922 | AG6: 18.791699 | AH6: 0 | AI6: 63.921341 | AJ6: 41.914662 | AK6: 6.9336926 | AL6: 0 | AM6: 0 | AN6: 0 | AO6: 10.824521 | AP6: 0.79118993 | AQ6: 0 | AR6: 4.59432 | AS6: 1.7864688 | AT6: 18.469957 | AU6: 1.2418675 | AV6: 4.7324264 | AW6: 0.69068283 | AX6: 0.62139267 | AY6: 14.264854 | AZ6: 0 | BA6: 0 | BB6: 12.427866 | BC6: 0 | BD6: 29.543038 | BE6: 0 | BF6: 0 | BG6: 0 | BH6: 77.189666 | BI6: 0 | BJ6: 0 | BK6: 0 | BL6: 0 | BM6: 0 | BN6: 0 | BO6: 21.812413 | BP6: 5.416488 | BQ6: 82.084464 | BR6: 49.73166 | BS6: 20.838114 | BT6: 10.01781 | BU6: 0 | BV6: 0 | BW6: 0 | BX6: 0 | BY6: 0 | BZ6: 0 | CA6: 0 | CB6: 0 | CC6: 0 | CD6: 0 | CE6: 2.9914459 | CF6: 0 | CG6: 0 | CH6: 0 | CI6: 16.317971 | CJ6: 15.597032 | CK6: 45.748465 | CL6: 4.9974961 | CM6: 18.78962 | CN6: 4.3063337 | CO6: 0.93918913 | CP6: 0 | CQ6: 18.683804 | CR6: 11.842684 | CS6: 13.376939 | CT6: 67.112147 | CU6: 24.868661 | CV6: 18.735193 | CW6: 4.7921527 | CX6: 5.0830618 | CY6: 2.447007 | CZ6: 5.1002112 | DA6: 45.476634 | DB6: 8.8619527 | DC6: 9.8171665 | DD6: 2.8986175 | DE6: 6.5007469 | DF6: 4.8534005 | DG6: 2.7078078 | DH6: 38.777125 | DI6: 3.5223488 | DJ6: 0 | DK6: 0 | DL6: 0 | DM6: 52.745346 | DN6: 9.447002 | DO6: 6.4607004 | DP6: 14.67083 | DQ6: 28.247648 | DR6: 11.518713 | DS6: 128.85159 | DT6: 39.656096 | DU6: 7.6868576 | DV6: 17.295526 | DW6: 0 | DX6: 0 | DY6: 0 | DZ6: 0 | EA6: 0 | EB6: 0 | EC6: 0 | ED6: 0 | EE6: 11.238601 | EF6: 66.924308 | EG6: 537.95637 | EH6: 2459.4222 | EI6: 0 | EJ6: 0 | EK6: 0 | EL6: 0 | EM6: 0 | EN6: 0 | EO6: 196.46438 | EP6: 0 | EQ6: 0 | ER6: 307.05323 | ES6: 0 | ET6: 41.25431 | EU6: 333.49013 | EV6: 61.749432 | EW6: 44.919142 | EX6: 14.226167 | EY6: 31.80815 | EZ6: 4.7035848 | FA6: 7.2743568 | FB6: 1.4572014 | FC6: 0.4800194 | FD6: 2.1409774 | FE6: 0.33060336 | FF6: 0.24364673 | FG6: 0.59971415 | FH6: 1.3825379 | FI6: 0 | FJ6: 0 | FK6: 0 | FL6: 0 | FM6: 0 | FN6: 0 | FO6: 0 | FP6: 0 | FQ6: 0
B7: 2 | D7: Internal | E7: All Scope 2 LB | F7: =SUMIFS(G7:FQ7,$G$3:$FQ$3,"<>Divested") -> 5618.5539 | G7: 0 | H7: 16.665555 | I7: 171.51355 | J7: 30.649054 | K7: 2.9258327 | L7: 74.575955 | M7: 5.8095594 | N7: 6.6495952 | O7: 0 | P7: 0 | Q7: 23.454888 | R7: 13.292924 | S7: 9.9029537 | T7: 13.107616 | U7: 17.032679 | V7: 0 | W7: 0 | X7: 0 | Y7: 6.7506251 | Z7: 1.8473383 | AA7: 13.677815 | AB7: 0 | AC7: 6.301551 | AD7: 14.8135 | AE7: 0 | AF7: 28.114645 | AG7: 10.478021 | AH7: 0 | AI7: 32.975963 | AJ7: 33.534077 | AK7: 4.3328165 | AL7: 0 | AM7: 0 | AN7: 0 | AO7: 8.8399215 | AP7: 1.2447481 | AQ7: 0 | AR7: 4.33908 | AS7: 0.020890564 | AT7: 250.67668 | AU7: 0.20581649 | AV7: 0.78371319 | AW7: 0.11438049 | AX7: 0.1029843 | AY7: 17.728644 | AZ7: 0 | BA7: 0 | BB7: 12.137882 | BC7: 0 | BD7: 28.8537 | BE7: 0 | BF7: 0 | BG7: 0 | BH7: 75.388574 | BI7: 0 | BJ7: 0 | BK7: 0 | BL7: 0 | BM7: 0 | BN7: 0 | BO7: 21.303456 | BP7: 5.2901033 | BQ7: 80.16916 | BR7: 48.571255 | BS7: 20.351891 | BT7: 9.7840611 | BU7: 0 | BV7: 0 | BW7: 0 | BX7: 0 | BY7: 0 | BZ7: 0 | CA7: 0 | CB7: 0 | CC7: 0 | CD7: 0 | CE7: 1.9479867 | CF7: 0 | CG7: 0 | CH7: 0 | CI7: 8.698757 | CJ7: 8.3144398 | CK7: 24.387516 | CL7: 2.6640569 | CM7: 10.016339 | CN7: 2.2956132 | CO7: 0.50066138 | CP7: 0 | CQ7: 9.9599315 | CR7: 6.3130786 | CS7: 7.1309562 | CT7: 35.776032 | CU7: 13.256944 | CV7: 9.9873256 | CW7: 2.5545928 | CX7: 2.7096702 | CY7: 1.3044464 | CZ7: 2.7188121 | DA7: 24.242609 | DB7: 6.1724791 | DC7: 5.2333188 | DD7: 1.5451902 | DE7: 3.4654074 | DF7: 2.5872427 | DG7: 1.4434737 | DH7: 20.671246 | DI7: 1.8776878 | DJ7: 0 | DK7: 0 | DL7: 0 | DM7: 28.117402 | DN7: 5.0359921 | DO7: 6.3099507 | DP7: 14.32851 | DQ7: 27.588536 | DR7: 20.769901 | DS7: 129.79573 | DT7: 38.057095 | DU7: 7.8186859 | DV7: 17.409152 | DW7: 0 | DX7: 0 | DY7: 0 | DZ7: 0 | EA7: 0 | EB7: 0 | EC7: 0 | ED7: 0 | EE7: 11.029766 | EF7: 65.724791 | EG7: 532.12386 | EH7: 2418.8407 | EI7: 0 | EJ7: 0 | EK7: 0 | EL7: 0 | EM7: 0 | EN7: 0 | EO7: 199.31798 | EP7: 0 | EQ7: 0 | ER7: 283.94616 | ES7: 0 | ET7: 39.884994 | EU7: 313.87254 | EV7: 63.68796 | EW7: 44.072059 | EX7: 7.9323361 | EY7: 32.027226 | EZ7: 1.2017781 | FA7: 7.2743568 | FB7: 0.53456725 | FC7: 0.062209017 | FD7: 2.1526063 | FE7: 0.32288928 | FF7: 0.23796164 | FG7: 0.58572082 | FH7: 1.3502787 | FI7: 0 | FJ7: 0 | FK7: 0 | FL7: 0 | FM7: 0 | FN7: 0 | FO7: 0 | FP7: 0 | FQ7: 0
B8: 3 | C8: 1 | D8: Upstream | E8: Purchased goods and services | F8: =SUMIFS(G8:FQ8,$G$3:$FQ$3,"<>Divested") -> 154151.64 | G8: 3.2269331 | H8: 2619.963 | I8: 7153.3533 | J8: 937.57984 | K8: 63.261552 | L8: 1709.3097 | M8: 38.99719 | N8: 1090.0556 | O8: 0 | P8: -8.9191836 | Q8: 8311.5881 | R8: 5680.3414 | S8: 5630.0725 | T8: 1139.7804 | U8: 1314.4504 | V8: 0.2969612 | W8: 151.73144 | X8: -63.059566 | Y8: 2751.297 | Z8: 316.49291 | AA8: 1108.2225 | AB8: 0 | AC8: 821.14604 | AD8: 442.83038 | AE8: 0 | AF8: 1948.279 | AG8: 1937.968 | AH8: 18.58531 | AI8: 2398.7292 | AJ8: 4200.222 | AK8: 899.77399 | AL8: 0 | AM8: 0 | AN8: 5.4685528 | AO8: 93.93731 | AP8: 138.24676 | AQ8: 404.58738 | AR8: 892.69114 | AS8: 63.360117 | AT8: 3218.7647 | AU8: 163.20592 | AV8: 1907.0475 | AW8: 146.56122 | AX8: 513.31353 | AY8: 2068.4347 | AZ8: 0 | BA8: 3.6310835 | BB8: 1528.3039 | BC8: 0.89774055 | BD8: 1462.6436 | BE8: -5.6716948 | BF8: 24.68316 | BG8: 129.09258 | BH8: 2177.9464 | BI8: 0 | BJ8: 0 | BK8: 0 | BL8: 0 | BM8: 0 | BN8: 764.70508 | BO8: 3557.4666 | BP8: 1089.1778 | BQ8: 1466.4461 | BR8: 2213.2394 | BS8: 1421.8289 | BT8: 3188.8431 | BU8: 652.90835 | BV8: 0.050545148 | BW8: 0.46098604 | BX8: 0.0005026478 | BY8: 0 | BZ8: 99.22187 | CA8: 469.03925 | CB8: 0 | CC8: 0 | CD8: 0 | CE8: 649.39871 | CF8: -0.043620539 | CG8: 0 | CH8: 0 | CI8: 243.60655 | CJ8: 302.94138 | CK8: 911.92881 | CL8: 238.87408 | CM8: 255.69256 | CN8: 146.07426 | CO8: 11.399287 | CP8: 0 | CQ8: 519.873 | CR8: 313.8299 | CS8: 353.19776 | CT8: 917.53715 | CU8: -26.756125 | CV8: 176.28728 | CW8: 282.10001 | CX8: 159.07762 | CY8: 341.63222 | CZ8: 56.246827 | DA8: 1359.5527 | DB8: 102.77307 | DC8: 129.6547 | DD8: 70.6088 | DE8: 159.125 | DF8: 96.585704 | DG8: 62.327421 | DH8: 658.42846 | DI8: 26.768079 | DJ8: 0.58606817 | DK8: 0.00019332608 | DL8: 0 | DM8: 461.58492 | DN8: 79.104109 | DO8: 56.745444 | DP8: 605.3168 | DQ8: 170.60066 | DR8: 452.87973 | DS8: 1070.0337 | DT8: 365.45568 | DU8: 1240.5024 | DV8: 613.06328 | DW8: 0 | DX8: 0 | DY8: 0 | DZ8: 0 | EA8: 0 | EB8: 0 | EC8: 0 | ED8: 0 | EE8: 326.86716 | EF8: 1708.9757 | EG8: 9093.455 | EH8: 3171.6579 | EI8: 633.96932 | EJ8: -26.842556 | EK8: 0 | EL8: -8.1055637 | EM8: 0 | EN8: 8.1055637 | EO8: 22155.434 | EP8: 136.72325 | EQ8: 151.78747 | ER8: 11777.627 | ES8: 0 | ET8: 1420.1594 | EU8: 10716.976 | EV8: 350.5603 | EW8: 1010.4558 | EX8: 623.00849 | EY8: 0 | EZ8: 158.17205 | FA8: 241.55887 | FB8: 48.787275 | FC8: 13.863832 | FD8: 24.225316 | FE8: 10.985171 | FF8: 8.9040879 | FG8: 16.599829 | FH8: 28.012808 | FI8: 0.0072238241 | FJ8: 0 | FK8: -1.1320572 | FL8: 2.3874246 | FM8: 0.084635661 | FN8: 0.58411305 | FO8: 1.3551281 | FP8: -4.2208501 | FQ8: 0.0024447463
B9: 3 | C9: 2 | D9: Upstream | E9: Capital goods | F9: =SUMIFS(G9:FQ9,$G$3:$FQ$3,"<>Divested") -> 5971.4072 | G9: 0 | H9: 33.006963 | I9: 305.60767 | J9: 25.786915 | K9: 0 | L9: 90.571407 | M9: 0 | N9: 12.098101 | O9: 0 | P9: 2.3684887 | Q9: 82.263382 | R9: 115.94725 | S9: 2339.712 | T9: 36.82451 | U9: 2.7611816 | V9: 0 | W9: 0 | X9: 0 | Y9: 95.003086 | Z9: 2.7914662 | AA9: 21.161681 | AB9: 0 | AC9: 13.513406 | AD9: 14.565131 | AE9: 0 | AF9: 32.96296 | AG9: 5.2841781 | AH9: 0 | AI9: 77.498658 | AJ9: 34.818838 | AK9: 1.7017103 | AL9: 0 | AM9: 0 | AN9: 0 | AO9: 2.1139674 | AP9: 3.7590375 | AQ9: 0 | AR9: 16.686392 | AS9: 0 | AT9: 233.85815 | AU9: 0 | AV9: 45.250796 | AW9: 0 | AX9: 0 | AY9: 190.73004 | AZ9: 0 | BA9: 3.7844193 | BB9: 7.0515748 | BC9: 0 | BD9: 10.003325 | BE9: 0 | BF9: 0 | BG9: 0 | BH9: 35.0062 | BI9: 0 | BJ9: 0 | BK9: 0 | BL9: 0 | BM9: 0 | BN9: 0 | BO9: 8.0800987 | BP9: 0 | BQ9: 155.97984 | BR9: 5.5609745 | BS9: 50.060467 | BT9: 285.94676 | BU9: 0 | BV9: 0 | BW9: 0 | BX9: 0 | BY9: 0 | BZ9: 0 | CA9: 0 | CB9: 0 | CC9: 0 | CD9: 0 | CE9: 0 | CF9: 0 | CG9: 0 | CH9: 0 | CI9: 16.325298 | CJ9: 14.257762 | CK9: 55.535342 | CL9: 14.05004 | CM9: 5.1802705 | CN9: 8.1063743 | CO9: -8.0255595 | CP9: 0 | CQ9: 0.39095193 | CR9: 5.4759927 | CS9: 2.2005805 | CT9: 74.012784 | CU9: 0 | CV9: 10.639605 | CW9: 6.9733618 | CX9: 10.985274 | CY9: 0 | CZ9: 0 | DA9: 60.059483 | DB9: 1.5457627 | DC9: 0 | DD9: 0 | DE9: 0 | DF9: 0 | DG9: 0 | DH9: 115.36306 | DI9: 31.414747 | DJ9: 0 | DK9: 0 | DL9: 0 | DM9: 0 | DN9: 0 | DO9: 0 | DP9: 69.46086 | DQ9: 0 | DR9: 0 | DS9: 98.758412 | DT9: 11.735967 | DU9: 98.411368 | DV9: 0 | DW9: 0 | DX9: 0 | DY9: 0 | DZ9: 0 | EA9: 0 | EB9: 0 | EC9: 0 | ED9: 0 | EE9: 6.1147748 | EF9: 13.825543 | EG9: 0 | EH9: 518.70477 | EI9: 0 | EJ9: 0 | EK9: 0 | EL9: 0 | EM9: 0 | EN9: 0 | EO9: 87.550869 | EP9: 0 | EQ9: 0 | ER9: 151.34932 | ES9: 0 | ET9: 0 | EU9: 96.502901 | EV9: 0 | EW9: 0 | EX9: 19.16267 | EY9: 0 | EZ9: 0.2207746 | FA9: 0.1909568 | FB9: 0 | FC9: 0 | FD9: 0 | FE9: 1.0837612 | FF9: 0 | FG9: 1.3766413 | FH9: 0 | FI9: 0 | FJ9: -0.40065237 | FK9: 0 | FL9: 0 | FM9: 0 | FN9: 0 | FO9: 0 | FP9: 0 | FQ9: 0
B10: 3 | C10: 3 | D10: Upstream | E10: Fuel and energy related activities | F10: =SUMIFS(G10:FQ10,$G$3:$FQ$3,"<>Divested") -> 2160.8372 | G10: 0 | H10: 3.6151833 | I10: 37.307362 | J10: 13.011484 | K10: 0.63468762 | L10: 57.893027 | M10: 1.2602414 | N10: 9.5397257 | O10: 0 | P10: 0 | Q10: 16.588132 | R10: 3.6260216 | S10: 6.187773 | T10: 3.6206977 | U10: 4.4671327 | V10: 0 | W10: 0 | X10: 0 | Y10: 26.266586 | Z10: 1.1058217 | AA10: 25.912059 | AB10: 0 | AC10: 6.0062121 | AD10: 11.398 | AE10: 0 | AF10: 25.565711 | AG10: 9.2671092 | AH10: 0 | AI10: 47.605296 | AJ10: 72.240799 | AK10: 3.5325564 | AL10: 0 | AM10: 0 | AN10: 0 | AO10: 7.49468 | AP10: 0.94436736 | AQ10: 0 | AR10: 3.5903294 | AS10: 0.003772161 | AT10: 94.273442 | AU10: 2.4326981 | AV10: 5.9793796 | AW10: 0.13278735 | AX10: 4.3491891 | AY10: 22.724183 | AZ10: 0 | BA10: 0 | BB10: 5.3428408 | BC10: 0 | BD10: 20.052985 | BE10: 0 | BF10: 0 | BG10: 0 | BH10: 36.199664 | BI10: 0 | BJ10: 0 | BK10: 0 | BL10: 0 | BM10: 0 | BN10: 0 | BO10: 16.195203 | BP10: 6.6225582 | BQ10: 32.117045 | BR10: 19.1468 | BS10: 17.837938 | BT10: 3.5362078 | BU10: 0 | BV10: 0 | BW10: 0 | BX10: 0 | BY10: 0 | BZ10: 0 | CA10: 0 | CB10: 0 | CC10: 0 | CD10: 0 | CE10: 9.7079227 | CF10: 1.6585735 | CG10: 0.15251251 | CH10: 0.59507113 | CI10: 23.252362 | CJ10: 13.077673 | CK10: 26.27555 | CL10: 1.7574626 | CM10: 7.7902609 | CN10: 4.7254813 | CO10: 0.30926184 | CP10: 0 | CQ10: 3.5055958 | CR10: 5.4048763 | CS10: 11.460397 | CT10: 19.755177 | CU10: 6.1761284 | CV10: 3.6308758 | CW10: 0.96144737 | CX10: 1.7941032 | CY10: 4.9704307 | CZ10: 1.9809222 | DA10: 61.472662 | DB10: 4.4220009 | DC10: 2.0995557 | DD10: 2.105531 | DE10: 4.2865814 | DF10: 1.1041585 | DG10: 1.3369419 | DH10: 7.1333793 | DI10: 3.1577213 | DJ10: 0 | DK10: 0 | DL10: 0 | DM10: 12.292095 | DN10: 1.9292645 | DO10: 4.9941009 | DP10: 9.6038563 | DQ10: 14.384737 | DR10: 9.6039775 | DS10: 38.703261 | DT10: 11.472887 | DU10: 3.1778757 | DV10: 8.4563175 | DW10: 0 | DX10: 0 | DY10: 0 | DZ10: 0 | EA10: 0 | EB10: 0 | EC10: 0 | ED10: 0 | EE10: 2.6013372 | EF10: 14.219837 | EG10: 118.50012 | EH10: 686.19331 | EI10: 0 | EJ10: 0 | EK10: 0 | EL10: 0 | EM10: 0 | EN10: 0 | EO10: 58.636322 | EP10: 0 | EQ10: 0 | ER10: 81.347843 | ES10: 0 | ET10: 24.063621 | EU10: 110.73158 | EV10: 12.558292 | EW10: 29.423963 | EX10: 26.560042 | EY10: 8.1907426 | EZ10: 0.68179323 | FA10: 3.1771699 | FB10: 0.24579454 | FC10: 0.088671391 | FD10: 0.46695513 | FE10: 0.11670037 | FF10: 0.086005369 | FG10: 0.21169436 | FH10: 0.48802497 | FI10: 0 | FJ10: 0 | FK10: 0 | FL10: 0 | FM10: 0 | FN10: 0 | FO10: 0 | FP10: 0 | FQ10: 0
B11: 3 | C11: 4 | D11: Upstream | E11: Upstream transportation and distribution | F11: =SUMIFS(G11:FQ11,$G$3:$FQ$3,"<>Divested") -> 42362.16 | G11: 0 | H11: 310.16221 | I11: 655.68649 | J11: 25.727806 | K11: 4.3131603 | L11: -4.492455 | M11: 2.3135593 | N11: -34.680132 | O11: 0 | P11: 0 | Q11: 698.99929 | R11: 1024.0096 | S11: 919.13442 | T11: 495.11585 | U11: 356.74271 | V11: 0 | W11: 6.381398 | X11: 0 | Y11: 312.24094 | Z11: 128.1013 | AA11: 595.95237 | AB11: 0 | AC11: 210.58228 | AD11: 117.93328 | AE11: 0 | AF11: 29.197501 | AG11: 52.283798 | AH11: 0 | AI11: 781.97736 | AJ11: 325.65944 | AK11: 24.299283 | AL11: 0 | AM11: 0 | AN11: 0 | AO11: 26.494154 | AP11: 4.2756447 | AQ11: 57.375283 | AR11: 29.7542 | AS11: 0.84610064 | AT11: 7505.0302 | AU11: 5.374463 | AV11: 163.10903 | AW11: 1.7952758 | AX11: 70.966264 | AY11: 67.060233 | AZ11: 0 | BA11: 0 | BB11: 599.92686 | BC11: 0 | BD11: 314.1922 | BE11: 13.217872 | BF11: 0 | BG11: 0 | BH11: 488.38278 | BI11: 0 | BJ11: 0 | BK11: 0 | BL11: 0 | BM11: 0 | BN11: 92.857382 | BO11: 862.01049 | BP11: 240.30315 | BQ11: 410.17295 | BR11: 1442.4818 | BS11: 1081.6585 | BT11: 0 | BU11: 0 | BV11: 0 | BW11: 0 | BX11: 0 | BY11: 0 | BZ11: 0 | CA11: 0 | CB11: 0 | CC11: 0 | CD11: 0 | CE11: 2.660982 | CF11: 0 | CG11: 0 | CH11: 0 | CI11: 27.843504 | CJ11: 120.17037 | CK11: 131.94164 | CL11: 132.30014 | CM11: 21.513712 | CN11: 11.933563 | CO11: 0.59475563 | CP11: 0 | CQ11: 454.88465 | CR11: 46.687422 | CS11: 39.524634 | CT11: 368.56566 | CU11: 42.052086 | CV11: 123.85525 | CW11: 0 | CX11: 17.85585 | CY11: 6.1811631 | CZ11: 0 | DA11: 189.44828 | DB11: 38.777782 | DC11: 37.092905 | DD11: 11.610066 | DE11: 15.79024 | DF11: 46.061834 | DG11: 11.294989 | DH11: 180.27344 | DI11: 0.0048861021 | DJ11: 0 | DK11: 0 | DL11: 0 | DM11: 384.82485 | DN11: 46.670904 | DO11: 10.047165 | DP11: 101.88798 | DQ11: 61.555115 | DR11: 56.475584 | DS11: 307.28678 | DT11: 89.451578 | DU11: 25.733218 | DV11: 127.51085 | DW11: 0 | DX11: 0 | DY11: 0 | DZ11: 0 | EA11: 0 | EB11: 0 | EC11: 0 | ED11: 0 | EE11: 242.75552 | EF11: 163.20459 | EG11: 1460.251 | EH11: 526.45588 | EI11: 0 | EJ11: 0 | EK11: 0 | EL11: 0 | EM11: 0 | EN11: 0 | EO11: 7772.6152 | EP11: 128.73682 | EQ11: 0 | ER11: 7365.65 | ES11: 0 | ET11: 495.35896 | EU11: 1063.276 | EV11: 30.868861 | EW11: 409.14101 | EX11: 103.87532 | EY11: 0 | EZ11: 22.705302 | FA11: 31.523831 | FB11: 6.0802843 | FC11: 1.1777618 | FD11: 0.76183012 | FE11: 0 | FF11: 0 | FG11: 0.031541226 | FH11: 2.9803613 | FI11: 0 | FJ11: 0 | FK11: 0.075878292 | FL11: 0 | FM11: 0 | FN11: 0 | FO11: 0 | FP11: 0 | FQ11: 0
B12: 3 | C12: 5 | D12: Upstream | E12: Waste generated in operations | F12: =SUMIFS(G12:FQ12,$G$3:$FQ$3,"<>Divested") -> 464.9853 | G12: 0 | H12: 0 | I12: 3.4508704 | J12: 4.4824955 | K12: 0 | L12: 15.467046 | M12: 0 | N12: 0 | O12: 0 | P12: 0 | Q12: 7.8447229 | R12: 0 | S12: 5.0385756 | T12: 2.8593702 | U12: 2.7303976 | V12: 0 | W12: 0 | X12: 0 | Y12: 0.11320952 | Z12: 0 | AA12: 12.416314 | AB12: 0 | AC12: 0.26459844 | AD12: 0.24604522 | AE12: 0 | AF12: 0.12152927 | AG12: 0.049330449 | AH12: 0 | AI12: 0.32238446 | AJ12: 0.22164721 | AK12: 0.13897443 | AL12: 0 | AM12: 0 | AN12: 0 | AO12: 0.017822452 | AP12: 0 | AQ12: 0 | AR12: 1.5214145 | AS12: 0 | AT12: 10.107193 | AU12: 0.0010477071 | AV12: 0.026306974 | AW12: 0 | AX12: 0.32486938 | AY12: 0.32643221 | AZ12: 0 | BA12: 0 | BB12: 0.10644228 | BC12: 0 | BD12: 1.3128688 | BE12: 0 | BF12: 0 | BG12: 0 | BH12: 0.39750961 | BI12: 0 | BJ12: 0 | BK12: 0 | BL12: 0 | BM12: 0 | BN12: 0 | BO12: 0 | BP12: 0 | BQ12: 10.822146 | BR12: 1.06743 | BS12: 1.7754919 | BT12: 0.31936625 | BU12: 0 | BV12: 0 | BW12: 0 | BX12: 0 | BY12: 0 | BZ12: 0 | CA12: 0 | CB12: 0 | CC12: 0 | CD12: 0 | CE12: 0.0019334959 | CF12: 0 | CG12: 0 | CH12: 0 | CI12: 0.057152425 | CJ12: 0.056613856 | CK12: 0.169913 | CL12: 0.033929043 | CM12: 0.041825707 | CN12: 0.013310643 | CO12: 0 | CP12: 0 | CQ12: 8.3288128 | CR12: 3.1300502 | CS12: 0.01929448 | CT12: 25.913288 | CU12: 0 | CV12: 2.5076414 | CW12: 0.065888732 | CX12: 0.91374509 | CY12: 0.026630811 | CZ12: 0.025846935 | DA12: 12.223939 | DB12: 0.049777918 | DC12: 0.96112234 | DD12: 0.49198865 | DE12: 0.67220203 | DF12: 0.24218827 | DG12: 0.1772357 | DH12: 0.17987227 | DI12: 0 | DJ12: 0 | DK12: 0 | DL12: 0 | DM12: 0.12679233 | DN12: 0.19166223 | DO12: 0.064579192 | DP12: 0.23243021 | DQ12: 6.6077222 | DR12: 12.331192 | DS12: 26.353075 | DT12: 36.985994 | DU12: 4.2042252 | DV12: 4.0175386 | DW12: 0 | DX12: 0 | DY12: 0 | DZ12: 0 | EA12: 0 | EB12: 0 | EC12: 0 | ED12: 0 | EE12: 0.07192319 | EF12: 4.6773118 | EG12: 0 | EH12: 166.85894 | EI12: 0 | EJ12: 0 | EK12: 0 | EL12: 0 | EM12: 0 | EN12: 0 | EO12: 8.7039737 | EP12: 0 | EQ12: 0 | ER12: 2.9749279 | ES12: 0 | ET12: 3.0125398 | EU12: 32.215255 | EV12: 7.9084667 | EW12: 7.2486967 | EX12: 0 | EY12: 0 | EZ12: 0 | FA12: 0 | FB12: 0 | FC12: 0 | FD12: 0 | FE12: 0 | FF12: 0 | FG12: 0 | FH12: 0 | FI12: 0 | FJ12: 0 | FK12: 0 | FL12: 0 | FM12: 0 | FN12: 0 | FO12: 0 | FP12: 0 | FQ12: 0
B13: 3 | C13: 6 | D13: Upstream | E13: Business travel | F13: =SUMIFS(G13:FQ13,$G$3:$FQ$3,"<>Divested") -> 5708.7733 | G13: 0 | H13: 61.45832 | I13: 284.31562 | J13: 22.765523 | K13: 5.6470046 | L13: 176.59875 | M13: 22.975051 | N13: 20.51563 | O13: 0 | P13: 218.51751 | Q13: 318.48096 | R13: 143.19895 | S13: 102.29783 | T13: 28.37342 | U13: 12.912877 | V13: 0.2436759 | W13: 2.5065199 | X13: 0 | Y13: 146.08288 | Z13: 33.705645 | AA13: 50.557726 | AB13: 0 | AC13: 25.80602 | AD13: 29.048481 | AE13: 0 | AF13: 37.874121 | AG13: 12.490936 | AH13: 0 | AI13: 88.229436 | AJ13: 88.356368 | AK13: 2.784486 | AL13: 0 | AM13: 0 | AN13: 5.1519347 | AO13: 8.2275582 | AP13: 5.793867 | AQ13: 8.8193238 | AR13: 52.647973 | AS13: 0.12164884 | AT13: 73.137592 | AU13: 5.5873942 | AV13: 58.863122 | AW13: 2.9722392 | AX13: 9.9065897 | AY13: 93.123765 | AZ13: 0 | BA13: 4.5151619 | BB13: 19.823158 | BC13: 0 | BD13: 113.44075 | BE13: 6.8663495 | BF13: 43.373071 | BG13: 50.201584 | BH13: 54.208778 | BI13: 0 | BJ13: 0 | BK13: 0 | BL13: 0 | BM13: 0 | BN13: 12.406525 | BO13: 53.817995 | BP13: 6.4146965 | BQ13: 14.111526 | BR13: 20.419233 | BS13: 54.595839 | BT13: 693.04742 | BU13: 0 | BV13: 0 | BW13: 0 | BX13: 0 | BY13: 0 | BZ13: 0 | CA13: 40.967701 | CB13: -191.44489 | CC13: 105.0915 | CD13: 45.385714 | CE13: 10.392583 | CF13: 0.56099875 | CG13: 0 | CH13: 0 | CI13: 37.213292 | CJ13: 15.238986 | CK13: 44.817285 | CL13: 0.62029479 | CM13: 13.354965 | CN13: 7.0842277 | CO13: 0 | CP13: 0 | CQ13: 17.6856 | CR13: 3.0442594 | CS13: 29.499355 | CT13: 31.618235 | CU13: 4.1667444 | CV13: 2.5462052 | CW13: 3.1326889 | CX13: 3.0134933 | CY13: 19.219684 | CZ13: 18.839899 | DA13: 82.632752 | DB13: 7.5503369 | DC13: 2.2278652 | DD13: 3.3804509 | DE13: 0.80341766 | DF13: 0.12920858 | DG13: 1.1668506 | DH13: 5.632987 | DI13: 26.460438 | DJ13: 0 | DK13: 0 | DL13: 0 | DM13: 12.417884 | DN13: 2.5253845 | DO13: 1.9447829 | DP13: 10.034602 | DQ13: 2.1505748 | DR13: 1.8085357 | DS13: 57.383806 | DT13: 4.497537 | DU13: 64.817232 | DV13: 74.125263 | DW13: 0 | DX13: 0 | DY13: 0 | DZ13: 0 | EA13: 0 | EB13: 0 | EC13: 0 | ED13: 0 | EE13: 18.431846 | EF13: 10.959815 | EG13: 116.60011 | EH13: 467.51302 | EI13: 88.799162 | EJ13: 0 | EK13: 0 | EL13: -62.926989 | EM13: 0 | EN13: 62.926989 | EO13: 214.83899 | EP13: 0 | EQ13: 74.370333 | ER13: 277.06895 | ES13: 0 | ET13: 27.351238 | EU13: 381.08996 | EV13: 40.255972 | EW13: 8.3013789 | EX13: 51.275965 | EY13: 0 | EZ13: 0.73777145 | FA13: 2.5413049 | FB13: 0.85254074 | FC13: 0.33426079 | FD13: 0.13165398 | FE13: 3.4782896 | FF13: 3.9353529 | FG13: 4.8023601 | FH13: 13.090518 | FI13: 0 | FJ13: 0 | FK13: 0 | FL13: 0 | FM13: 0 | FN13: 0 | FO13: 0 | FP13: 0 | FQ13: 0
B14: 3 | C14: 7 | D14: Upstream | E14: Employee commuting | F14: =SUMIFS(G14:FQ14,$G$3:$FQ$3,"<>Divested") -> 5166.7426 | G14: 0 | H14: 0 | I14: 174.59779 | J14: 78.014423 | K14: 0 | L14: 193.28576 | M14: 0 | N14: 27.460141 | O14: 0 | P14: 4.3008401 | Q14: 101.78655 | R14: 0 | S14: 141.92772 | T14: 38.358268 | U14: 29.742628 | V14: 0 | W14: 0 | X14: 0 | Y14: 54.206455 | Z14: 8.6016802 | AA14: 48.552465 | AB14: 1.4336134 | AC14: 26.352865 | AD14: 12.812746 | AE14: 0 | AF14: 105.41632 | AG14: 32.73251 | AH14: 0 | AI14: 112.01657 | AJ14: 147.85621 | AK14: 15.769747 | AL14: 0 | AM14: 0 | AN14: 0 | AO14: 4.3008401 | AP14: 7.1680668 | AQ14: 0 | AR14: 15.652986 | AS14: 0 | AT14: 122.75068 | AU14: 3.7826904 | AV14: 26.40315 | AW14: 1.4336134 | AX14: 15.469119 | AY14: 113.9799 | AZ14: 0 | BA14: 4.3008401 | BB14: 46.584278 | BC14: 1.4336134 | BD14: 124.24788 | BE14: 0 | BF14: 0 | BG14: 0 | BH14: 114.02214 | BI14: 0 | BJ14: 0 | BK14: 0 | BL14: 0 | BM14: 0 | BN14: 0 | BO14: 0 | BP14: 0 | BQ14: 0 | BR14: 274.50397 | BS14: 0 | BT14: 22.659109 | BU14: 0 | BV14: 0 | BW14: 0 | BX14: 0 | BY14: 8.6016802 | BZ14: 0 | CA14: 4.3008401 | CB14: 0 | CC14: 2.8672267 | CD14: 1.4336134 | CE14: 7.1680668 | CF14: 0 | CG14: 0 | CH14: 0 | CI14: 46.177289 | CJ14: 15.950305 | CK14: 102.55837 | CL14: 16.476371 | CM14: 29.711603 | CN14: 8.3087398 | CO14: 0 | CP14: 0 | CQ14: 25.64988 | CR14: 21.527043 | CS14: 61.248653 | CT14: 58.58096 | CU14: 8.9560568 | CV14: 8.1542545 | CW14: 11.07054 | CX14: 4.0595881 | CY14: 12.914325 | CZ14: 12.90252 | DA14: 109.32509 | DB14: 9.6092403 | DC14: 2.0895966 | DD14: 5.0193718 | DE14: 16.712882 | DF14: 6.7842954 | DG14: 2.4412803 | DH14: 97.485709 | DI14: 53.52524 | DJ14: 0 | DK14: 0 | DL14: 0 | DM14: 41.733522 | DN14: 11.468907 | DO14: 7.5186715 | DP14: 25.00374 | DQ14: 47.814051 | DR14: 57.141649 | DS14: 137.82209 | DT14: 71.755538 | DU14: 69.624109 | DV14: 0 | DW14: 0 | DX14: 0 | DY14: 0 | DZ14: 0 | EA14: 0 | EB14: 0 | EC14: 0 | ED14: 0 | EE14: 18.36881 | EF14: 28.576462 | EG14: 88.884029 | EH14: 631.70106 | EI14: 7.1680668 | EJ14: 0 | EK14: 1.4336134 | EL14: 0 | EM14: 1.4336134 | EN14: 1.4336134 | EO14: 188.53015 | EP14: 0 | EQ14: 14.336134 | ER14: 329.45145 | ES14: 1.4336134 | ET14: 61.680798 | EU14: 253.89169 | EV14: 7.1680668 | EW14: 35.840334 | EX14: 0 | EY14: 0 | EZ14: 0 | FA14: 0 | FB14: 0 | FC14: 0 | FD14: 0 | FE14: 0 | FF14: 0 | FG14: 0 | FH14: 0 | FI14: 0 | FJ14: 0 | FK14: 0 | FL14: 0 | FM14: 0 | FN14: 0 | FO14: 0 | FP14: 0 | FQ14: 0
B15: 3 | C15: 8 | D15: Upstream | E15: Upstream leased assets | F15: =SUMIFS(G15:FQ15,$G$3:$FQ$3,"<>Divested") -> 2691.9199 | G15: 0 | H15: 15.579784 | I15: 37.041003 | J15: 20.104863 | K15: 16.617856 | L15: 56.47646 | M15: 0.92006558 | N15: 19.299838 | O15: 0 | P15: 2.4231848 | Q15: 0.62604334 | R15: 16.510114 | S15: 17.05158 | T15: 25.162474 | U15: 16.694151 | V15: 2.4963838 | W15: 3.6302117 | X15: 0 | Y15: 22.661346 | Z15: 2.6559738 | AA15: 29.433382 | AB15: 0 | AC15: 43.760759 | AD15: 6.1321246 | AE15: 0 | AF15: 70.209989 | AG15: 10.862142 | AH15: 0 | AI15: 15.474318 | AJ15: 23.13209 | AK15: 6.4202112 | AL15: 0 | AM15: 0 | AN15: 0 | AO15: 4.7816699 | AP15: 12.205496 | AQ15: 0 | AR15: 9.8229237 | AS15: 0 | AT15: 78.205436 | AU15: 4.7145098 | AV15: 20.55978 | AW15: 0 | AX15: 3.2642975 | AY15: 75.397202 | AZ15: 0 | BA15: 1.2228079 | BB15: 11.912137 | BC15: 0 | BD15: 7.7858907 | BE15: 6.7080208 | BF15: 1.8650643 | BG15: 18.308566 | BH15: 57.553183 | BI15: 0 | BJ15: 0 | BK15: 0 | BL15: 0 | BM15: 0 | BN15: 0 | BO15: 36.860248 | BP15: 8.0923277 | BQ15: 28.958743 | BR15: 93.376803 | BS15: 30.63872 | BT15: 68.065713 | BU15: 0 | BV15: 0 | BW15: 0 | BX15: 0 | BY15: 0 | BZ15: 0 | CA15: 0 | CB15: 0 | CC15: 0 | CD15: 0 | CE15: 2.837526 | CF15: 0 | CG15: 0 | CH15: 0 | CI15: 7.7759297 | CJ15: 11.141844 | CK15: 47.626595 | CL15: 6.967562 | CM15: 14.986608 | CN15: 2.5898757 | CO15: 0.7774943 | CP15: 0 | CQ15: 29.228453 | CR15: 9.0806078 | CS15: 11.891795 | CT15: 48.245799 | CU15: 1.4029447 | CV15: 1.4614395 | CW15: 3.6501145 | CX15: 4.2354911 | CY15: 12.107647 | CZ15: 6.6176708 | DA15: 34.097058 | DB15: 6.1061472 | DC15: 3.9527378 | DD15: 2.8706934 | DE15: 6.8979389 | DF15: 2.7956847 | DG15: 1.5985588 | DH15: 0 | DI15: 0.7259291 | DJ15: -6.9022163 | DK15: 0 | DL15: 0 | DM15: 26.212405 | DN15: 2.1659249 | DO15: 7.3975194 | DP15: 21.384302 | DQ15: 9.0291096 | DR15: 5.4094156 | DS15: 26.138062 | DT15: 7.217858 | DU15: 4.2238334 | DV15: 51.814202 | DW15: 0 | DX15: 0 | DY15: 0 | DZ15: 0 | EA15: 0 | EB15: 0 | EC15: 0 | ED15: 0 | EE15: 7.2557332 | EF15: 12.184877 | EG15: 0 | EH15: 694.20952 | EI15: 0 | EJ15: 0 | EK15: 0 | EL15: 0 | EM15: 0 | EN15: 0 | EO15: 147.68417 | EP15: 0 | EQ15: 0 | ER15: 144.7508 | ES15: 0 | ET15: 47.718675 | EU15: 135.0712 | EV15: 21.867947 | EW15: 23.22769 | EX15: 20.500022 | EY15: 0 | EZ15: 2.4758659 | FA15: 4.6657819 | FB15: 0.33210679 | FC15: 0.1675759 | FD15: 0 | FE15: 2.0907898 | FF15: 1.0712125 | FG15: 2.3034076 | FH15: 4.2669994 | FI15: 0 | FJ15: 0 | FK15: 0 | FL15: 0 | FM15: 0 | FN15: 0 | FO15: 0 | FP15: 0 | FQ15: 0
B16: 3 | C16: 9 | D16: Downstream | E16: Downstream transportation and distribution | F16: =SUMIFS(G16:FQ16,$G$3:$FQ$3,"<>Divested") -> 0 | G16: 0 | H16: 0 | I16: 0 | J16: 0 | K16: 0 | L16: 0 | M16: 0 | N16: 0 | O16: 0 | P16: 0 | Q16: 0 | R16: 0 | S16: 0 | T16: 0 | U16: 0 | V16: 0 | W16: 0 | X16: 0 | Y16: 0 | Z16: 0 | AA16: 0 | AB16: 0 | AC16: 0 | AD16: 0 | AE16: 0 | AF16: 0 | AG16: 0 | AH16: 0 | AI16: 0 | AJ16: 0 | AK16: 0 | AL16: 0 | AM16: 0 | AN16: 0 | AO16: 0 | AP16: 0 | AQ16: 0 | AR16: 0 | AS16: 0 | AT16: 0 | AU16: 0 | AV16: 0 | AW16: 0 | AX16: 0 | AY16: 0 | AZ16: 0 | BA16: 0 | BB16: 0 | BC16: 0 | BD16: 0 | BE16: 0 | BF16: 0 | BG16: 0 | BH16: 0 | BI16: 0 | BJ16: 0 | BK16: 0 | BL16: 0 | BM16: 0 | BN16: 0 | BO16: 0 | BP16: 0 | BQ16: 0 | BR16: 0 | BS16: 0 | BT16: 0 | BU16: 0 | BV16: 0 | BW16: 0 | BX16: 0 | BY16: 0 | BZ16: 0 | CA16: 0 | CB16: 0 | CC16: 0 | CD16: 0 | CE16: 0 | CF16: 0 | CG16: 0 | CH16: 0 | CI16: 0 | CJ16: 0 | CK16: 0 | CL16: 0 | CM16: 0 | CN16: 0 | CO16: 0 | CP16: 0 | CQ16: 0 | CR16: 0 | CS16: 0 | CT16: 0 | CU16: 0 | CV16: 0 | CW16: 0 | CX16: 0 | CY16: 0 | CZ16: 0 | DA16: 0 | DB16: 0 | DC16: 0 | DD16: 0 | DE16: 0 | DF16: 0 | DG16: 0 | DH16: 0 | DI16: 0 | DJ16: 0 | DK16: 0 | DL16: 0 | DM16: 0 | DN16: 0 | DO16: 0 | DP16: 0 | DQ16: 0 | DR16: 0 | DS16: 0 | DT16: 0 | DU16: 0 | DV16: 0 | DW16: 0 | DX16: 0 | DY16: 0 | DZ16: 0 | EA16: 0 | EB16: 0 | EC16: 0 | ED16: 0 | EE16: 0 | EF16: 0 | EG16: 0 | EH16: 0 | EI16: 0 | EJ16: 0 | EK16: 0 | EL16: 0 | EM16: 0 | EN16: 0 | EO16: 0 | EP16: 0 | EQ16: 0 | ER16: 0 | ES16: 0 | ET16: 0 | EU16: 0 | EV16: 0 | EW16: 0 | EX16: 0 | EY16: 0 | EZ16: 0 | FA16: 0 | FB16: 0 | FC16: 0 | FD16: 0 | FE16: 0 | FF16: 0 | FG16: 0 | FH16: 0 | FI16: 0 | FJ16: 0 | FK16: 0 | FL16: 0 | FM16: 0 | FN16: 0 | FO16: 0 | FP16: 0 | FQ16: 0
B17: 3 | C17: 10 | D17: Downstream | E17: Processing of sold products | F17: =SUMIFS(G17:FQ17,$G$3:$FQ$3,"<>Divested") -> 0 | G17: 0 | H17: 0 | I17: 0 | J17: 0 | K17: 0 | L17: 0 | M17: 0 | N17: 0 | O17: 0 | P17: 0 | Q17: 0 | R17: 0 | S17: 0 | T17: 0 | U17: 0 | V17: 0 | W17: 0 | X17: 0 | Y17: 0 | Z17: 0 | AA17: 0 | AB17: 0 | AC17: 0 | AD17: 0 | AE17: 0 | AF17: 0 | AG17: 0 | AH17: 0 | AI17: 0 | AJ17: 0 | AK17: 0 | AL17: 0 | AM17: 0 | AN17: 0 | AO17: 0 | AP17: 0 | AQ17: 0 | AR17: 0 | AS17: 0 | AT17: 0 | AU17: 0 | AV17: 0 | AW17: 0 | AX17: 0 | AY17: 0 | AZ17: 0 | BA17: 0 | BB17: 0 | BC17: 0 | BD17: 0 | BE17: 0 | BF17: 0 | BG17: 0 | BH17: 0 | BI17: 0 | BJ17: 0 | BK17: 0 | BL17: 0 | BM17: 0 | BN17: 0 | BO17: 0 | BP17: 0 | BQ17: 0 | BR17: 0 | BS17: 0 | BT17: 0 | BU17: 0 | BV17: 0 | BW17: 0 | BX17: 0 | BY17: 0 | BZ17: 0 | CA17: 0 | CB17: 0 | CC17: 0 | CD17: 0 | CE17: 0 | CF17: 0 | CG17: 0 | CH17: 0 | CI17: 0 | CJ17: 0 | CK17: 0 | CL17: 0 | CM17: 0 | CN17: 0 | CO17: 0 | CP17: 0 | CQ17: 0 | CR17: 0 | CS17: 0 | CT17: 0 | CU17: 0 | CV17: 0 | CW17: 0 | CX17: 0 | CY17: 0 | CZ17: 0 | DA17: 0 | DB17: 0 | DC17: 0 | DD17: 0 | DE17: 0 | DF17: 0 | DG17: 0 | DH17: 0 | DI17: 0 | DJ17: 0 | DK17: 0 | DL17: 0 | DM17: 0 | DN17: 0 | DO17: 0 | DP17: 0 | DQ17: 0 | DR17: 0 | DS17: 0 | DT17: 0 | DU17: 0 | DV17: 0 | DW17: 0 | DX17: 0 | DY17: 0 | DZ17: 0 | EA17: 0 | EB17: 0 | EC17: 0 | ED17: 0 | EE17: 0 | EF17: 0 | EG17: 0 | EH17: 0 | EI17: 0 | EJ17: 0 | EK17: 0 | EL17: 0 | EM17: 0 | EN17: 0 | EO17: 0 | EP17: 0 | EQ17: 0 | ER17: 0 | ES17: 0 | ET17: 0 | EU17: 0 | EV17: 0 | EW17: 0 | EX17: 0 | EY17: 0 | EZ17: 0 | FA17: 0 | FB17: 0 | FC17: 0 | FD17: 0 | FE17: 0 | FF17: 0 | FG17: 0 | FH17: 0 | FI17: 0 | FJ17: 0 | FK17: 0 | FL17: 0 | FM17: 0 | FN17: 0 | FO17: 0 | FP17: 0 | FQ17: 0
B18: 3 | C18: 11 | D18: Downstream | E18: Use of sold products | F18: =SUMIFS(G18:FQ18,$G$3:$FQ$3,"<>Divested") -> 1722.23 | G18: 0 | H18: 0 | I18: 836.84893 | J18: 0 | K18: 0 | L18: 0 | M18: 0 | N18: 0 | O18: 0 | P18: 0 | Q18: 474.82489 | R18: 0 | S18: 0 | T18: 0 | U18: 0 | V18: 0 | W18: 0 | X18: 0 | Y18: 0 | Z18: 0 | AA18: 0 | AB18: 0 | AC18: 0 | AD18: 0 | AE18: 0 | AF18: 0 | AG18: 0 | AH18: 0 | AI18: 0 | AJ18: 0 | AK18: 0 | AL18: 0 | AM18: 0 | AN18: 0 | AO18: 0 | AP18: 0 | AQ18: 0 | AR18: 410.55622 | AS18: 0 | AT18: 0 | AU18: 0 | AV18: 0 | AW18: 0 | AX18: 0 | AY18: 0 | AZ18: 0 | BA18: 0 | BB18: 0 | BC18: 0 | BD18: 0 | BE18: 0 | BF18: 0 | BG18: 0 | BH18: 0 | BI18: 0 | BJ18: 0 | BK18: 0 | BL18: 0 | BM18: 0 | BN18: 0 | BO18: 0 | BP18: 0 | BQ18: 0 | BR18: 0 | BS18: 0 | BT18: 0 | BU18: 0 | BV18: 0 | BW18: 0 | BX18: 0 | BY18: 0 | BZ18: 0 | CA18: 0 | CB18: 0 | CC18: 0 | CD18: 0 | CE18: 0 | CF18: 0 | CG18: 0 | CH18: 0 | CI18: 0 | CJ18: 0 | CK18: 0 | CL18: 0 | CM18: 0 | CN18: 0 | CO18: 0 | CP18: 0 | CQ18: 0 | CR18: 0 | CS18: 0 | CT18: 0 | CU18: 0 | CV18: 0 | CW18: 0 | CX18: 0 | CY18: 0 | CZ18: 0 | DA18: 0 | DB18: 0 | DC18: 0 | DD18: 0 | DE18: 0 | DF18: 0 | DG18: 0 | DH18: 0 | DI18: 0 | DJ18: 0 | DK18: 0 | DL18: 0 | DM18: 0 | DN18: 0 | DO18: 0 | DP18: 0 | DQ18: 0 | DR18: 0 | DS18: 0 | DT18: 0 | DU18: 0 | DV18: 0 | DW18: 0 | DX18: 0 | DY18: 0 | DZ18: 0 | EA18: 0 | EB18: 0 | EC18: 0 | ED18: 0 | EE18: 0 | EF18: 0 | EG18: 0 | EH18: 0 | EI18: 0 | EJ18: 0 | EK18: 0 | EL18: 0 | EM18: 0 | EN18: 0 | EO18: 0 | EP18: 0 | EQ18: 0 | ER18: 0 | ES18: 0 | ET18: 0 | EU18: 0 | EV18: 0 | EW18: 0 | EX18: 0 | EY18: 0 | EZ18: 0 | FA18: 0 | FB18: 0 | FC18: 0 | FD18: 0 | FE18: 0 | FF18: 0 | FG18: 0 | FH18: 0 | FI18: 0 | FJ18: 0 | FK18: 0 | FL18: 0 | FM18: 0 | FN18: 0 | FO18: 0 | FP18: 0 | FQ18: 0
B19: 3 | C19: 12 | D19: Downstream | E19: End of life treatment of sold products | F19: =SUMIFS(G19:FQ19,$G$3:$FQ$3,"<>Divested") -> 95.631573 | G19: 0 | H19: 0.83790072 | I19: 1.5869819 | J19: 0 | K19: 0 | L19: 0.61630432 | M19: 0.048941416 | N19: 0.24424699 | O19: 0 | P19: 0 | Q19: 1.9779131 | R19: 1.3663524 | S19: 1.2812997 | T19: 0.93397644 | U19: 0.38628279 | V19: 0 | W19: 0.039605276 | X19: 0 | Y19: 1.5986995 | Z19: 0.19269702 | AA19: 0.81764497 | AB19: 0 | AC19: 0.98458953 | AD19: 0.479072 | AE19: 0 | AF19: 2.80601 | AG19: 0.13599854 | AH19: 0 | AI19: 1.2753503 | AJ19: 0 | AK19: 0.049568433 | AL19: 0 | AM19: 0 | AN19: 0 | AO19: 0.15534185 | AP19: 0 | AQ19: 0.3181236 | AR19: 0.036698319 | AS19: 0.0028604043 | AT19: 5.8172167 | AU19: 0 | AV19: 0 | AW19: 0 | AX19: 0.18256687 | AY19: 1.0597875 | AZ19: 0 | BA19: 0 | BB19: 1.1507923 | BC19: 0 | BD19: 1.3162848 | BE19: 0.054345621 | BF19: 0 | BG19: 0 | BH19: 2.78398 | BI19: 0 | BJ19: 0 | BK19: 0 | BL19: 0 | BM19: 0 | BN19: 0.55570299 | BO19: 1.8569654 | BP19: 1.0394679 | BQ19: 2.1090643 | BR19: 2.2492553 | BS19: 1.7097145 | BT19: 0 | BU19: 0 | BV19: 0 | BW19: 0 | BX19: 0 | BY19: 0 | BZ19: 0 | CA19: 0 | CB19: 0 | CC19: 0 | CD19: 0 | CE19: 0 | CF19: 0 | CG19: 0 | CH19: 0 | CI19: 0 | CJ19: 0 | CK19: 0 | CL19: 0 | CM19: 0 | CN19: 0 | CO19: 0 | CP19: 0 | CQ19: 0 | CR19: 0 | CS19: 0 | CT19: 0 | CU19: 0 | CV19: 0 | CW19: 0 | CX19: 0.033885104 | CY19: 0 | CZ19: 0 | DA19: 0 | DB19: 0 | DC19: 0 | DD19: 0 | DE19: 0 | DF19: 0 | DG19: 0.016647696 | DH19: 0.46907264 | DI19: 3.0324926e-05 | DJ19: 0 | DK19: 0 | DL19: 0 | DM19: 0 | DN19: 0 | DO19: 0.022850046 | DP19: 0.39995567 | DQ19: 0 | DR19: 0 | DS19: 0 | DT19: 0 | DU19: 0.1536621 | DV19: 0.46191015 | DW19: 0 | DX19: 0 | DY19: 0 | DZ19: 0 | EA19: 0 | EB19: 0 | EC19: 0 | ED19: 0 | EE19: 0.15398481 | EF19: 0 | EG19: 0 | EH19: 36.314328 | EI19: 0 | EJ19: 0 | EK19: 0 | EL19: 0 | EM19: 0 | EN19: 0 | EO19: 1.2910007 | EP19: 0.076274909 | EQ19: 0 | ER19: 15.707839 | ES19: 0 | ET19: 1.9496112 | EU19: 1.4193494 | EV19: 0 | EW19: 0 | EX19: 0.21489335 | EY19: 0 | EZ19: 0.0049615205 | FA19: 0.12461294 | FB19: 0.02594645 | FC19: 0.007309618 | FD19: 0 | FE19: 0 | FF19: 0 | FG19: 0 | FH19: 0.0076471615 | FI19: 0 | FJ19: 0 | FK19: 0 | FL19: 0 | FM19: 0 | FN19: 0 | FO19: 0 | FP19: 0 | FQ19: 0
... B22: 3 | C22: 15 | D22: Downstream | E22: Investments | F22: =SUMIFS(G22:FQ22,$G$3:$FQ$3,"<>Divested") -> 0 | G22: 0 | H22: 0 | I22: 0 | J22: 0 | K22: 0 | L22: 0 | M22: 0 | N22: 0 | O22: 0 | P22: 0 | Q22: 0 | R22: 0 | S22: 0 | T22: 0 | U22: 0 | V22: 0 | W22: 0 | X22: 0 | Y22: 0 | Z22: 0 | AA22: 0 | AB22: 0 | AC22: 0 | AD22: 0 | AE22: 0 | AF22: 0 | AG22: 0 | AH22: 0 | AI22: 0 | AJ22: 0 | AK22: 0 | AL22: 0 | AM22: 0 | AN22: 0 | AO22: 0 | AP22: 0 | AQ22: 0 | AR22: 0 | AS22: 0 | AT22: 0 | AU22: 0 | AV22: 0 | AW22: 0 | AX22: 0 | AY22: 0 | AZ22: 0 | BA22: 0 | BB22: 0 | BC22: 0 | BD22: 0 | BE22: 0 | BF22: 0 | BG22: 0 | BH22: 0 | BI22: 0 | BJ22: 0 | BK22: 0 | BL22: 0 | BM22: 0 | BN22: 0 | BO22: 0 | BP22: 0 | BQ22: 0 | BR22: 0 | BS22: 0 | BT22: 0 | BU22: 0 | BV22: 0 | BW22: 0 | BX22: 0 | BY22: 0 | BZ22: 0 | CA22: 0 | CB22: 0 | CC22: 0 | CD22: 0 | CE22: 0 | CF22: 0 | CG22: 0 | CH22: 0 | CI22: 0 | CJ22: 0 | CK22: 0 | CL22: 0 | CM22: 0 | CN22: 0 | CO22: 0 | CP22: 0 | CQ22: 0 | CR22: 0 | CS22: 0 | CT22: 0 | CU22: 0 | CV22: 0 | CW22: 0 | CX22: 0 | CY22: 0 | CZ22: 0 | DA22: 0 | DB22: 0 | DC22: 0 | DD22: 0 | DE22: 0 | DF22: 0 | DG22: 0 | DH22: 0 | DI22: 0 | DJ22: 0 | DK22: 0 | DL22: 0 | DM22: 0 | DN22: 0 | DO22: 0 | DP22: 0 | DQ22: 0 | DR22: 0 | DS22: 0 | DT22: 0 | DU22: 0 | DV22: 0 | DW22: 0 | DX22: 0 | DY22: 0 | DZ22: 0 | EA22: 0 | EB22: 0 | EC22: 0 | ED22: 0 | EE22: 0 | EF22: 0 | EG22: 0 | EH22: 0 | EI22: 0 | EJ22: 0 | EK22: 0 | EL22: 0 | EM22: 0 | EN22: 0 | EO22: 0 | EP22: 0 | EQ22: 0 | ER22: 0 | ES22: 0 | ET22: 0 | EU22: 0 | EV22: 0 | EW22: 0 | EX22: 0 | EY22: 0 | EZ22: 0 | FA22: 0 | FB22: 0 | FC22: 0 | FD22: 0 | FE22: 0 | FF22: 0 | FG22: 0 | FH22: 0 | FI22: 0 | FJ22: 0 | FK22: 0 | FL22: 0 | FM22: 0 | FN22: 0 | FO22: 0 | FP22: 0 | FQ22: 0
E23: Total LB | F23: =SUMIFS(G23:FQ23,$G$3:$FQ$3,"<>Divested") -> 229684.69 | G23: =SUM(G7:G22,G5) -> 3.2269331 | H23: =SUM(H7:H22,H5) -> 3061.2889 | I23: =SUM(I7:I22,I5) -> 9661.6645 | J23: =SUM(J7:J22,J5) -> 1181.3376 | K23: =SUM(K7:K22,K5) -> 93.400094 | L23: =SUM(L7:L22,L5) -> 2533.9493 | M23: =SUM(M7:M22,M5) -> 72.324608 | N23: =SUM(N7:N22,N5) -> 1180.4129 | ... FQ23: =SUM(FQ7:FQ22,FQ5) -> 0.0024447463
E24: Total MB | F24: =SUMIFS(G24:FQ24,$G$3:$FQ$3,"<>Divested") -> 229915.94 | G24: =SUM(G8:G22,G5:G6) -> 3.2269331 | H24: =SUM(H8:H22,H5:H6) -> 3061.1989 | I24: =SUM(I8:I22,I5:I6) -> 9660.738 | J24: =SUM(J8:J22,J5:J6) -> 1163.516 | K24: =SUM(K8:K22,K5:K6) -> 93.384288 | L24: =SUM(L8:L22,L5:L6) -> 2533.5464 | M24: =SUM(M8:M22,M5:M6) -> 72.293223 | N24: =SUM(N8:N22,N5:N6) -> 1179.6349 | ... FQ24: =SUM(FQ8:FQ22,FQ5:FQ6) -> 0.0024447463
B26: FY22 Summary (excl. Divestments)
B28: Scope | C28: Category | D28: Upstream/Downstream | E28: Emission Source | F28: tCO2e Market | G28: tCO2e Location | I28: Extrapolated sites
B29: 1 | C29: - | D29: Internal | E29: Stationary combustion | F29: 1408.5867 | G29: 1408.5867 | I29: R2210 | J29: R1220 | K29: S7030 | L29: R1190 | M29: R4100 | N29: S1040
B30: 1 | C30: - | D30: Internal | E30: Company vehicles | F30: 825.72832 | G30: 825.72832 | I30: R2220 | J30: R2130 | K30: L5010 | L30: R1210 | M30: R4110
B31: 1 | C31: - | D31: Internal | E31: Fugitive emissions | F31: 0 | G31: 0 | I31: R4150 | J31: R2180 | K31: S7020 | L31: R1230 | M31: R4120
B32: 1 | C32: - | D32: Internal | E32: Refrigerants | F32: 1.6471 | G32: 1.6471 | I32: R4160 | J32: R2190 | K32: L2700 | L32: R1240 | M32: R4130
B33: 1 | C33: - | D33: Internal | E33: Extrapolated tCo2e | F33: 1333.8499 | G33: 1333.8499 | I33: C5510 | J33: R5100 | K33: L5020 | L33: R2100 | M33: R4140
B34: 2 | C34: - | D34: Internal | E34: Electricity usage | F34: 4520.5869 | G34: 4279.6023 | I34: L7010 | J34: C1510 | K34: R1100 | L34: R2110 | M34: S3010
B35: 2 | C35: - | D35: Internal | E35: Heating | F35: 0 | G35: 0 | I35: S1030 | J35: C1520 | K35: R1120 | L35: R2120 | M35: S3030
B36: 2 | C36: - | D36: Internal | E36: Cooling | F36: 0 | G36: 0 | I36: L7030 | J36: C1530 | K36: R1140 | L36: R2150 | M36: R3100
B37: 2 | C37: - | D37: Internal | E37: Extrapolated tCo2e | F37: 1329.2162 | G37: 1338.9516 | I37: S1010 | J37: S1020 | K37: R1170 | L37: R2160 | M37: C5520
B38: 3 | C38: 1 | D38: Upstream | E38: Purchased goods and services | F38: 154151.64 | G38: 154151.64 | I38: L7020 | J38: S8030 | K38: R1180 | L38: R2170 | M38: C1040
B39: 3 | C39: 2 | D39: Upstream | E39: Capital goods | F39: 5971.4072 | G39: 5971.4072
B40: 3 | C40: 3 | D40: Upstream | E40: Fuel and energy related activities | F40: 2160.8372 | G40: 2160.8372 | I40: Divested sites
B41: 3 | C41: 4 | D41: Upstream | E41: Upstream transportation and distribution | F41: 42362.16 | G41: 42362.16 | I41: C5010 | J41: S5050
B42: 3 | C42: 5 | D42: Upstream | E42: Waste generated in operations | F42: 464.9853 | G42: 464.9853 | I42: C6020 | J42: S5070
B43: 3 | C43: 6 | D43: Upstream | E43: Business travel | F43: 5708.7733 | G43: 5708.7733 | I43: L4010 | J43: L4040
B44: 3 | C44: 7 | D44: Upstream | E44: Employee commuting | F44: 5166.7426 | G44: 5166.7426 | I44: S5010 | J44: S5040
B45: 3 | C45: 8 | D45: Upstream | E45: Upstream leased assets | F45: 2691.9199 | G45: 2691.9199 | I45: S5020 | J45: S5080
B46: 3 | C46: 9 | D46: Downstream | E46: Downstream transportation and distribution | F46: 0 | G46: 0
B47: 3 | C47: 10 | D47: Downstream | E47: Processing of sold products | F47: 0 | G47: 0
B48: 3 | C48: 11 | D48: Downstream | E48: Use of sold products | F48: 1722.23 | G48: 1722.23
B49: 3 | C49: 12 | D49: Downstream | E49: End of life treatment of sold products | F49: 95.631573 | G49: 95.631573
B50: 3 | C50: 13 | D50: Downstream | E50: Downstream leased assets | F50: 0 | G50: 0
B51: 3 | C51: 14 | D51: Downstream | E51: Franchises | F51: 0 | G51: 0
B52: 3 | C52: 15 | D52: Downstream | E52: Investments | F52: 0 | G52: 0
B53: Total | F53: =SUM(F29:F52) -> 229915.94 | G53: =SUM(G29:G52) -> 229684.69
